Workbook

Sheet Leeme
A1: Malla SALVIA Etapa 2 | B1: Actualizada el 28 de octubre de 2026 (horas de gerencia de octubre en Bolsa 2 y plan de cierre a diciembre). Versión anterior: 27 de octubre de 2026.
A2: Hitos | B2: Los hitos de producto siguen los módulos del Anexo Técnico: M1 Seguimiento, M2 Tamizaje de feminicidio, M3 Medidas de Emergencia (nuevo), M4 LGBTIQ+, M5 ASP y la app móvil. Los hitos transversales H06 a H11 no cambian. La hoja Hitos trae el ID anterior de cada uno.
A3: Entendimiento | B3: Se agregaron a la EDT los grupos 4.4 (Reporte y Registro) y 4.5 (Medidas de Emergencia), más las filas de construcción 6.1.8 a 6.1.10 y de pruebas 7.1.7. Reporte y Registro cruza con M2, M4 y M5 porque sus preguntas de identificación de la víctima cubren tamizaje, LGBTIQ+ y ASP. Actas separa el avance de cada hito en entendimiento (obligaciones 1 a 4) y construcción y cierre (obligaciones 5 a 13).
A4: Qué se edita | B4: Solo la columna Avance_% de las actividades de tercer nivel en la hoja Plan (celdas amarillas) y los textos de la hoja Actas. Todo lo demás se calcula.
A5: Estados | B5: Pendiente = 0 %. En curso = entre 1 % y 99 %. Completado = 100 %. Las filas de primer y segundo nivel promedian sus actividades.
A6: Matriz | B6: Ya no es 0/1: muestra 0 si la actividad no pertenece al hito, 1 pendiente, 2 en curso, 3 completado. La pertenencia original está en la hoja Pertenencia.
A7: Avance del hito | B7: Promedio del avance de las actividades de tercer nivel que pertenecen al hito. Reemplaza los porcentajes puestos a mano en julio, que se conservan en la columna Avance_julio de Actas; por el cambio de método no son comparables uno a uno.
A8: Avance EDT | B8: Promedio de las 103 actividades de tercer nivel. El generador lo calcula y lo escribe en el encabezado del tablero.
A9: Evidencia y confianza | B9: Cada actividad cita su soporte. Alta: consta en documentos revisados. Media: inferido de ellos. Por confirmar: sin soporte en lo revisado.
A10: Fuentes | B10: Solicitud de prórroga (22-sep), informe de alcance y riesgos (17-sep), mapa mental de agosto, Anexo Técnico, historias de usuario de Medidas de Emergencia v1.0, guía del mockup de Reporte y Registro (27-sep), bitácora de ajustes (1-oct), Sprints 15 a 19, commits de septiembre y fichas de julio.
A11: Antes de generar | B11: Abrir y guardar este archivo en Excel si se cambió algún avance, para que las fórmulas queden calculadas; luego correr generador_registry.py.
A12: Navegación mensual | B12: El tablero muestra cada mes de febrero a septiembre y el corte del 6-oct. La hoja Meses trae las horas oficiales por bolsa y los aspectos relevantes de cada resumen; Fichas_Mes, el texto de cada hito por mes (tomado de los resúmenes mensuales). El corte de octubre usa los textos de Actas.
... A24: Riesgos_QA | B24: Hallazgos de QA con fecha de detección y de cierre. El dashboard marca con ⚠ un hito cuando, al corte del mes seleccionado, tiene hallazgos con Critico = Sí (severidad Crítica o Alta) abiertos: detectados antes del corte y sin cerrar, o cerrados después del corte. Los cerrados sin fecha en la matriz toman la fecha de la revisión Kreivo (8-oct-2026). Celdas amarillas editables.

Sheet Plan
A1: ID | B1: Actividad | C1: ENTREGABLE | D1: Nivel | E1: Avance_% | F1: Estado | G1: Evidencia al 28-oct-2026 | H1: Confianza | I1: Codigo_Estado | J1: Fase
A2: 1 | B2: OBL-01: APROBACION EQUIPO DE TRABAJO | C2: Hojas de vida, soportes academicos y certificados de proyectos aprobados por el Ministerio | D2: 1 | E2: =SUMPRODUCT((D3:D5=3)*E3:E5)/COUNTIF(D3:D5,3) -> 1 | F2: =IF(E2>=0.995,"Completado",IF(E2>0,"En curso","Pendiente")) -> Completado | I2: =IF(E2>=0.995,3,IF(E2>0,2,1)) -> 3 | J2: Entendimiento
A3: 1.1 | B3: Conformacion y validacion del equipo (Bolsa 1) | C3: Equipo Bolsa 1 conformado y aprobado | D3: 2 | E3: =SUMPRODUCT((D4:D5=3)*E4:E5)/COUNTIF(D4:D5,3) -> 1 | F3: =IF(E3>=0.995,"Completado",IF(E3>0,"En curso","Pendiente")) -> Completado | I3: =IF(E3>=0.995,3,IF(E3>0,2,1)) -> 3 | J3: Entendimiento
A4: 1.1.1 | B4: Entrega de hojas de vida y soportes del equipo | C4: HV, soportes academicos y certificados entregados | D4: 3 | E4: 1 | F4: =IF(E4>=0.995,"Completado",IF(E4>0,"En curso","Pendiente")) -> Completado | G4: El equipo opera desde febrero; sin acta de aprobación en los documentos revisados | H4: Media | I4: =IF(E4>=0.995,3,IF(E4>0,2,1)) -> 3 | J4: Entendimiento
A5: 1.1.2 | B5: Reunion de inicio y presentacion del proyecto | C5: Acta de reunion de inicio | D5: 3 | E5: 1 | F5: =IF(E5>=0.995,"Completado",IF(E5>0,"En curso","Pendiente")) -> Completado | G5: Acta de inicio del 26-ene-2026, citada en la solicitud de prórroga | H5: Alta | I5: =IF(E5>=0.995,3,IF(E5>0,2,1)) -> 3 | J5: Entendimiento
A6: 2 | B6: OBL-02: PLAN DE GESTION DEL PROYECTO | C6: Plan de gestion, cronograma, plan de comunicaciones, gestion del cambio, plan de QA y matriz de riesgos | D6: 1 | E6: =SUMPRODUCT((D7:D15=3)*E7:E15)/COUNTIF(D7:D15,3) -> 0.77142857 | F6: =IF(E6>=0.995,"Completado",IF(E6>0,"En curso","Pendiente")) -> En curso | I6: =IF(E6>=0.995,3,IF(E6>0,2,1)) -> 2 | J6: Entendimiento
A7: 2.1 | B7: Gestion integral del proyecto SALVIA Web (Bolsa 1) | C7: Artefactos de gestion de la Bolsa 1 aprobados | D7: 2 | E7: =SUMPRODUCT((D8:D11=3)*E8:E11)/COUNTIF(D8:D11,3) -> 0.85 | F7: =IF(E7>=0.995,"Completado",IF(E7>0,"En curso","Pendiente")) -> En curso | I7: =IF(E7>=0.995,3,IF(E7>0,2,1)) -> 2 | J7: Entendimiento
A8: 2.1.1 | B8: Presentacion, aprobacion y uso del Mockup Kreivo-SALVIA | C8: Mockup v2.4-v3.4 aprobado por el Ministerio | D8: 3 | E8: 1 | F8: =IF(E8>=0.995,"Completado",IF(E8>0,"En curso","Pendiente")) -> Completado | G8: Ficha de julio: mockups v2.4 a v3.4 validados | H8: Media | I8: =IF(E8>=0.995,3,IF(E8>0,2,1)) -> 3 | J8: Entendimiento
A9: 2.1.2 | B9: Firma de Acta de Alcance y SLA | C9: Acta de alcance y SLA firmada | D9: 3 | E9: 0.9 | F9: =IF(E9>=0.995,"Completado",IF(E9>0,"En curso","Pendiente")) -> En curso | G9: Prórroga del contrato otorgada hasta el 31-dic-2026; queda pendiente el acta formal del nuevo alcance | H9: Media | I9: =IF(E9>=0.995,3,IF(E9>0,2,1)) -> 2 | J9: Entendimiento
A10: 2.1.3 | B10: Levantamiento: Modulo Web ASP - Variables de Riesgo | C10: Documento de variables de riesgo ASP | D10: 3 | E10: 0.5 | F10: =IF(E10>=0.995,"Completado",IF(E10>0,"En curso","Pendiente")) -> En curso | G10: Variables de riesgo documentadas en julio. Lineamientos, mockups y criterios de la Dirección ASP no recibidos | H10: Media | I10: =IF(E10>=0.995,3,IF(E10>0,2,1)) -> 2 | J10: Entendimiento
A11: 2.1.4 | B11: Gantt y plan de trabajo Kreivo-SALVIA | C11: Cronograma Gantt aprobado | D11: 3 | E11: 1 | F11: =IF(E11>=0.995,"Completado",IF(E11>0,"En curso","Pendiente")) -> Completado | G11: Gantt aprobado en julio y ajustado a la prórroga hasta el 31-dic: plan de cierre de 8 semanas con 12 líneas, responsables y semanas (hoja Plan_Cierre, 28-oct) | H11: Alta | I11: =IF(E11>=0.995,3,IF(E11>0,2,1)) -> 3 | J11: Entendimiento
A12: 2.2 | B12: Gestion integral del proyecto App MASP (Bolsa 2) | C12: Artefactos de gestion de la Bolsa 2 aprobados | D12: 2 | E12: =SUMPRODUCT((D13:D15=3)*E13:E15)/COUNTIF(D13:D15,3) -> 0.66666667 | F12: =IF(E12>=0.995,"Completado",IF(E12>0,"En curso","Pendiente")) -> En curso | I12: =IF(E12>=0.995,3,IF(E12>0,2,1)) -> 2 | J12: Entendimiento
A13: 2.2.1 | B13: App MASP: diseno de interfaz segura | C13: Documento de UX/UI de interfaz segura | D13: 3 | E13: 1 | F13: =IF(E13>=0.995,"Completado",IF(E13>0,"En curso","Pendiente")) -> Completado | G13: Rediseño de la app entregado el 16-sep | H13: Media | I13: =IF(E13>=0.995,3,IF(E13>0,2,1)) -> 3 | J13: Entendimiento
A14: 2.2.2 | B14: App MASP: diseno de alertas y Push Notifications | C14: Especificacion de alertas y notificaciones push | D14: 3 | E14: 0.75 | F14: =IF(E14>=0.995,"Completado",IF(E14>0,"En curso","Pendiente")) -> En curso | G14: Informe 17-sep: Seguridad y SOS completado; sincronización y bitácora en desarrollo | H14: Media | I14: =IF(E14>=0.995,3,IF(E14>0,2,1)) -> 2 | J14: Entendimiento
A15: 2.2.3 | B15: App MASP: integracion con core SALVIA | C15: Especificacion de integracion API App-Core | D15: 3 | E15: 0.25 | F15: =IF(E15>=0.995,"Completado",IF(E15>0,"En curso","Pendiente")) -> En curso | G15: Integración app-web prevista para octubre; el desarrollo integral de ASP no es viable en la prórroga | H15: Alta | I15: =IF(E15>=0.995,3,IF(E15>0,2,1)) -> 2 | J15: Entendimiento
A16: 3 | B16: OBL-03: METODOLOGIA DE DESARROLLO DE SOFTWARE | C16: Documento metodologico (Planificacion, Diseno, QA, Lanzamiento, Mantenimiento) | D16: 1 | E16: =SUMPRODUCT((D17:D23=3)*E17:E23)/COUNTIF(D17:D23,3) -> 0.81 | F16: =IF(E16>=0.995,"Completado",IF(E16>0,"En curso","Pendiente")) -> En curso | I16: =IF(E16>=0.995,3,IF(E16>0,2,1)) -> 2 | J16: Entendimiento
A17: 3.1 | B17: Metodologia de desarrollo - SALVIA Web (Bolsa 1) | C17: Metodologia documentada y aprobada para modulos web | D17: 2 | E17: =SUMPRODUCT((D18:D20=3)*E18:E20)/COUNTIF(D18:D20,3) -> 0.85 | F17: =IF(E17>=0.995,"Completado",IF(E17>0,"En curso","Pendiente")) -> En curso | I17: =IF(E17>=0.995,3,IF(E17>0,2,1)) -> 2 | J17: Entendimiento
A18: 3.1.1 | B18: Diseno y logica: Landing Page, Login y Captcha | C18: Pantallas y logica aprobadas | D18: 3 | E18: 1 | F18: =IF(E18>=0.995,"Completado",IF(E18>0,"En curso","Pendiente")) -> Completado | G18: En producción. Hay un rediseño del login en rama de diseño, sin integrar | H18: Alta | I18: =IF(E18>=0.995,3,IF(E18>0,2,1)) -> 3 | J18: Entendimiento
A19: 3.1.2 | B19: Logica y arbol de decision: Modulo de Tamizaje (escala severidad) | C19: Arbol de decision aprobado | D19: 3 | E19: 0.65 | F19: =IF(E19>=0.995,"Completado",IF(E19>0,"En curso","Pendiente")) -> En curso | G19: Clasificación alto/bajo y tiempos por riesgo operan; el árbol de tamizaje ya se calcula desde el Registro V3 en testing (casos TZ del plan de QA). Falta calibrar rangos con el Ministerio | H19: Alta | I19: =IF(E19>=0.995,3,IF(E19>0,2,1)) -> 2 | J19: Entendimiento
A20: 3.1.3 | B20: Refinamiento UX: Dashboard y trazabilidad de casos | C20: UX final de dashboard y trazabilidad | D20: 3 | E20: 0.9 | F20: =IF(E20>=0.995,"Completado",IF(E20>0,"En curso","Pendiente")) -> En curso | G20: Corte 13-oct más, en testing: estados de caso que la lista mostraba como Desconocido, con filtro por estado (4f9b633), y casos registrados que quedan con estado (1dee9b9) | H20: Alta | I20: =IF(E20>=0.995,3,IF(E20>0,2,1)) -> 2 | J20: Entendimiento
A21: 3.2 | B21: Metodologia de desarrollo - App MASP (Bolsa 2) | C21: Metodologia documentada y aprobada para app movil | D21: 2 | E21: =SUMPRODUCT((D22:D23=3)*E22:E23)/COUNTIF(D22:D23,3) -> 0.75 | F21: =IF(E21>=0.995,"Completado",IF(E21>0,"En curso","Pendiente")) -> En curso | I21: =IF(E21>=0.995,3,IF(E21>0,2,1)) -> 2 | J21: Entendimiento
A22: 3.2.1 | B22: Diseno de flujos y UI: App Movil MASP | C22: Flujos y UI aprobados | D22: 3 | E22: 1 | F22: =IF(E22>=0.995,"Completado",IF(E22>0,"En curso","Pendiente")) -> Completado | G22: Flujos y pantallas de la app definidos; la prórroga no incluye pantallas nuevas | H22: Media | I22: =IF(E22>=0.995,3,IF(E22>0,2,1)) -> 3 | J22: Entendimiento
A23: 3.2.2 | B23: Aprobacion de Arquitectura e Interoperabilidad | C23: Documento de arquitectura de interoperabilidad aprobado | D23: 3 | E23: 0.5 | F23: =IF(E23>=0.995,"Completado",IF(E23>0,"En curso","Pendiente")) -> En curso | G23: Arquitectura aprobada; mecanismo de interoperabilidad con SIVIGE sin definir | H23: Alta | I23: =IF(E23>=0.995,3,IF(E23>0,2,1)) -> 2 | J23: Entendimiento
A24: 4 | B24: OBL-04: ANALISIS, DISENO Y REQUERIMIENTOS | C24: Arquitectura, casos de uso, diccionario de datos, diagramas, actas de mesas tecnicas e historias de usuario | D24: 1 | E24: =SUMPRODUCT((D25:D54=3)*E25:E54)/COUNTIF(D25:D54,3) -> 0.806 | F24: =IF(E24>=0.995,"Completado",IF(E24>0,"En curso","Pendiente")) -> En curso | I24: =IF(E24>=0.995,3,IF(E24>0,2,1)) -> 2 | J24: Entendimiento
A25: 4.1 | B25: Documentacion previa y auditoria (Bolsa 1) | C25: Documentacion de la etapa 1 consolidada | D25: 2 | E25: =SUMPRODUCT((D26:D28=3)*E26:E28)/COUNTIF(D26:D28,3) -> 1 | F25: =IF(E25>=0.995,"Completado",IF(E25>0,"En curso","Pendiente")) -> Completado | I25: =IF(E25>=0.995,3,IF(E25>0,2,1)) -> 3 | J25: Entendimiento
A26: 4.1.1 | B26: Documentacion y metodologia SALVIA Web heredada | C26: Informe de documentacion SALVIA Web | D26: 3 | E26: 1 | F26: =IF(E26>=0.995,"Completado",IF(E26>0,"En curso","Pendiente")) -> Completado | G26: Fase inicial cerrada (hito de arquitectura al 100 % en julio) | H26: Media | I26: =IF(E26>=0.995,3,IF(E26>0,2,1)) -> 3 | J26: Entendimiento
A27: 4.1.2 | B27: Historias de Usuario actuales (sistema heredado) | C27: Inventario de HU existentes | D27: 3 | E27: 1 | F27: =IF(E27>=0.995,"Completado",IF(E27>0,"En curso","Pendiente")) -> Completado | G27: Fase inicial cerrada | H27: Media | I27: =IF(E27>=0.995,3,IF(E27>0,2,1)) -> 3 | J27: Entendimiento
A28: 4.1.3 | B28: Arquitectura actual y diagnostico de deuda tecnica | C28: Informe de arquitectura actual | D28: 3 | E28: 1 | F28: =IF(E28>=0.995,"Completado",IF(E28>0,"En curso","Pendiente")) -> Completado | G28: Fase inicial cerrada | H28: Media | I28: =IF(E28>=0.995,3,IF(E28>0,2,1)) -> 3 | J28: Entendimiento
A29: 4.2 | B29: Analisis y diseno SALVIA Web (Bolsa 1) | C29: Artefactos de analisis y diseno aprobados | D29: 2 | E29: =SUMPRODUCT((D30:D37=3)*E30:E37)/COUNTIF(D30:D37,3) -> 0.8 | F29: =IF(E29>=0.995,"Completado",IF(E29>0,"En curso","Pendiente")) -> En curso | I29: =IF(E29>=0.995,3,IF(E29>0,2,1)) -> 2 | J29: Entendimiento
A30: 4.2.1 | B30: Arquitectura SOG hacia EAV-DAG | C30: Diseno de arquitectura EAV-DAG | D30: 3 | E30: 1 | F30: =IF(E30>=0.995,"Completado",IF(E30>0,"En curso","Pendiente")) -> Completado | G30: Arquitectura EAV-DAG implementada y en producción | H30: Alta | I30: =IF(E30>=0.995,3,IF(E30>0,2,1)) -> 3 | J30: Entendimiento
A31: 4.2.2 | B31: Casos de uso e Historias de Usuario (interconectividad y flujo) | C31: Casos de uso e HU integrados | D31: 3 | E31: 0.85 | F31: =IF(E31>=0.995,"Completado",IF(E31>0,"En curso","Pendiente")) -> En curso | G31: Historias de usuario en curso (PSWYA-778, Medidas) y formulario de seguimiento V4 con prototipo, siembra y lógica (PSWYA-871 a 878, octubre) | H31: Alta | I31: =IF(E31>=0.995,3,IF(E31>0,2,1)) -> 2 | J31: Entendimiento
A32: 4.2.3 | B32: Diagramas Figma y diccionario de datos (SALVIA Web) | C32: Diagramas Figma y diccionario de datos | D32: 3 | E32: 0.75 | F32: =IF(E32>=0.995,"Completado",IF(E32>0,"En curso","Pendiente")) -> En curso | G32: Diccionario preliminar entregado; mockups de Medidas, Familiares y LGBTIQ+ por aprobar | H32: Media | I32: =IF(E32>=0.995,3,IF(E32>0,2,1)) -> 2 | J32: Entendimiento
A33: 4.2.4 | B33: Actas de mesas tecnicas | C33: Actas de mesas tecnicas firmadas | D33: 3 | E33: 0.9 | F33: =IF(E33>=0.995,"Completado",IF(E33>0,"En curso","Pendiente")) -> En curso | G33: Mesas técnicas continuas; últimas el 30-sep (cuatro sesiones) | H33: Alta | I33: =IF(E33>=0.995,3,IF(E33>0,2,1)) -> 2 | J33: Entendimiento
A34: 4.2.5 | B34: Historias de Usuario ancladas a Figma | C34: HU vinculadas a Figma | D34: 3 | E34: 0.6 | F34: =IF(E34>=0.995,"Completado",IF(E34>0,"En curso","Pendiente")) -> En curso | G34: Depende de los mockups pendientes de aprobación | H34: Media | I34: =IF(E34>=0.995,3,IF(E34>0,2,1)) -> 2 | J34: Entendimiento
A35: 4.2.6 | B35: Migracion de Kobo a Zenkit (analisis solucion transitoria) | C35: Zenkit desplegado y operativo | D35: 3 | E35: 1 | F35: =IF(E35>=0.995,"Completado",IF(E35>0,"En curso","Pendiente")) -> Completado | G35: Ficha de julio: solución transitoria Zenkit desplegada | H35: Media | I35: =IF(E35>=0.995,3,IF(E35>0,2,1)) -> 3 | J35: Entendimiento
A36: 4.2.7 | B36: Integracion data SOG hacia EAV-DAG | C36: Scripts de integracion ejecutados | D36: 3 | E36: 0.8 | F36: =IF(E36>=0.995,"Completado",IF(E36>0,"En curso","Pendiente")) -> En curso | G36: Migración ejecutada; quedan casos migrados con formularios vacíos o sin esquema (SEG-01, SEG-02) | H36: Alta | I36: =IF(E36>=0.995,3,IF(E36>0,2,1)) -> 2 | J36: Entendimiento
A37: 4.2.8 | B37: Documentacion y metodologia App MASP | C37: Informe de documentacion App MASP | D37: 3 | E37: 0.5 | F37: =IF(E37>=0.995,"Completado",IF(E37>0,"En curso","Pendiente")) -> En curso | G37: Sin evidencia en los documentos revisados | H37: Por confirmar | I37: =IF(E37>=0.995,3,IF(E37>0,2,1)) -> 2 | J37: Entendimiento
A38: 4.3 | B38: Analisis y diseno App MASP (Bolsa 2) | C38: Artefactos de analisis y diseno de la App aprobados | D38: 2 | E38: =SUMPRODUCT((D39:D39=3)*E39:E39)/COUNTIF(D39:D39,3) -> 0.6 | F38: =IF(E38>=0.995,"Completado",IF(E38>0,"En curso","Pendiente")) -> En curso | I38: =IF(E38>=0.995,3,IF(E38>0,2,1)) -> 2 | J38: Entendimiento
A39: 4.3.1 | B39: Diagramas Figma y diccionario de datos (App MASP) | C39: Diagramas Figma y diccionario de datos App | D39: 3 | E39: 0.6 | F39: =IF(E39>=0.995,"Completado",IF(E39>0,"En curso","Pendiente")) -> En curso | G39: Rediseño hecho; diccionario de datos de la app sin evidencia | H39: Por confirmar | I39: =IF(E39>=0.995,3,IF(E39>0,2,1)) -> 2 | J39: Entendimiento
A40: 4.4 | B40: Entendimiento: Reporte y Registro (Bolsa 1) | C40: Guion, formulario y mockup de Reporte y Registro validados | D40: 2 | E40: =SUMPRODUCT((D41:D48=3)*E41:E48)/COUNTIF(D41:D48,3) -> 0.9375 | F40: =IF(E40>=0.995,"Completado",IF(E40>0,"En curso","Pendiente")) -> En curso | I40: =IF(E40>=0.995,3,IF(E40>0,2,1)) -> 2 | J40: Entendimiento
A41: 4.4.1 | B41: Guion Funcional de Registro v3.0 y Formulario Kreivo v5.0 | C41: Guion funcional y formulario de registro | D41: 3 | E41: 1 | F41: =IF(E41>=0.995,"Completado",IF(E41>0,"En curso","Pendiente")) -> Completado | G41: Mockup de Reportes, Registro y Alerta Inminente aprobado por Gestión del Conocimiento (según el equipo, 13-oct). Base: Guion v3.0 y Formulario v5.0 existen (guía del 27-sep); los rangos del tamizaje están marcados como pendientes de ajuste | H41: Media | I41: =IF(E41>=0.995,3,IF(E41>0,2,1)) -> 3 | J41: Entendimiento
A42: 4.4.2 | B42: Mockup de Reporte y Registro y guia de 22 videos | C42: Mockup navegable y guia de videos | D42: 3 | E42: 1 | F42: =IF(E42>=0.995,"Completado",IF(E42>0,"En curso","Pendiente")) -> Completado | G42: Mockup y guía de 22 videos entregados el 27-sep; los videos no se grabaron porque el HTML pasó directo al equipo de desarrollo | H42: Alta | I42: =IF(E42>=0.995,3,IF(E42>0,2,1)) -> 3 | J42: Entendimiento
A43: 4.4.3 | B43: Identificacion de la victima: preguntas OSIGD para poblacion LGBTIQ+ | C43: Preguntas y logica condicional LGBTIQ+ definidas | D43: 3 | E43: 1 | F43: =IF(E43>=0.995,"Completado",IF(E43>0,"En curso","Pendiente")) -> Completado | G43: Mockup de Reportes, Registro y Alerta Inminente aprobado por Gestión del Conocimiento (según el equipo, 13-oct). Antes: Preguntas OSIGD y lógica condicional en el mockup (videos 13, 14, 17 y 19); falta la lista cerrada de preguntas (MOC-04) | H43: Media | I43: =IF(E43>=0.995,3,IF(E43>0,2,1)) -> 3 | J43: Entendimiento
A44: 4.4.4 | B44: Identificacion de la victima: actividades sexuales pagas (ASP) | C44: Preguntas de identificacion ASP definidas | D44: 3 | E44: 1 | F44: =IF(E44>=0.995,"Completado",IF(E44>0,"En curso","Pendiente")) -> Completado | G44: Mockup de Reportes, Registro y Alerta Inminente aprobado por Gestión del Conocimiento (según el equipo, 13-oct). Incluye el formulario del módulo web ASP. Antes: La identificación de ASP aparece en datos personales (video 14); la caracterización ampliada no tiene lineamientos de la Dirección ASP | H44: Media | I44: =IF(E44>=0.995,3,IF(E44>0,2,1)) -> 3 | J44: Entendimiento
A45: 4.4.5 | B45: Tamizaje de riesgo en el registro: bifurcaciones, puntaje y alertas | C45: Instrumento de tamizaje por perfil definido | D45: 3 | E45: 0.9 | F45: =IF(E45>=0.995,"Completado",IF(E45>0,"En curso","Pendiente")) -> En curso | G45: Mockup de Reportes, Registro y Alerta Inminente aprobado por Gestión del Conocimiento (según el equipo, 13-oct). Queda confirmar los rangos del puntaje, que la guía marcaba pendientes. Antes: Bifurcaciones OSIGD y pareja/no pareja y alertas en el mockup (videos 17 y 19); se asumió 1 punto por cada Sí, rangos por validar (MOC-05) | H45: Media | I45: =IF(E45>=0.995,3,IF(E45>0,2,1)) -> 2 | J45: Entendimiento
A46: 4.4.6 | B46: Gestion de reportes, recontacto 3x3 y envio del caso a Seguimiento | C46: Flujo de reporte a caso definido | D46: 3 | E46: 0.9 | F46: =IF(E46>=0.995,"Completado",IF(E46>0,"En curso","Pendiente")) -> En curso | G46: Flujo de reportes, recontacto 3x3 y envío a Seguimiento en el mockup (videos 07 a 10 y 18) | H46: Alta | I46: =IF(E46>=0.995,3,IF(E46>0,2,1)) -> 2 | J46: Entendimiento
A47: 4.4.7 | B47: Validacion con el Ministerio de los puntos abiertos del mockup | C47: Decisiones del mockup validadas | D47: 3 | E47: 1 | F47: =IF(E47>=0.995,"Completado",IF(E47>0,"En curso","Pendiente")) -> Completado | G47: Mockup de Reportes, Registro y Alerta Inminente aprobado por Gestión del Conocimiento (según el equipo, 13-oct). Antes: El mockup tomó 10 decisiones donde guion y formulario no coinciden; sin evidencia de validación del Ministerio | H47: Media | I47: =IF(E47>=0.995,3,IF(E47>0,2,1)) -> 3 | J47: Entendimiento
A48: 4.4.8 | B48: Historia de usuario del nuevo formulario de registro | C48: Historia de usuario aprobada | D48: 3 | E48: 0.7 | F48: =IF(E48>=0.995,"Completado",IF(E48>0,"En curso","Pendiente")) -> En curso | G48: Especificación de Registro V3 en DocsMD (eventos, campos, condicionales) y plan de QA con 25 casos (14 y 15-oct); PSWYA-778 sigue abierta | H48: Media | I48: =IF(E48>=0.995,3,IF(E48>0,2,1)) -> 2 | J48: Entendimiento
A49: 4.5 | B49: Entendimiento: Medidas de Emergencia (Bolsa 1) | C49: Historias de usuario, mockups y criterios de Medidas de Emergencia aprobados | D49: 2 | E49: =SUMPRODUCT((D50:D54=3)*E50:E54)/COUNTIF(D50:D54,3) -> 0.53 | F49: =IF(E49>=0.995,"Completado",IF(E49>0,"En curso","Pendiente")) -> En curso | I49: =IF(E49>=0.995,3,IF(E49>0,2,1)) -> 2 | J49: Entendimiento
A50: 4.5.1 | B50: Historias de usuario de Medidas de Emergencia v1.0 (38 HU) | C50: Documento de historias de usuario | D50: 3 | E50: 1 | F50: =IF(E50>=0.995,"Completado",IF(E50>0,"En curso","Pendiente")) -> Completado | G50: Documento v1.0 con 38 historias en 12 grupos: remisión, riesgo inminente, caracterización, Cruz Roja, seguimiento, novedades y conclusión | H50: Alta | I50: =IF(E50>=0.995,3,IF(E50>0,2,1)) -> 3 | J50: Entendimiento
A51: 4.5.2 | B51: Mockups de Medidas de Emergencia y revision con el Ministerio | C51: Mockups aprobados | D51: 3 | E51: 0.85 | F51: =IF(E51>=0.995,"Completado",IF(E51>0,"En curso","Pendiente")) -> En curso | G51: Mockups de Medidas de Emergencia (PSWYA-862, 12 y 13-oct) y sesiones de feedback con el Ministerio; pendiente retroalimentación del Equipo Técnico-Administrativo | H51: Alta | I51: =IF(E51>=0.995,3,IF(E51>0,2,1)) -> 2 | J51: Entendimiento
A52: 4.5.3 | B52: Matriz de campos y logica para determinar las medidas | C52: Matriz de campos y reglas de pertinencia | D52: 3 | E52: 0.4 | F52: =IF(E52>=0.995,"Completado",IF(E52>0,"En curso","Pendiente")) -> En curso | G52: La prórroga la lista como insumo mínimo para congelar alcance; en agosto el motor se validó con dos casos en sesión | H52: Media | I52: =IF(E52>=0.995,3,IF(E52>0,2,1)) -> 2 | J52: Entendimiento
A53: 4.5.4 | B53: Familiares y personas huerfanas dentro de Medidas (Ley 2530 de 2025) | C53: Variables y bloques repetibles definidos | D53: 3 | E53: 0.4 | F53: =IF(E53>=0.995,"Completado",IF(E53>0,"En curso","Pendiente")) -> En curso | G53: Mockup de Registro Familiares Feminicidio en revisión (Andrés Felipe, semanas 2 a 5 del plan de cierre); las 38 historias de usuario no cubren familiares | H53: Media | I53: =IF(E53>=0.995,3,IF(E53>0,2,1)) -> 2 | J53: Entendimiento
A54: 4.5.5 | B54: Criterios de aceptacion y estados aprobados por el Ministerio | C54: Criterios de aceptacion firmados | D54: 3 | E54: 0 | F54: =IF(E54>=0.995,"Completado",IF(E54>0,"En curso","Pendiente")) -> Pendiente | G54: Pendiente de aprobación formal del Ministerio; condición de la prórroga para iniciar desarrollo | H54: Alta | I54: =IF(E54>=0.995,3,IF(E54>0,2,1)) -> 1 | J54: Entendimiento
A55: 5 | B55: OBL-05: DESARROLLO DE MODULOS SALVIA | C55: Codigo fuente documentado, manuales de usuario, documentacion tecnica y componentes de BD y aplicacion | D55: 1 | E55: =SUMPRODUCT((D56:D63=3)*E56:E63)/COUNTIF(D56:D63,3) -> 0.50833333 | F55: =IF(E55>=0.995,"Completado",IF(E55>0,"En curso","Pendiente")) -> En curso | I55: =IF(E55>=0.995,3,IF(E55>0,2,1)) -> 2 | J55: Construcción y cierre
A56: 5.1 | B56: Sprints de construccion SALVIA Web (Bolsa 1) | C56: Sprints 1 a 5 entregados | D56: 2 | E56: =SUMPRODUCT((D57:D60=3)*E57:E60)/COUNTIF(D57:D60,3) -> 0.6125 | F56: =IF(E56>=0.995,"Completado",IF(E56>0,"En curso","Pendiente")) -> En curso | I56: =IF(E56>=0.995,3,IF(E56>0,2,1)) -> 2 | J56: Construcción y cierre
A57: 5.1.1 | B57: Sprint 1: Setup de entornos, BD y seguridad (autenticacion) | C57: Entornos, BD y autenticacion listos | D57: 3 | E57: 1 | F57: =IF(E57>=0.995,"Completado",IF(E57>0,"En curso","Pendiente")) -> Completado | G57: Entornos, base de datos y roles en producción | H57: Alta | I57: =IF(E57>=0.995,3,IF(E57>0,2,1)) -> 3 | J57: Construcción y cierre
A58: 5.1.2 | B58: Sprint 2: Modulos de registro y motor de tamizaje | C58: Modulo de registro y motor de tamizaje operativos | D58: 3 | E58: 0.7 | F58: =IF(E58>=0.995,"Completado",IF(E58>0,"En curso","Pendiente")) -> En curso | G58: Registro en producción; el tamizaje del nuevo Registro V3 persiste y se relee de la base (2c78f3b, en testing). Pendiente: confirmar rangos del puntaje y paso a main | H58: Alta | I58: =IF(E58>=0.995,3,IF(E58>0,2,1)) -> 2 | J58: Construcción y cierre
A59: 5.1.3 | B59: Sprint 3: Dashboard de trazabilidad y alertas | C59: Dashboard de trazabilidad y alertas desplegado | D59: 3 | E59: 0.75 | F59: =IF(E59>=0.995,"Completado",IF(E59>0,"En curso","Pendiente")) -> En curso | G59: Corte 13-oct más, en testing: estado obligatorio al registrar caso (1dee9b9) y filtro por estado en Lista de casos (4f9b633) | H59: Alta | I59: =IF(E59>=0.995,3,IF(E59>0,2,1)) -> 2 | J59: Construcción y cierre
A60: 5.1.4 | B60: Sprint 5: Integracion SIVIGE (interoperabilidad) | C60: API de interoperabilidad con SIVIGE | D60: 3 | E60: 0 | F60: =IF(E60>=0.995,"Completado",IF(E60>0,"En curso","Pendiente")) -> Pendiente | G60: Mecanismo de réplica y auditoría con SIVIGE sin definir (riesgo 2 del informe del 17-sep) | H60: Alta | I60: =IF(E60>=0.995,3,IF(E60>0,2,1)) -> 1 | J60: Construcción y cierre
A61: 5.2 | B61: Sprints de construccion App MASP (Bolsa 2) | C61: Sprints 4 y 6 de la App entregados | D61: 2 | E61: =SUMPRODUCT((D62:D63=3)*E62:E63)/COUNTIF(D62:D63,3) -> 0.3 | F61: =IF(E61>=0.995,"Completado",IF(E61>0,"En curso","Pendiente")) -> En curso | I61: =IF(E61>=0.995,3,IF(E61>0,2,1)) -> 2 | J61: Construcción y cierre
A62: 5.2.1 | B62: Sprint 4: Desarrollo App MASP (iOS / Android) | C62: Build nativo iOS y Android generado | D62: 3 | E62: 0.6 | F62: =IF(E62>=0.995,"Completado",IF(E62>0,"En curso","Pendiente")) -> En curso | G62: Versión Android subida el 23-sep; iOS sin evidencia; directorio en desarrollo | H62: Alta | I62: =IF(E62>=0.995,3,IF(E62>0,2,1)) -> 2 | J62: Construcción y cierre
A63: 5.2.2 | B63: Ejecucion de pruebas unitarias y de carga (sprint) | C63: Pruebas unitarias y de carga del sprint ejecutadas | D63: 3 | E63: 0 | F63: =IF(E63>=0.995,"Completado",IF(E63>0,"En curso","Pendiente")) -> Pendiente | G63: Sin evidencia de pruebas unitarias ni de carga de la app | H63: Por confirmar | I63: =IF(E63>=0.995,3,IF(E63>0,2,1)) -> 1 | J63: Construcción y cierre
A64: 6 | B64: OBL-06: ACOMPANAMIENTO EN FASES DE DESARROLLO | C64: Actas de acompanamiento y uso de modulos (diseno, pruebas, produccion) y documento de verificacion de calidad | D64: 1 | E64: =SUMPRODUCT((D65:D85=3)*E65:E85)/COUNTIF(D65:D85,3) -> 0.49210526 | F64: =IF(E64>=0.995,"Completado",IF(E64>0,"En curso","Pendiente")) -> En curso | I64: =IF(E64>=0.995,3,IF(E64>0,2,1)) -> 2 | J64: Construcción y cierre
A65: 6.1 | B65: Acompanamiento SALVIA Web (Bolsa 1) | C65: Acompanamiento continuo a la construccion de modulos web | D65: 2 | E65: =SUMPRODUCT((D66:D77=3)*E66:E77)/COUNTIF(D66:D77,3) -> 0.54166667 | F65: =IF(E65>=0.995,"Completado",IF(E65>0,"En curso","Pendiente")) -> En curso | I65: =IF(E65>=0.995,3,IF(E65>0,2,1)) -> 2 | J65: Construcción y cierre
A66: 6.1.1 | B66: BI: Diseno de Dashboards y ETL | C66: Dashboards y rutinas ETL implementados | D66: 3 | E66: 0.5 | F66: =IF(E66>=0.995,"Completado",IF(E66>0,"En curso","Pendiente")) -> En curso | G66: Lista para main (corte 13-oct): cerca de 30 campos nuevos en el Excel consolidado y corrección de tipo/subtipo de violencia. Antes: tablero de KPIs y descarga existen, con hallazgos (SEG-07, SEG-08); BI en mockup | H66: Alta | I66: =IF(E66>=0.995,3,IF(E66>0,2,1)) -> 2 | J66: Construcción y cierre
A67: 6.1.2 | B67: Adopcion: manuales y capacitacion (SALVIA Web) | C67: Manuales de adopcion y plan de capacitacion | D67: 3 | E67: 0.65 | F67: =IF(E67>=0.995,"Completado",IF(E67>0,"En curso","Pendiente")) -> En curso | G67: Ocho manuales técnicos de SALVIA Web en PDF (14 y 15-oct) y 15 videos de uso de SALVIA Web (unos 58 minutos: Seguimiento, detalle y timeline del caso, 3x3, plan de contactos, Barreras, oficios, Notificaciones, Tareas, reasignación y reportes) más 2 videos de avance de Rutas (16 minutos), Mapa de navegación y consolidado de historias de usuario (48 págs.), usados por la entidad en capacitación y pruebas (según el equipo, 28-oct) | H67: Alta | I67: =IF(E67>=0.995,3,IF(E67>0,2,1)) -> 2 | J67: Construcción y cierre
A68: 6.1.3 | B68: Setup entornos, BD Postgres y seguridad (SALVIA) | C68: Entornos productivos configurados | D68: 3 | E68: 1 | F68: =IF(E68>=0.995,"Completado",IF(E68>0,"En curso","Pendiente")) -> Completado | G68: Entornos productivos operando | H68: Alta | I68: =IF(E68>=0.995,3,IF(E68>0,2,1)) -> 3 | J68: Construcción y cierre
A69: 6.1.4 | B69: Modulo de recepcion y motor de tamizaje (web) | C69: Modulo de recepcion y tamizaje web operativo | D69: 3 | E69: 0.6 | F69: =IF(E69>=0.995,"Completado",IF(E69>0,"En curso","Pendiente")) -> En curso | G69: Igual que 5.1.2: tamizaje integrado al Registro V3 en testing (23-oct) | H69: Alta | I69: =IF(E69>=0.995,3,IF(E69>0,2,1)) -> 2 | J69: Construcción y cierre
A70: 6.1.5 | B70: Modulo de seguimiento y tableros BI/ETL (web) | C70: Modulo de seguimiento con BI y ETL | D70: 3 | E70: 0.9 | F70: =IF(E70>=0.995,"Completado",IF(E70>0,"En curso","Pendiente")) -> En curso | G70: Lista para main (corte 13-oct) más, en testing: nombre del agente resuelto en backend, seguimientos realizados y pendientes agrupados, y sin bloqueo de fecha al iniciar o abrir el formulario (adc24dc, 345b0df). El nuevo formulario V4 se registra en 4.2.2 | H70: Alta | I70: =IF(E70>=0.995,3,IF(E70>0,2,1)) -> 2 | J70: Construcción y cierre
A71: 6.1.6 | B71: Modulo LGBTIQ+ (construccion y variables diferenciales) | C71: Modulo LGBTIQ+ implementado | D71: 3 | E71: 0.25 | F71: =IF(E71>=0.995,"Completado",IF(E71>0,"En curso","Pendiente")) -> En curso | G71: Secciones OSIGHN construidas en psicosocial (17-sep); MVP de preguntas en registro y seguimiento pendiente de lista cerrada | H71: Alta | I71: =IF(E71>=0.995,3,IF(E71>0,2,1)) -> 2 | J71: Construcción y cierre
A72: 6.1.7 | B72: Modulo ASP Web - caracterizacion y analisis de riesgo | C72: Modulo SALVIA Web ASP implementado | D72: 3 | E72: 0 | F72: =IF(E72>=0.995,"Completado",IF(E72>0,"En curso","Pendiente")) -> Pendiente | G72: Sin desarrollo. La solicitud de prórroga pide definir su tratamiento | H72: Alta | I72: =IF(E72>=0.995,3,IF(E72>0,2,1)) -> 1 | J72: Construcción y cierre
A73: 6.1.8 | B73: Nuevo formulario de Reporte y Registro (construccion) | C73: Reporte y Registro operativos | D73: 3 | E73: 0.75 | F73: =IF(E73>=0.995,"Completado",IF(E73>0,"En curso","Pendiente")) -> En curso | G73: Registro V3 en testing desde el 14-oct (1a08a2c): Habeas Data, cabezote, 7 módulos con tamizaje, Gestión Salvia (remisión, entidades, barreras y alerta inminente) y cierre; QA con Playwright el 15-oct, 8 bugs corregidos (2c78f3b). Pendiente: nuevo caso sobre registro existente y actualizar caso, ajustes de UI de la supervisión, UAT y paso a main | H73: Alta | I73: =IF(E73>=0.995,3,IF(E73>0,2,1)) -> 2 | J73: Construcción y cierre
A74: 6.1.9 | B74: Modulo Medidas de Emergencia: pantallas y flujo | C74: Pantallas de los mockups aprobados construidas | D74: 3 | E74: 0.15 | F74: =IF(E74>=0.995,"Completado",IF(E74>0,"En curso","Pendiente")) -> En curso | G74: Primeras pantallas de remisiones y detalle de remisión de Medidas en Jira (PSWYA-849 y 854, 22 y 23-oct) y flujo completo asignado en FigJam "Terminar Medidas" (Santiago y Juan, semanas 1 a 4) | H74: Media | I74: =IF(E74>=0.995,3,IF(E74>0,2,1)) -> 2 | J74: Construcción y cierre
A75: 6.1.10 | B75: Medidas de Emergencia: logica de medidas, entrega y seguimiento | C75: Logica de medidas y trazabilidad de entrega operativas | D75: 3 | E75: 0 | F75: =IF(E75>=0.995,"Completado",IF(E75>0,"En curso","Pendiente")) -> Pendiente | G75: Sin desarrollo según la solicitud de prórroga | H75: Alta | I75: =IF(E75>=0.995,3,IF(E75>0,2,1)) -> 1 | J75: Construcción y cierre
A76: 6.1.11 | B76: Atencion Psicosocial: construccion y estabilizacion | C76: Modulo psicosocial operativo y estabilizado | D76: 3 | E76: 0.9 | F76: =IF(E76>=0.995,"Completado",IF(E76>0,"En curso","Pendiente")) -> En curso | G76: En producción desde septiembre; en testing (19 al 20-oct): indicador de atenciones realizadas y agendadas en detalle y remisiones, filtro por estado, nuevo seguimiento con autoasignación para rol an (e09fb2f), seguimiento desde la cita y filtro por dupla (b207846) | H76: Alta | I76: =IF(E76>=0.995,3,IF(E76>0,2,1)) -> 2 | J76: Construcción y cierre
A77: 6.1.12 | B77: Rutas y gestion institucional: portal de entidades, mecanismos y directorio | C77: Rutas operativo en produccion | D77: 3 | E77: 0.8 | F77: =IF(E77>=0.995,"Completado",IF(E77>0,"En curso","Pendiente")) -> En curso | G77: En testing (20 al 22-oct): migración de las Alcaldías y de las 38 entidades de la hoja 4 del Formulario de Rutas con sus acciones institucionales (f921f35, 127ba07), DIVIPOLA por municipio (01246e8), sedes generadas desde el Directorio (cf53257), sede asignada al usuario entidad y cerrar sesión (11f0970), campo sucursal al crear usuario Alcaldía (597d246), Mis Tareas bloqueado para rol et (d873f7b) y estilos del detalle de caso entidad (7bb9d42) | H77: Alta | I77: =IF(E77>=0.995,3,IF(E77>0,2,1)) -> 2 | J77: Construcción y cierre
A78: 6.2 | B78: Acompanamiento App MASP (Bolsa 2) | C78: Acompanamiento continuo a la construccion de la App | D78: 2 | E78: =SUMPRODUCT((D79:D85=3)*E79:E85)/COUNTIF(D79:D85,3) -> 0.40714286 | F78: =IF(E78>=0.995,"Completado",IF(E78>0,"En curso","Pendiente")) -> En curso | I78: =IF(E78>=0.995,3,IF(E78>0,2,1)) -> 2 | J78: Construcción y cierre
A79: 6.2.1 | B79: Despliegue: migracion a produccion (App) | C79: App migrada a entorno productivo | D79: 3 | E79: 0.6 | F79: =IF(E79>=0.995,"Completado",IF(E79>0,"En curso","Pendiente")) -> En curso | G79: La app apunta a salvia-colombia.co desde el 15-sep; el informe del 17-sep la reporta en Play Store | H79: Media | I79: =IF(E79>=0.995,3,IF(E79>0,2,1)) -> 2 | J79: Construcción y cierre
A80: 6.2.2 | B80: Soporte: activacion de mesa de ayuda | C80: Mesa de ayuda 24/7 activa | D80: 3 | E80: 0 | F80: =IF(E80>=0.995,"Completado",IF(E80>0,"En curso","Pendiente")) -> Pendiente | G80: Sin evidencia de mesa de ayuda activa; los hallazgos entran por Forms y bitácora | H80: Por confirmar | I80: =IF(E80>=0.995,3,IF(E80>0,2,1)) -> 1 | J80: Construcción y cierre
A81: 6.2.3 | B81: Ejecucion de pruebas unitarias y de carga (App) | C81: Pruebas unitarias y de carga de la App ejecutadas | D81: 3 | E81: 0 | F81: =IF(E81>=0.995,"Completado",IF(E81>0,"En curso","Pendiente")) -> Pendiente | G81: Sin evidencia | H81: Por confirmar | I81: =IF(E81>=0.995,3,IF(E81>0,2,1)) -> 1 | J81: Construcción y cierre
A82: 6.2.4 | B82: Setup de entornos y seguridad API (App MASP) | C82: Entornos y seguridad API configurados | D82: 3 | E82: 0.9 | F82: =IF(E82>=0.995,"Completado",IF(E82>0,"En curso","Pendiente")) -> En curso | G82: Firma de la app y dominio productivo configurados el 15-sep | H82: Media | I82: =IF(E82>=0.995,3,IF(E82>0,2,1)) -> 2 | J82: Construcción y cierre
A83: 6.2.5 | B83: Desarrollo de interfaz y logica de App Movil MASP | C83: Interfaz y logica de la App implementadas | D83: 3 | E83: 0.6 | F83: =IF(E83>=0.995,"Completado",IF(E83>0,"En curso","Pendiente")) -> En curso | G83: Contactos, Home, programas y ajustes visuales; directorio en desarrollo | H83: Alta | I83: =IF(E83>=0.995,3,IF(E83>0,2,1)) -> 2 | J83: Construcción y cierre
A84: 6.2.6 | B84: Desarrollo backend - Boton de Panico Linea 155 | C84: Backend de boton de panico operativo | D84: 3 | E84: 0.5 | F84: =IF(E84>=0.995,"Completado",IF(E84>0,"En curso","Pendiente")) -> En curso | G84: Informe 17-sep lo da por completado; el cronograma mantiene avance de botón de pánico en octubre | H84: Media | I84: =IF(E84>=0.995,3,IF(E84>0,2,1)) -> 2 | J84: Construcción y cierre
A85: 6.2.7 | B85: Integracion App - Boton de Panico Linea 155 | C85: Integracion boton de panico con Linea 155 | D85: 3 | E85: 0.25 | F85: =IF(E85>=0.995,"Completado",IF(E85>0,"En curso","Pendiente")) -> En curso | G85: Sincronización y bitácora en desarrollo; integración app-web prevista para octubre | H85: Alta | I85: =IF(E85>=0.995,3,IF(E85>0,2,1)) -> 2 | J85: Construcción y cierre
A86: 7 | B86: OBL-07: PRUEBAS FUNCIONALES Y NO FUNCIONALES | C86: Escenarios de pruebas e informe de resultados con certificacion de la OTI o area funcional | D86: 1 | E86: =SUMPRODUCT((D87:D99=3)*E87:E99)/COUNTIF(D87:D99,3) -> 0.33181818 | F86: =IF(E86>=0.995,"Completado",IF(E86>0,"En curso","Pendiente")) -> En curso | I86: =IF(E86>=0.995,3,IF(E86>0,2,1)) -> 2 | J86: Construcción y cierre
A87: 7.1 | B87: Pruebas SALVIA Web (Bolsa 1) | C87: Plan de pruebas del sistema web ejecutado | D87: 2 | E87: =SUMPRODUCT((D88:D94=3)*E88:E94)/COUNTIF(D88:D94,3) -> 0.36428571 | F87: =IF(E87>=0.995,"Completado",IF(E87>0,"En curso","Pendiente")) -> En curso | I87: =IF(E87>=0.995,3,IF(E87>0,2,1)) -> 2 | J87: Construcción y cierre
A88: 7.1.1 | B88: Pruebas de Aceptacion de Usuario (UAT) con el Ministerio | C88: Acta de UAT aprobada | D88: 3 | E88: 0.45 | F88: =IF(E88>=0.995,"Completado",IF(E88>0,"En curso","Pendiente")) -> En curso | G88: La matriz de hallazgos de SALVIA (revisión Kreivo del 8-oct) da 107 de 159 hallazgos por cerrados. Mesas de hallazgos y Forms con SALVIA en marcha; UAT formal del alcance contractual sin iniciar | H88: Alta | I88: =IF(E88>=0.995,3,IF(E88>0,2,1)) -> 2 | J88: Construcción y cierre
A89: 7.1.2 | B89: Transferencia de conocimiento y capacitacion inicial | C89: Sesiones de transferencia ejecutadas | D89: 3 | E89: 0.65 | F89: =IF(E89>=0.995,"Completado",IF(E89>0,"En curso","Pendiente")) -> En curso | G89: 15 videos de uso de SALVIA Web (unos 58 minutos: Seguimiento, detalle y timeline del caso, 3x3, plan de contactos, Barreras, oficios, Notificaciones, Tareas, reasignación y reportes) más 2 videos de avance de Rutas (16 minutos), Mapa de navegación y consolidado de historias de usuario (48 págs.). Según el equipo (28-oct), la entidad los usa como material de capacitación masiva y en pruebas | H89: Media | I89: =IF(E89>=0.995,3,IF(E89>0,2,1)) -> 2 | J89: Construcción y cierre
A90: 7.1.3 | B90: Paso a produccion oficial SALVIA | C90: SALVIA Web en produccion | D90: 3 | E90: 0.65 | F90: =IF(E90>=0.995,"Completado",IF(E90>0,"En curso","Pendiente")) -> En curso | G90: 64 cambios del corte 13-oct y 29 commits más (13 al 23-oct) integrados en testing (PR #117 a #132); main sigue sin cambios desde el 10-sep. Seguimiento, Barreras, Notificaciones, Tareas y Psicosocial en producción | H90: Alta | I90: =IF(E90>=0.995,3,IF(E90>0,2,1)) -> 2 | J90: Construcción y cierre
A91: 7.1.4 | B91: API de sincronizacion SIVIGE (Minsalud) | C91: API SIVIGE certificada | D91: 3 | E91: 0 | F91: =IF(E91>=0.995,"Completado",IF(E91>0,"En curso","Pendiente")) -> Pendiente | G91: Depende de 5.1.4 | H91: Alta | I91: =IF(E91>=0.995,3,IF(E91>0,2,1)) -> 1 | J91: Construcción y cierre
A92: 7.1.5 | B92: QA unitarias, carga y vulnerabilidad (SALVIA Web) | C92: Informe de QA SALVIA Web | D92: 3 | E92: 0.35 | F92: =IF(E92>=0.995,"Completado",IF(E92>0,"En curso","Pendiente")) -> En curso | G92: QA de Rutas, primera iteración; plan de QA de Registro V3 ejecutado con Playwright (15-oct) y pruebas unitarias nuevas en migraciones, DIVIPOLA y estado de casos. Estrés y seguridad pendientes | H92: Alta | I92: =IF(E92>=0.995,3,IF(E92>0,2,1)) -> 2 | J92: Construcción y cierre
A93: 7.1.6 | B93: Pruebas de Aceptacion de Usuario UAT (SALVIA Web) | C93: Acta UAT SALVIA Web | D93: 3 | E93: 0.45 | F93: =IF(E93>=0.995,"Completado",IF(E93>0,"En curso","Pendiente")) -> En curso | G93: Igual que 7.1.1: 107 de 159 hallazgos cerrados en la matriz de SALVIA; sin acta de UAT | H93: Alta | I93: =IF(E93>=0.995,3,IF(E93>0,2,1)) -> 2 | J93: Construcción y cierre
A94: 7.1.7 | B94: Pruebas y aceptacion de Medidas de Emergencia | C94: Acta de pruebas de Medidas de Emergencia | D94: 3 | E94: 0 | F94: =IF(E94>=0.995,"Completado",IF(E94>0,"En curso","Pendiente")) -> Pendiente | G94: Depende de la construcción | H94: Alta | I94: =IF(E94>=0.995,3,IF(E94>0,2,1)) -> 1 | J94: Construcción y cierre
A95: 7.2 | B95: Pruebas App MASP (Bolsa 2) | C95: Plan de pruebas de la App ejecutado | D95: 2 | E95: =SUMPRODUCT((D96:D99=3)*E96:E99)/COUNTIF(D96:D99,3) -> 0.275 | F95: =IF(E95>=0.995,"Completado",IF(E95>0,"En curso","Pendiente")) -> En curso | I95: =IF(E95>=0.995,3,IF(E95>0,2,1)) -> 2 | J95: Construcción y cierre
A96: 7.2.1 | B96: Ajustes Post-UAT y estabilizacion | C96: Version estabilizada post UAT | D96: 3 | E96: 0.6 | F96: =IF(E96>=0.995,"Completado",IF(E96>0,"En curso","Pendiente")) -> En curso | G96: El despliegue del 13-oct corrige hallazgos que la matriz de SALVIA aún marca abiertos o en proceso (hoja Despliegue_13oct) | H96: Alta | I96: =IF(E96>=0.995,3,IF(E96>0,2,1)) -> 2 | J96: Construcción y cierre
A97: 7.2.2 | B97: Publicacion App MASP en stores | C97: App publicada en Play Store y App Store | D97: 3 | E97: 0.5 | F97: =IF(E97>=0.995,"Completado",IF(E97>0,"En curso","Pendiente")) -> En curso | G97: Play Store según informe del 17-sep; App Store sin evidencia | H97: Media | I97: =IF(E97>=0.995,3,IF(E97>0,2,1)) -> 2 | J97: Construcción y cierre
A98: 7.2.3 | B98: QA unitarias, estres y vulnerabilidad (App MASP) | C98: Informe de QA App MASP | D98: 3 | E98: 0 | F98: =IF(E98>=0.995,"Completado",IF(E98>0,"En curso","Pendiente")) -> Pendiente | G98: Sin evidencia | H98: Por confirmar | I98: =IF(E98>=0.995,3,IF(E98>0,2,1)) -> 1 | J98: Construcción y cierre
A99: 7.2.4 | B99: Pruebas de Aceptacion de Usuario UAT (App MASP) | C99: Acta UAT App MASP | D99: 3 | E99: 0 | F99: =IF(E99>=0.995,"Completado",IF(E99>0,"En curso","Pendiente")) -> Pendiente | G99: Sin evidencia | H99: Por confirmar | I99: =IF(E99>=0.995,3,IF(E99>0,2,1)) -> 1 | J99: Construcción y cierre
A100: 8 | B100: OBL-08: CONFIGURACION EN PRODUCCION | C100: Actas de acompanamiento, instalacion y configuracion de la version estable en produccion con evidencias | D100: 1 | E100: =SUMPRODUCT((D101:D108=3)*E101:E108)/COUNTIF(D101:D108,3) -> 0.3 | F100: =IF(E100>=0.995,"Completado",IF(E100>0,"En curso","Pendiente")) -> En curso | I100: =IF(E100>=0.995,3,IF(E100>0,2,1)) -> 2 | J100: Construcción y cierre
...

Sheet Matriz
A1: ID | B1: M1 | C1: M2 | D1: M3 | E1: M4 | F1: M5 | G1: APP | H1: H06 | I1: H07 | J1: H08 | K1: H09 | L1: H10 | M1: H11
A2: 1 | B2: =IF(Pertenencia!B2=1,Plan!$I2,0) -> 0 | C2: =IF(Pertenencia!C2=1,Plan!$I2,0) -> 0 | D2: =IF(Pertenencia!D2=1,Plan!$I2,0) -> 0 | E2: =IF(Pertenencia!E2=1,Plan!$I2,0) -> 0 | F2: =IF(Pertenencia!F2=1,Plan!$I2,0) -> 0 | G2: =IF(Pertenencia!G2=1,Plan!$I2,0) -> 0 | H2: =IF(Pertenencia!H2=1,Plan!$I2,0) -> 0 | I2: =IF(Pertenencia!I2=1,Plan!$I2,0) -> 3 | ... M2: =IF(Pertenencia!M2=1,Plan!$I2,0) -> 0
A3: 1.1 | B3: =IF(Pertenencia!B3=1,Plan!$I3,0) -> 0 | C3: =IF(Pertenencia!C3=1,Plan!$I3,0) -> 0 | D3: =IF(Pertenencia!D3=1,Plan!$I3,0) -> 0 | E3: =IF(Pertenencia!E3=1,Plan!$I3,0) -> 0 | F3: =IF(Pertenencia!F3=1,Plan!$I3,0) -> 0 | G3: =IF(Pertenencia!G3=1,Plan!$I3,0) -> 0 | H3: =IF(Pertenencia!H3=1,Plan!$I3,0) -> 0 | I3: =IF(Pertenencia!I3=1,Plan!$I3,0) -> 3 | ... M3: =IF(Pertenencia!M3=1,Plan!$I3,0) -> 0
A4: 1.1.1 | B4: =IF(Pertenencia!B4=1,Plan!$I4,0) -> 0 | C4: =IF(Pertenencia!C4=1,Plan!$I4,0) -> 0 | D4: =IF(Pertenencia!D4=1,Plan!$I4,0) -> 0 | E4: =IF(Pertenencia!E4=1,Plan!$I4,0) -> 0 | F4: =IF(Pertenencia!F4=1,Plan!$I4,0) -> 0 | G4: =IF(Pertenencia!G4=1,Plan!$I4,0) -> 0 | H4: =IF(Pertenencia!H4=1,Plan!$I4,0) -> 0 | I4: =IF(Pertenencia!I4=1,Plan!$I4,0) -> 3 | ... M4: =IF(Pertenencia!M4=1,Plan!$I4,0) -> 0
A5: 1.1.2 | B5: =IF(Pertenencia!B5=1,Plan!$I5,0) -> 0 | C5: =IF(Pertenencia!C5=1,Plan!$I5,0) -> 0 | D5: =IF(Pertenencia!D5=1,Plan!$I5,0) -> 0 | E5: =IF(Pertenencia!E5=1,Plan!$I5,0) -> 0 | F5: =IF(Pertenencia!F5=1,Plan!$I5,0) -> 0 | G5: =IF(Pertenencia!G5=1,Plan!$I5,0) -> 0 | H5: =IF(Pertenencia!H5=1,Plan!$I5,0) -> 0 | I5: =IF(Pertenencia!I5=1,Plan!$I5,0) -> 3 | ... M5: =IF(Pertenencia!M5=1,Plan!$I5,0) -> 0
A6: 2 | B6: =IF(Pertenencia!B6=1,Plan!$I6,0) -> 0 | C6: =IF(Pertenencia!C6=1,Plan!$I6,0) -> 0 | D6: =IF(Pertenencia!D6=1,Plan!$I6,0) -> 0 | E6: =IF(Pertenencia!E6=1,Plan!$I6,0) -> 0 | F6: =IF(Pertenencia!F6=1,Plan!$I6,0) -> 2 | G6: =IF(Pertenencia!G6=1,Plan!$I6,0) -> 2 | H6: =IF(Pertenencia!H6=1,Plan!$I6,0) -> 2 | I6: =IF(Pertenencia!I6=1,Plan!$I6,0) -> 2 | ... M6: =IF(Pertenencia!M6=1,Plan!$I6,0) -> 0
A7: 2.1 | B7: =IF(Pertenencia!B7=1,Plan!$I7,0) -> 0 | C7: =IF(Pertenencia!C7=1,Plan!$I7,0) -> 0 | D7: =IF(Pertenencia!D7=1,Plan!$I7,0) -> 0 | E7: =IF(Pertenencia!E7=1,Plan!$I7,0) -> 0 | F7: =IF(Pertenencia!F7=1,Plan!$I7,0) -> 2 | G7: =IF(Pertenencia!G7=1,Plan!$I7,0) -> 0 | H7: =IF(Pertenencia!H7=1,Plan!$I7,0) -> 2 | I7: =IF(Pertenencia!I7=1,Plan!$I7,0) -> 2 | ... M7: =IF(Pertenencia!M7=1,Plan!$I7,0) -> 0
A8: 2.1.1 | B8: =IF(Pertenencia!B8=1,Plan!$I8,0) -> 0 | C8: =IF(Pertenencia!C8=1,Plan!$I8,0) -> 0 | D8: =IF(Pertenencia!D8=1,Plan!$I8,0) -> 0 | E8: =IF(Pertenencia!E8=1,Plan!$I8,0) -> 0 | F8: =IF(Pertenencia!F8=1,Plan!$I8,0) -> 0 | G8: =IF(Pertenencia!G8=1,Plan!$I8,0) -> 0 | H8: =IF(Pertenencia!H8=1,Plan!$I8,0) -> 3 | I8: =IF(Pertenencia!I8=1,Plan!$I8,0) -> 3 | ... M8: =IF(Pertenencia!M8=1,Plan!$I8,0) -> 0
A9: 2.1.2 | B9: =IF(Pertenencia!B9=1,Plan!$I9,0) -> 0 | C9: =IF(Pertenencia!C9=1,Plan!$I9,0) -> 0 | D9: =IF(Pertenencia!D9=1,Plan!$I9,0) -> 0 | E9: =IF(Pertenencia!E9=1,Plan!$I9,0) -> 0 | F9: =IF(Pertenencia!F9=1,Plan!$I9,0) -> 0 | G9: =IF(Pertenencia!G9=1,Plan!$I9,0) -> 0 | H9: =IF(Pertenencia!H9=1,Plan!$I9,0) -> 0 | I9: =IF(Pertenencia!I9=1,Plan!$I9,0) -> 2 | ... M9: =IF(Pertenencia!M9=1,Plan!$I9,0) -> 0
A10: 2.1.3 | B10: =IF(Pertenencia!B10=1,Plan!$I10,0) -> 0 | C10: =IF(Pertenencia!C10=1,Plan!$I10,0) -> 0 | D10: =IF(Pertenencia!D10=1,Plan!$I10,0) -> 0 | E10: =IF(Pertenencia!E10=1,Plan!$I10,0) -> 0 | F10: =IF(Pertenencia!F10=1,Plan!$I10,0) -> 2 | G10: =IF(Pertenencia!G10=1,Plan!$I10,0) -> 0 | H10: =IF(Pertenencia!H10=1,Plan!$I10,0) -> 0 | I10: =IF(Pertenencia!I10=1,Plan!$I10,0) -> 2 | ... M10: =IF(Pertenencia!M10=1,Plan!$I10,0) -> 0
A11: 2.1.4 | B11: =IF(Pertenencia!B11=1,Plan!$I11,0) -> 0 | C11: =IF(Pertenencia!C11=1,Plan!$I11,0) -> 0 | D11: =IF(Pertenencia!D11=1,Plan!$I11,0) -> 0 | E11: =IF(Pertenencia!E11=1,Plan!$I11,0) -> 0 | F11: =IF(Pertenencia!F11=1,Plan!$I11,0) -> 0 | G11: =IF(Pertenencia!G11=1,Plan!$I11,0) -> 0 | H11: =IF(Pertenencia!H11=1,Plan!$I11,0) -> 0 | I11: =IF(Pertenencia!I11=1,Plan!$I11,0) -> 3 | ... M11: =IF(Pertenencia!M11=1,Plan!$I11,0) -> 0
A12: 2.2 | B12: =IF(Pertenencia!B12=1,Plan!$I12,0) -> 0 | C12: =IF(Pertenencia!C12=1,Plan!$I12,0) -> 0 | D12: =IF(Pertenencia!D12=1,Plan!$I12,0) -> 0 | E12: =IF(Pertenencia!E12=1,Plan!$I12,0) -> 0 | F12: =IF(Pertenencia!F12=1,Plan!$I12,0) -> 2 | G12: =IF(Pertenencia!G12=1,Plan!$I12,0) -> 2 | H12: =IF(Pertenencia!H12=1,Plan!$I12,0) -> 0 | I12: =IF(Pertenencia!I12=1,Plan!$I12,0) -> 0 | ... M12: =IF(Pertenencia!M12=1,Plan!$I12,0) -> 0
A13: 2.2.1 | B13: =IF(Pertenencia!B13=1,Plan!$I13,0) -> 0 | C13: =IF(Pertenencia!C13=1,Plan!$I13,0) -> 0 | D13: =IF(Pertenencia!D13=1,Plan!$I13,0) -> 0 | E13: =IF(Pertenencia!E13=1,Plan!$I13,0) -> 0 | F13: =IF(Pertenencia!F13=1,Plan!$I13,0) -> 0 | G13: =IF(Pertenencia!G13=1,Plan!$I13,0) -> 3 | H13: =IF(Pertenencia!H13=1,Plan!$I13,0) -> 0 | I13: =IF(Pertenencia!I13=1,Plan!$I13,0) -> 0 | ... M13: =IF(Pertenencia!M13=1,Plan!$I13,0) -> 0
... A145: 13.2.1 | B145: =IF(Pertenencia!B145=1,Plan!$I145,0) -> 0 | C145: =IF(Pertenencia!C145=1,Plan!$I145,0) -> 0 | D145: =IF(Pertenencia!D145=1,Plan!$I145,0) -> 0 | E145: =IF(Pertenencia!E145=1,Plan!$I145,0) -> 0 | F145: =IF(Pertenencia!F145=1,Plan!$I145,0) -> 0 | G145: =IF(Pertenencia!G145=1,Plan!$I145,0) -> 0 | H145: =IF(Pertenencia!H145=1,Plan!$I145,0) -> 0 | I145: =IF(Pertenencia!I145=1,Plan!$I145,0) -> 2 | ... M145: =IF(Pertenencia!M145=1,Plan!$I145,0) -> 0

Sheet Actas
A1: ID_Hito | B1: Nombre_Hito | C1: Fecha_Ejecucion | D1: Avance_% | E1: Resumen_Acta (Ficha Técnica) | F1: Responsable | G1: Avance_julio | H1: Fecha_Corte | I1: Avance_Entendimiento | J1: Avance_Construccion | K1: Grupo
A2: M1 | B2: M1 · SEGUIMIENTO A LOS CASOS | C2: 46191 | D2: =SUMPRODUCT((Pertenencia!B$2:B$145=1)*(Plan!$D$2:$D$145=3)*Plan!$E$2:$E$145)/SUMPRODUCT((Pertenencia!B$2:B$145=1)*(Plan!$D$2:$D$145=3)) -> 0.75 | E2: Corte 23-oct: en testing quedaron 29 commits más. Rutas y gestión institucional suma la migración de las Alcaldías y de 38 entidades con sus acciones institucionales, el DIVIPOLA y las sedes desde el Directorio, y corrige lo que la supervisión reportó del rol entidad (sede del usuario, cerrar sesión, Mis Tareas, estilos, sucursal). Psicosocial y Seguimiento suman indicador de atenciones, filtro por dupla y fechas sin bloqueo; el formulario de seguimiento V4 tiene prototipo y siembra en base. Avance: Seguimiento, Barreras, Notificaciones, Tareas y Atención Psicosocial están en producción; Rutas y gestión institucional está en pruebas. El equipo dejó listos 64 cambios para el próximo despliegue a main (corte 13-oct): Rutas y gestión institucional (Mis Acciones Institucionales, Casos Entidad y Mecanismo, checklist de obligaciones, catálogo de competencias y carga masiva del directorio), Atención Psicosocial (cierre y validación de remisiones, contacto inmediato, filtro por dupla) y Seguimiento (vencidos, zona horaria, reapertura por supervisor). Varios de estos cambios corrigen hallazgos que la matriz de SALVIA aún marcaba abiertos porque no se habían reportado como listos. Pendiente: desplegarlos y que SALVIA los valide en producción; Enlace Territorial se valida aparte. | F2: Brayan Marbello / Juan Buitrago | G2: 1 | H2: 46318 | I2: =IF(SUMPRODUCT((Pertenencia!B$2:B$145=1)*(Plan!$D$2:$D$145=3)*(Plan!$J$2:$J$145="Entendimiento"))=0,"",SUMPRODUCT((Pertenencia!B$2:B$145=1)*(Plan!$D$2:$D$145=3)*(Plan!$J$2:$J$145="Entendimiento")*Plan!$E$2:$E$145)/SUMPRODUCT((Pertenencia!B$2:B$145=1)*(Plan!$D$2:$D$145=3)*(Plan!$J$2:$J$145="Entendimiento"))) -> 0.88214286 | J2: =IF(SUMPRODUCT((Pertenencia!B$2:B$145=1)*(Plan!$D$2:$D$145=3)*(Plan!$J$2:$J$145="Construcción y cierre"))=0,"",SUMPRODUCT((Pertenencia!B$2:B$145=1)*(Plan!$D$2:$D$145=3)*(Plan!$J$2:$J$145="Construcción y cierre")*Plan!$E$2:$E$145)/SUMPRODUCT((Pertenencia!B$2:B$145=1)*(Plan!$D$2:$D$145=3)*(Plan!$J$2:$J$145="Construcción y cierre"))) -> 0.58181818 | K2: Módulos contractuales (Anexo Técnico)
A3: M2 | B3: M2 · TAMIZAJE DE FEMINICIDIO | C3: 46218 | D3: =SUMPRODUCT((Pertenencia!C$2:C$145=1)*(Plan!$D$2:$D$145=3)*Plan!$E$2:$E$145)/SUMPRODUCT((Pertenencia!C$2:C$145=1)*(Plan!$D$2:$D$145=3)) -> 0.83181818 | E3: Corte 23-oct: el nuevo Registro V3 está construido en testing (14-oct), con tamizaje, Gestión Salvia, remisión, entidades, barreras y alerta inminente, y pasó QA de punta a punta con Playwright (15-oct, 8 bugs corregidos). Pendiente: nuevo caso sobre registro existente, actualizar caso, ajustes de UI de la supervisión, UAT y paso a main. Avance: Gestión del Conocimiento aprobó el mockup de Reportes, Registro y Alerta Inminente (según el equipo, 13-oct), que incluye el formulario completo del tamizaje de feminicidio con bifurcaciones OSIGD y pareja/no pareja, puntaje y alertas por nivel de riesgo. En producción operan la parametrización de tiempos, la clasificación alto/bajo y la asignación automática. Pendiente: confirmar los rangos del puntaje; el HTML del mockup ya está con el equipo de desarrollo y su paso al servidor de pruebas está prevista para finales de la semana del 13-oct o, a más tardar, a mediados de la semana del 20-oct. Nota: el trabajo del mockup no aparece completo en las horas reportadas; se registra como evidencia en la hoja Trabajo_sin_horas. | F3: Brayan Marbello | G3: 0.55 | H3: 46318 | I3: =IF(SUMPRODUCT((Pertenencia!C$2:C$145=1)*(Plan!$D$2:$D$145=3)*(Plan!$J$2:$J$145="Entendimiento"))=0,"",SUMPRODUCT((Pertenencia!C$2:C$145=1)*(Plan!$D$2:$D$145=3)*(Plan!$J$2:$J$145="Entendimiento")*Plan!$E$2:$E$145)/SUMPRODUCT((Pertenencia!C$2:C$145=1)*(Plan!$D$2:$D$145=3)*(Plan!$J$2:$J$145="Entendimiento"))) -> 0.8875 | J3: =IF(SUMPRODUCT((Pertenencia!C$2:C$145=1)*(Plan!$D$2:$D$145=3)*(Plan!$J$2:$J$145="Construcción y cierre"))=0,"",SUMPRODUCT((Pertenencia!C$2:C$145=1)*(Plan!$D$2:$D$145=3)*(Plan!$J$2:$J$145="Construcción y cierre")*Plan!$E$2:$E$145)/SUMPRODUCT((Pertenencia!C$2:C$145=1)*(Plan!$D$2:$D$145=3)*(Plan!$J$2:$J$145="Construcción y cierre"))) -> 0.68333333 | K3: Módulos contractuales (Anexo Técnico)
A4: M3 | B4: M3 · MEDIDAS DE EMERGENCIA | C4: 46321 | D4: =SUMPRODUCT((Pertenencia!D$2:D$145=1)*(Plan!$D$2:$D$145=3)*Plan!$E$2:$E$145)/SUMPRODUCT((Pertenencia!D$2:D$145=1)*(Plan!$D$2:$D$145=3)) -> 0.35 | E4: Avance: entendimiento documentado en 38 historias de usuario v1.0 (12 grupos, de la remisión a la conclusión, con Cruz Roja y riesgo inminente), que sirven de base al mockup de Medidas de Emergencia; el mockup aprobado de Reportes, Registro y Alerta Inminente ya incluye el formulario de alerta inminente. Pendiente: todo el desarrollo; matriz de campos, lógica de medidas y criterios de aceptación aprobados por el Ministerio. Riesgo: las historias de usuario no cubren familiares ni personas huérfanas (Ley 2530 de 2025). Octubre suma 42 h: 27 h del equipo en los Sprints 19 a 21 y 15 h de gerencia (validación de las historias de usuario y feedback del mockup). El equipo trabajó en las historias de usuario y mockups de Medidas y las primeras pantallas de remisiones de Medidas (PSWYA-849 y 854, en Jira del 22 al 23-oct), además de su adaptación al formulario de seguimiento V4. | F4: Por definir | H4: 46318 | I4: =IF(SUMPRODUCT((Pertenencia!D$2:D$145=1)*(Plan!$D$2:$D$145=3)*(Plan!$J$2:$J$145="Entendimiento"))=0,"",SUMPRODUCT((Pertenencia!D$2:D$145=1)*(Plan!$D$2:$D$145=3)*(Plan!$J$2:$J$145="Entendimiento")*Plan!$E$2:$E$145)/SUMPRODUCT((Pertenencia!D$2:D$145=1)*(Plan!$D$2:$D$145=3)*(Plan!$J$2:$J$145="Entendimiento"))) -> 0.53 | J4: =IF(SUMPRODUCT((Pertenencia!D$2:D$145=1)*(Plan!$D$2:$D$145=3)*(Plan!$J$2:$J$145="Construcción y cierre"))=0,"",SUMPRODUCT((Pertenencia!D$2:D$145=1)*(Plan!$D$2:$D$145=3)*(Plan!$J$2:$J$145="Construcción y cierre")*Plan!$E$2:$E$145)/SUMPRODUCT((Pertenencia!D$2:D$145=1)*(Plan!$D$2:$D$145=3)*(Plan!$J$2:$J$145="Construcción y cierre"))) -> 0.05 | K4: Módulos contractuales (Anexo Técnico)
A5: M4 | B5: M4 · LGBTIQ+ | C5: 46248 | D5: =SUMPRODUCT((Pertenencia!E$2:E$145=1)*(Plan!$D$2:$D$145=3)*Plan!$E$2:$E$145)/SUMPRODUCT((Pertenencia!E$2:E$145=1)*(Plan!$D$2:$D$145=3)) -> 0.825 | E5: Corte 23-oct: las preguntas OSIGD quedaron construidas dentro del Registro V3 en testing. Avance: el mockup aprobado de Reportes, Registro y Alerta Inminente incluye las preguntas OSIGD y el tamizaje diferencial para población LGBTIQ+ dentro del mismo formulario, sin módulo aparte; secciones OSIGHN construidas en psicosocial el 17-sep. Pendiente: construir el MVP en registro y seguimiento; el HTML del mockup ya está con el equipo de desarrollo y su paso al servidor de pruebas está prevista para finales de la semana del 13-oct o, a más tardar, a mediados de la semana del 20-oct. Riesgo: la pregunta OSIGHN aparece hoy donde no corresponde (hallazgo PSI-24). Nota: el trabajo del mockup se registra como evidencia en la hoja Trabajo_sin_horas, sin sumar horas. | F5: Brayan Marbello / Juan Buitrago | G5: 0.01 | H5: 46318 | I5: =IF(SUMPRODUCT((Pertenencia!E$2:E$145=1)*(Plan!$D$2:$D$145=3)*(Plan!$J$2:$J$145="Entendimiento"))=0,"",SUMPRODUCT((Pertenencia!E$2:E$145=1)*(Plan!$D$2:$D$145=3)*(Plan!$J$2:$J$145="Entendimiento")*Plan!$E$2:$E$145)/SUMPRODUCT((Pertenencia!E$2:E$145=1)*(Plan!$D$2:$D$145=3)*(Plan!$J$2:$J$145="Entendimiento"))) -> 0.93333333 | J5: =IF(SUMPRODUCT((Pertenencia!E$2:E$145=1)*(Plan!$D$2:$D$145=3)*(Plan!$J$2:$J$145="Construcción y cierre"))=0,"",SUMPRODUCT((Pertenencia!E$2:E$145=1)*(Plan!$D$2:$D$145=3)*(Plan!$J$2:$J$145="Construcción y cierre")*Plan!$E$2:$E$145)/SUMPRODUCT((Pertenencia!E$2:E$145=1)*(Plan!$D$2:$D$145=3)*(Plan!$J$2:$J$145="Construcción y cierre"))) -> 0.5 | K5: Módulos contractuales (Anexo Técnico)
A6: M5 | B6: M5 · ASP (MODULO WEB) | C6: 46248 | D6: =SUMPRODUCT((Pertenencia!F$2:F$145=1)*(Plan!$D$2:$D$145=3)*Plan!$E$2:$E$145)/SUMPRODUCT((Pertenencia!F$2:F$145=1)*(Plan!$D$2:$D$145=3)) -> 0.68888889 | E6: Corte 23-oct: el formulario ASP de identificación de la víctima quedó construido dentro del Registro V3 en testing. Avance: el mockup aprobado de Reportes, Registro y Alerta Inminente incluye el formulario del módulo web ASP dentro del registro de la víctima. Pendiente: construcción del módulo web; el formulario de registro ya está con el equipo de desarrollo para pasar al servidor de pruebas. Decisión: la solicitud de prórroga del 22-sep pide a la Supervisión definir el tratamiento del desarrollo integral del módulo y su app. Riesgo: los lineamientos de la Dirección de Actividades Sexuales Pagas no se han recibido formalmente. Nota: el trabajo del mockup se registra como evidencia en la hoja Trabajo_sin_horas, sin sumar horas. | F6: Santiago Ramos / Juan Buitrago | G6: 0.18 | H6: 46318 | I6: =IF(SUMPRODUCT((Pertenencia!F$2:F$145=1)*(Plan!$D$2:$D$145=3)*(Plan!$J$2:$J$145="Entendimiento"))=0,"",SUMPRODUCT((Pertenencia!F$2:F$145=1)*(Plan!$D$2:$D$145=3)*(Plan!$J$2:$J$145="Entendimiento")*Plan!$E$2:$E$145)/SUMPRODUCT((Pertenencia!F$2:F$145=1)*(Plan!$D$2:$D$145=3)*(Plan!$J$2:$J$145="Entendimiento"))) -> 0.77857143 | J6: =IF(SUMPRODUCT((Pertenencia!F$2:F$145=1)*(Plan!$D$2:$D$145=3)*(Plan!$J$2:$J$145="Construcción y cierre"))=0,"",SUMPRODUCT((Pertenencia!F$2:F$145=1)*(Plan!$D$2:$D$145=3)*(Plan!$J$2:$J$145="Construcción y cierre")*Plan!$E$2:$E$145)/SUMPRODUCT((Pertenencia!F$2:F$145=1)*(Plan!$D$2:$D$145=3)*(Plan!$J$2:$J$145="Construcción y cierre"))) -> 0.375 | K6: Módulos contractuales (Anexo Técnico)
A7: APP | B7: APP MOVIL MASP (M5) | C7: 46260 | D7: =SUMPRODUCT((Pertenencia!G$2:G$145=1)*(Plan!$D$2:$D$145=3)*Plan!$E$2:$E$145)/SUMPRODUCT((Pertenencia!G$2:G$145=1)*(Plan!$D$2:$D$145=3)) -> 0.485 | E7: Avance: lista de contactos, Home, información de programas y rediseño visual (16-sep); la app apunta al dominio productivo y se subió una nueva versión Android el 23-sep; el informe del 17-sep reporta Seguridad y SOS en Play Store. Pendiente: directorio de entidades, sincronización y bitácora, integración con la Línea 155, App Store, QA y UAT. Decisión: la prórroga solo cubre cerrar lo ya desarrollado, sin pantallas nuevas. | F7: Santiago Ramos | G7: 0.16 | H7: 46318 | I7: =IF(SUMPRODUCT((Pertenencia!G$2:G$145=1)*(Plan!$D$2:$D$145=3)*(Plan!$J$2:$J$145="Entendimiento"))=0,"",SUMPRODUCT((Pertenencia!G$2:G$145=1)*(Plan!$D$2:$D$145=3)*(Plan!$J$2:$J$145="Entendimiento")*Plan!$E$2:$E$145)/SUMPRODUCT((Pertenencia!G$2:G$145=1)*(Plan!$D$2:$D$145=3)*(Plan!$J$2:$J$145="Entendimiento"))) -> 0.65714286 | J7: =IF(SUMPRODUCT((Pertenencia!G$2:G$145=1)*(Plan!$D$2:$D$145=3)*(Plan!$J$2:$J$145="Construcción y cierre"))=0,"",SUMPRODUCT((Pertenencia!G$2:G$145=1)*(Plan!$D$2:$D$145=3)*(Plan!$J$2:$J$145="Construcción y cierre")*Plan!$E$2:$E$145)/SUMPRODUCT((Pertenencia!G$2:G$145=1)*(Plan!$D$2:$D$145=3)*(Plan!$J$2:$J$145="Construcción y cierre"))) -> 0.39230769 | K7: Módulos contractuales (Anexo Técnico)
A8: H06 | B8: ARQUITECTURA EAV-DAG | C8: 46156 | D8: =SUMPRODUCT((Pertenencia!H$2:H$145=1)*(Plan!$D$2:$D$145=3)*Plan!$E$2:$E$145)/SUMPRODUCT((Pertenencia!H$2:H$145=1)*(Plan!$D$2:$D$145=3)) -> 0.905 | E8: Avance: arquitectura EAV-DAG implementada y sosteniendo los módulos en producción. Pendiente: casos migrados con formularios vacíos o sin esquema de seguimiento (SEG-01 y SEG-02), que requieren script en producción. Riesgo: el mecanismo de interoperabilidad con SIVIGE sigue sin definición técnica. | F8: Andres Posada / Andres Ascencio | G8: 1 | H8: 46318 | I8: =IF(SUMPRODUCT((Pertenencia!H$2:H$145=1)*(Plan!$D$2:$D$145=3)*(Plan!$J$2:$J$145="Entendimiento"))=0,"",SUMPRODUCT((Pertenencia!H$2:H$145=1)*(Plan!$D$2:$D$145=3)*(Plan!$J$2:$J$145="Entendimiento")*Plan!$E$2:$E$145)/SUMPRODUCT((Pertenencia!H$2:H$145=1)*(Plan!$D$2:$D$145=3)*(Plan!$J$2:$J$145="Entendimiento"))) -> 0.89444444 | J8: =IF(SUMPRODUCT((Pertenencia!H$2:H$145=1)*(Plan!$D$2:$D$145=3)*(Plan!$J$2:$J$145="Construcción y cierre"))=0,"",SUMPRODUCT((Pertenencia!H$2:H$145=1)*(Plan!$D$2:$D$145=3)*(Plan!$J$2:$J$145="Construcción y cierre")*Plan!$E$2:$E$145)/SUMPRODUCT((Pertenencia!H$2:H$145=1)*(Plan!$D$2:$D$145=3)*(Plan!$J$2:$J$145="Construcción y cierre"))) -> 1 | K8: Hitos transversales
A9: H07 | B9: GOBERNANZA Y GESTION DEL PROYECTO | C9: 46325 | D9: =SUMPRODUCT((Pertenencia!I$2:I$145=1)*(Plan!$D$2:$D$145=3)*Plan!$E$2:$E$145)/SUMPRODUCT((Pertenencia!I$2:I$145=1)*(Plan!$D$2:$D$145=3)) -> 0.87142857 | E9: Avance: solicitud de prórroga hasta el 15-dic radicada el 22-sep, con informe de alcance y riesgos del 17-sep; bitácora de ajustes con 112 ítems, sesiones de revisión con SALVIA y formulario de hallazgos en uso; 3.924 de 5.396 horas ejecutadas a agosto (72,7 %). Pendiente: decisión de la Supervisión sobre la prórroga y el tratamiento de ASP, control de cambios para los nuevos requerimientos y cronograma actualizado. Riesgo: el plazo vigente vence el 26-oct. | F9: Andres Posada | G9: 0.95 | H9: 46318 | I9: =IF(SUMPRODUCT((Pertenencia!I$2:I$145=1)*(Plan!$D$2:$D$145=3)*(Plan!$J$2:$J$145="Entendimiento"))=0,"",SUMPRODUCT((Pertenencia!I$2:I$145=1)*(Plan!$D$2:$D$145=3)*(Plan!$J$2:$J$145="Entendimiento")*Plan!$E$2:$E$145)/SUMPRODUCT((Pertenencia!I$2:I$145=1)*(Plan!$D$2:$D$145=3)*(Plan!$J$2:$J$145="Entendimiento"))) -> 0.87058824 | J9: =IF(SUMPRODUCT((Pertenencia!I$2:I$145=1)*(Plan!$D$2:$D$145=3)*(Plan!$J$2:$J$145="Construcción y cierre"))=0,"",SUMPRODUCT((Pertenencia!I$2:I$145=1)*(Plan!$D$2:$D$145=3)*(Plan!$J$2:$J$145="Construcción y cierre")*Plan!$E$2:$E$145)/SUMPRODUCT((Pertenencia!I$2:I$145=1)*(Plan!$D$2:$D$145=3)*(Plan!$J$2:$J$145="Construcción y cierre"))) -> 0.875 | K9: Hitos transversales
A10: H08 | B10: QA Y PRUEBAS | C10: 46265 | D10: =SUMPRODUCT((Pertenencia!J$2:J$145=1)*(Plan!$D$2:$D$145=3)*Plan!$E$2:$E$145)/SUMPRODUCT((Pertenencia!J$2:J$145=1)*(Plan!$D$2:$D$145=3)) -> 0.32727273 | E10: Corte 23-oct: plan de QA de Registro V3 ejecutado con Playwright (25 casos, 8 bugs corregidos) y pruebas unitarias nuevas en migraciones y estados de caso. Avance: la matriz de hallazgos de SALVIA, con revisión de Kreivo del 8-oct, da por cerrados 107 de 159 hallazgos (29 de 43 en Seguimiento y 78 de 104 en Psicosocial); Rutas sigue con 11 de 12 abiertos desde el 8-sep, aunque el despliegue del 13-oct atiende varios. Pendiente: UAT formal, pruebas de estrés, seguridad y accesibilidad; QA y UAT de la app. Riesgo: las pruebas de punta a punta de Rutas dependen de usuarios y datos de prueba (RUT-17). | F10: Brayan Marbello | G10: 0.65 | H10: 46318 | I10: =IF(SUMPRODUCT((Pertenencia!J$2:J$145=1)*(Plan!$D$2:$D$145=3)*(Plan!$J$2:$J$145="Entendimiento"))=0,"",SUMPRODUCT((Pertenencia!J$2:J$145=1)*(Plan!$D$2:$D$145=3)*(Plan!$J$2:$J$145="Entendimiento")*Plan!$E$2:$E$145)/SUMPRODUCT((Pertenencia!J$2:J$145=1)*(Plan!$D$2:$D$145=3)*(Plan!$J$2:$J$145="Entendimiento"))) | J10: =IF(SUMPRODUCT((Pertenencia!J$2:J$145=1)*(Plan!$D$2:$D$145=3)*(Plan!$J$2:$J$145="Construcción y cierre"))=0,"",SUMPRODUCT((Pertenencia!J$2:J$145=1)*(Plan!$D$2:$D$145=3)*(Plan!$J$2:$J$145="Construcción y cierre")*Plan!$E$2:$E$145)/SUMPRODUCT((Pertenencia!J$2:J$145=1)*(Plan!$D$2:$D$145=3)*(Plan!$J$2:$J$145="Construcción y cierre"))) -> 0.32727273 | K10: Hitos transversales
A11: H09 | B11: DESPLIEGUE EN PRODUCCION | C11: 46326 | D11: =SUMPRODUCT((Pertenencia!K$2:K$145=1)*(Plan!$D$2:$D$145=3)*Plan!$E$2:$E$145)/SUMPRODUCT((Pertenencia!K$2:K$145=1)*(Plan!$D$2:$D$145=3)) -> 0.4 | E11: Corte 23-oct: testing integra los 64 cambios del 13-oct y 29 commits más (PR #117 a #132); main sigue sin cambios desde el 10-sep, así que el despliegue a producción sigue pendiente. Avance: 64 cambios listos para subir a main en el próximo despliegue (corte 13-oct), con lo que se cierra la brecha de main sin cambios desde el 10-sep. En producción: Seguimiento, Barreras, Notificaciones, Tareas y Psicosocial; app Android publicada. Pendiente: ejecutar el despliegue, pasar Rutas a producción con regresión sobre Seguimiento y validar Enlace Territorial, que va aparte. Riesgo: desplegar 64 cambios juntos exige una ventana con respaldo y una ronda de validación con SALVIA. | F11: Camilo Arias | G11: 0.7 | H11: 46318 | I11: =IF(SUMPRODUCT((Pertenencia!K$2:K$145=1)*(Plan!$D$2:$D$145=3)*(Plan!$J$2:$J$145="Entendimiento"))=0,"",SUMPRODUCT((Pertenencia!K$2:K$145=1)*(Plan!$D$2:$D$145=3)*(Plan!$J$2:$J$145="Entendimiento")*Plan!$E$2:$E$145)/SUMPRODUCT((Pertenencia!K$2:K$145=1)*(Plan!$D$2:$D$145=3)*(Plan!$J$2:$J$145="Entendimiento"))) | J11: =IF(SUMPRODUCT((Pertenencia!K$2:K$145=1)*(Plan!$D$2:$D$145=3)*(Plan!$J$2:$J$145="Construcción y cierre"))=0,"",SUMPRODUCT((Pertenencia!K$2:K$145=1)*(Plan!$D$2:$D$145=3)*(Plan!$J$2:$J$145="Construcción y cierre")*Plan!$E$2:$E$145)/SUMPRODUCT((Pertenencia!K$2:K$145=1)*(Plan!$D$2:$D$145=3)*(Plan!$J$2:$J$145="Construcción y cierre"))) -> 0.4 | K11: Hitos transversales
A12: H10 | B12: TRANSFERENCIA DE CONOCIMIENTO | C12: 46326 | D12: =SUMPRODUCT((Pertenencia!L$2:L$145=1)*(Plan!$D$2:$D$145=3)*Plan!$E$2:$E$145)/SUMPRODUCT((Pertenencia!L$2:L$145=1)*(Plan!$D$2:$D$145=3)) -> 0.25416667 | E12: Corte 28-oct: la entidad usa los 15 videos de uso como material de capacitación masiva, a satisfacción, y aceptó parte de ellos para producción (según el equipo). Avance: 15 videos de uso de SALVIA Web (Seguimiento, Barreras y Notificaciones), Mapa de navegación y consolidado de historias de usuario, compartidos con la entidad en agosto; 9 manuales técnicos en PDF (8 de SALVIA Web y 1 de la App MASP) y la Red de acción SALVIA, publicada en el tablero de hitos (19-oct). Pendiente: videos y manuales de usuario de Psicosocial, Medidas, Rutas y Registro, videos de uso de la App, plan de capacitación aprobado, capacitaciones y su validación por SALVIA. Riesgo: 33 de los 100 hallazgos abiertos se resuelven con proceso o entendimiento, lo que indica que la capacitación no debería esperar al final. | F12: Andres Ascencio / Brayan Marbello | G12: 0.4 | H12: 46318 | I12: =IF(SUMPRODUCT((Pertenencia!L$2:L$145=1)*(Plan!$D$2:$D$145=3)*(Plan!$J$2:$J$145="Entendimiento"))=0,"",SUMPRODUCT((Pertenencia!L$2:L$145=1)*(Plan!$D$2:$D$145=3)*(Plan!$J$2:$J$145="Entendimiento")*Plan!$E$2:$E$145)/SUMPRODUCT((Pertenencia!L$2:L$145=1)*(Plan!$D$2:$D$145=3)*(Plan!$J$2:$J$145="Entendimiento"))) | J12: =IF(SUMPRODUCT((Pertenencia!L$2:L$145=1)*(Plan!$D$2:$D$145=3)*(Plan!$J$2:$J$145="Construcción y cierre"))=0,"",SUMPRODUCT((Pertenencia!L$2:L$145=1)*(Plan!$D$2:$D$145=3)*(Plan!$J$2:$J$145="Construcción y cierre")*Plan!$E$2:$E$145)/SUMPRODUCT((Pertenencia!L$2:L$145=1)*(Plan!$D$2:$D$145=3)*(Plan!$J$2:$J$145="Construcción y cierre"))) -> 0.25416667 | K12: Hitos transversales
A13: H11 | B13: ENTREGA CONTRACTUAL Y DERECHOS DE AUTOR | C13: 46325 | D13: =SUMPRODUCT((Pertenencia!M$2:M$145=1)*(Plan!$D$2:$D$145=3)*Plan!$E$2:$E$145)/SUMPRODUCT((Pertenencia!M$2:M$145=1)*(Plan!$D$2:$D$145=3)) -> 0.17307692 | E13: Avance: sin inicio. Pendiente: registro ante la DNDA, publicación final en tiendas y entrega del código fuente; el cronograma propuesto los ubica del 7 al 15-dic. Riesgo: con el plazo vigente al 26-oct no hay ventana para estas actividades si la prórroga no se aprueba. | F13: Andres Posada | G13: 0 | H13: 46318 | I13: =IF(SUMPRODUCT((Pertenencia!M$2:M$145=1)*(Plan!$D$2:$D$145=3)*(Plan!$J$2:$J$145="Entendimiento"))=0,"",SUMPRODUCT((Pertenencia!M$2:M$145=1)*(Plan!$D$2:$D$145=3)*(Plan!$J$2:$J$145="Entendimiento")*Plan!$E$2:$E$145)/SUMPRODUCT((Pertenencia!M$2:M$145=1)*(Plan!$D$2:$D$145=3)*(Plan!$J$2:$J$145="Entendimiento"))) | J13: =IF(SUMPRODUCT((Pertenencia!M$2:M$145=1)*(Plan!$D$2:$D$145=3)*(Plan!$J$2:$J$145="Construcción y cierre"))=0,"",SUMPRODUCT((Pertenencia!M$2:M$145=1)*(Plan!$D$2:$D$145=3)*(Plan!$J$2:$J$145="Construcción y cierre")*Plan!$E$2:$E$145)/SUMPRODUCT((Pertenencia!M$2:M$145=1)*(Plan!$D$2:$D$145=3)*(Plan!$J$2:$J$145="Construcción y cierre"))) -> 0.17307692 | K13: Hitos transversales

Sheet Hitos
A1: No. | B1: HITO | C1: FECHA | D1: ENTREGABLE | E1: ID_ANTERIOR
A2: M1 | B2: M1 · SEGUIMIENTO A LOS CASOS | C2: 46191 | D2: Modulo 1 del Anexo Tecnico. Control y seguimiento de casos por la Linea 155, identificacion de barreras en la ruta de atencion, comunicaciones con entidades y cierre de casos. Incluye Rutas y Barreras y Atencion Psicosocial | E2: H01
A3: M2 | B3: M2 · TAMIZAJE DE FEMINICIDIO | C3: 46218 | D3: Modulo 2 del Anexo Tecnico. Valoracion inicial estructurada del nivel de riesgo de feminicidio con criterios tecnicos estandarizados | E3: H02
A4: M3 | B4: M3 · MEDIDAS DE EMERGENCIA | C4: 46321 | D4: Modulo 3 del Anexo Tecnico. Registro y valoracion estructurada de necesidades de personas en riesgo de feminicidio y de familiares de victimas, para priorizar casos y gestionar intervenciones | E4: Nuevo
A5: M4 | B5: M4 · LGBTIQ+ | C5: 46248 | D5: Modulo 4 del Anexo Tecnico. Profundizar en particularidades, necesidades diferenciadas y abordaje especializado de casos LGBTIQ+ o de violencia por prejuicio | E5: H04
A6: M5 | B6: M5 · ASP (MODULO WEB) | C6: 46248 | D6: Modulo 5 del Anexo Tecnico. Caracterizacion ampliada de personas en actividades sexuales pagas dentro de SALVIA | E6: H03
A7: APP | B7: APP MOVIL MASP (M5) | C7: 46260 | D7: Modulo 5 del Anexo Tecnico. Aplicacion movil para prevencion de violencias en actividades sexuales pagas, con orientacion, rutas de atencion y reporte seguro | E7: H05
A8: H06 | B8: ARQUITECTURA EAV-DAG | C8: 46156 | D8: Nueva arquitectura de datos EAV-DAG implementada, scripts de migracion desde el modelo SOG y diccionario de datos entregado | E8: H06
A9: H07 | B9: GOBERNANZA Y GESTION DEL PROYECTO | C9: 46325 | D9: Plan de gestion del proyecto, matriz de riesgos, comites tecnicos semanales, reportes mensuales y gestion del cambio ejecutados durante todo el contrato | E9: H07
A10: H08 | B10: QA Y PRUEBAS | C10: 46265 | D10: Escenarios de prueba ejecutados: pruebas unitarias, de carga, vulnerabilidad y UAT para SALVIA Web y App MASP con certificacion de la OTI | E10: H08
A11: H09 | B11: DESPLIEGUE EN PRODUCCION | C11: 46326 | D11: Migracion, despliegue de APIs y paso a produccion oficial de SALVIA Web y App MASP con recibo a satisfaccion del Ministerio | E11: H09
A12: H10 | B12: TRANSFERENCIA DE CONOCIMIENTO | C12: 46326 | D12: Manuales de usuario, videos de uso, capacitaciones a funcionarios y listados de asistencia oficiales entregados | E12: H10
A13: H11 | B13: ENTREGA CONTRACTUAL Y DERECHOS DE AUTOR | C13: 46325 | D13: Registro ante DNDA, publicacion oficial en tiendas (Play Store y App Store) y cesion formal del codigo fuente al Ministerio de Igualdad | E13: H11

Sheet Pertenencia
A1: ID | B1: M1 | C1: M2 | D1: M3 | E1: M4 | F1: M5 | G1: APP | H1: H06 | I1: H07 | J1: H08 | K1: H09 | L1: H10 | M1: H11
A2: 1 | B2: 0 | C2: 0 | D2: 0 | E2: 0 | F2: 0 | G2: 0 | H2: 0 | I2: 1 | J2: 0 | K2: 0 | L2: 0 | M2: 0
A3: 1.1 | B3: 0 | C3: 0 | D3: 0 | E3: 0 | F3: 0 | G3: 0 | H3: 0 | I3: 1 | J3: 0 | K3: 0 | L3: 0 | M3: 0
A4: 1.1.1 | B4: 0 | C4: 0 | D4: 0 | E4: 0 | F4: 0 | G4: 0 | H4: 0 | I4: 1 | J4: 0 | K4: 0 | L4: 0 | M4: 0
A5: 1.1.2 | B5: 0 | C5: 0 | D5: 0 | E5: 0 | F5: 0 | G5: 0 | H5: 0 | I5: 1 | J5: 0 | K5: 0 | L5: 0 | M5: 0
A6: 2 | B6: 0 | C6: 0 | D6: 0 | E6: 0 | F6: 1 | G6: 1 | H6: 1 | I6: 1 | J6: 0 | K6: 0 | L6: 0 | M6: 0
A7: 2.1 | B7: 0 | C7: 0 | D7: 0 | E7: 0 | F7: 1 | G7: 0 | H7: 1 | I7: 1 | J7: 0 | K7: 0 | L7: 0 | M7: 0
A8: 2.1.1 | B8: 0 | C8: 0 | D8: 0 | E8: 0 | F8: 0 | G8: 0 | H8: 1 | I8: 1 | J8: 0 | K8: 0 | L8: 0 | M8: 0
A9: 2.1.2 | B9: 0 | C9: 0 | D9: 0 | E9: 0 | F9: 0 | G9: 0 | H9: 0 | I9: 1 | J9: 0 | K9: 0 | L9: 0 | M9: 0
A10: 2.1.3 | B10: 0 | C10: 0 | D10: 0 | E10: 0 | F10: 1 | G10: 0 | H10: 0 | I10: 1 | J10: 0 | K10: 0 | L10: 0 | M10: 0
A11: 2.1.4 | B11: 0 | C11: 0 | D11: 0 | E11: 0 | F11: 0 | G11: 0 | H11: 0 | I11: 1 | J11: 0 | K11: 0 | L11: 0 | M11: 0
A12: 2.2 | B12: 0 | C12: 0 | D12: 0 | E12: 0 | F12: 1 | G12: 1 | H12: 0 | I12: 0 | J12: 0 | K12: 0 | L12: 0 | M12: 0
A13: 2.2.1 | B13: 0 | C13: 0 | D13: 0 | E13: 0 | F13: 0 | G13: 1 | H13: 0 | I13: 0 | J13: 0 | K13: 0 | L13: 0 | M13: 0
... A145: 13.2.1 | B145: 0 | C145: 0 | D145: 0 | E145: 0 | F145: 0 | G145: 0 | H145: 0 | I145: 1 | J145: 0 | K145: 0 | L145: 0 | M145: 0

Sheet Meses
A1: Mes | B1: Etiqueta | C1: Horas_B1 | D1: Horas_B2 | E1: Aspectos_relevantes | F1: Nota
A2: 2026-02 | B2: Feb 2026 | C2: 191 | D2: 0 | E2: Arranque: entendimiento del sistema heredado, auditoría del código y diagnóstico de mejoras urgentes de seguridad. Mockup inicial y primeras historias de usuario del Módulo 1 de Seguimiento. Hojas de vida del equipo entregadas; Gantt y herramienta de control de horas diseñados.
A3: 2026-03 | B3: Mar 2026 | C3: 594 | D3: 0 | E3: Arquitectura EAV-DAG diseñada y adoptada para formularios dinámicos sin alterar el esquema relacional. Requerimientos e historias de usuario de Seguimiento y mapeo del instrumento Kobo/155 al diccionario de datos. Plan de Trabajo v1.0 entregado y cinco mesas técnicas con SALVIA.
A4: 2026-04 | B4: Abr 2026 | C4: 473 | D4: 38 | E4: Primera construcción full-stack de Seguimiento: detalle del caso, timeline, reasignaciones y reporte unificado en Excel. Levantamiento y mockups de Barreras aprobados. Ambiente temporal con CI/CD mientras llegaba el servidor oficial del Ministerio. Primeras 38 horas de la Bolsa 2: requerimientos y flujos de la App MASP.
A5: 2026-05 | B5: May 2026 | C5: 512 | D5: 2.5 | E5: Despliegue en el ambiente de pruebas del Ministerio con CI/CD automatizado. Construcción de Barreras, Notificaciones, Oficios, Tareas, protocolo 3x3 y formulario de cierre. 139 horas de QA y pruebas piloto presenciales con usuarios reales. App firmada y enviada a publicación en Google Play.
A6: 2026-06 | B6: Jun 2026 | C6: 702 | D6: 6 | E6: Salida a producción oficial del módulo de Seguimiento y del Dashboard de KPIs de cinco niveles. Migración de la infraestructura a servidores Linux en AWS y PostgreSQL en RDS, con dominios salvia-colombia.co. Migración de casos activos de riesgo alto y bajo, manual de usuario y primeras capacitaciones presenciales. Nombre identitario (enfoque LGBTIQ+) aplicado en todo el portal.
A7: 2026-07 | B7: Jul 2026 | C7: 290 | D7: 471.5 | E7: Barreras y Notificaciones pasan a producción (9-jul). Construcción del módulo de Atención Psicosocial y del portal de entidades externas. Medidas de Emergencia se pausa por decisión ejecutiva del 6-jul para priorizar Barreras, Rutas y Psicosocial. Solicitud de modificación contractual de horas radicada el 23-jul; la Bolsa 2 registra 471,5 horas en el mes.
A8: 2026-08 | B8: Ago 2026 | C8: 320 | D8: 308 | E8: Actualización de los cuatro formularios de seguimiento y reasignación masiva de unos 3.000 casos. Primera iteración completa de QA del módulo de Atención Psicosocial. Flujos de Rutas y Decisiones del Comité construidos. Matrices de hallazgos unificadas; mapa mental y Gantt de cierre por módulo.
A9: 2026-09 | B9: Sep 2026 | C9: 184.5 | D9: 218 | E9: Atención Psicosocial migrada a producción. Flujo ciudadano Reportar Aquí y Gestión de Reportes construidos. Rutas pasa a pruebas: Mis Acciones Institucionales, Casos Mecanismo y carga masiva de entidades. Acumulado de 4.310,5 horas (79,9 % del contrato) y bitácora única de hallazgos con SALVIA.
A10: 2026-10 | B10: Oct 2026 · corte 23-oct | C10: 288.5 | D10: 180 | E10: Registro V3 construido en testing con QA en Playwright; migración de Alcaldías y 38 entidades con acciones institucionales para el rol entidad. Gestión del Conocimiento aprobó el mockup de Reportes, Registro y Alerta Inminente, que incluye los formularios de tamizaje, LGBTIQ+ y ASP; el HTML ya está con el equipo de desarrollo y su paso al servidor de pruebas está prevista para finales de la semana del 13-oct o, a más tardar, a mediados de la semana del 20-oct. 64 cambios listos para el próximo despliegue a main (corte 13-oct), varios de ellos hallazgos que el equipo no había reportado como resueltos. La matriz de hallazgos de SALVIA da por cerrados 107 de 159 (revisión Kreivo del 8-oct). Solicitud de prórroga hasta el 15-dic radicada el 22-sep, pendiente de decisión. Entendimiento de Reporte y Registro (mockup del 27-sep) y de Medidas de Emergencia (38 historias de usuario). | F10: Corte de avance al 23-oct; incluye los 64 cambios del 13-oct y 29 commits más, todos en testing y aún no desplegados en main ni validados por SALVIA. Horas de octubre: 468.5 h (288.5 h de los Sprints 19 a 21 validadas con Jira y 180 h de gerencia de Andrés Posada del informe INF-SGC-09, que no están en Jira). Las horas del equipo van a Bolsa 1 y las de gerencia a Bolsa 2, por decisión de la gerencia con la discrecionalidad otorgada para usar las bolsas.

Sheet Fichas_Mes
A1: Mes | B1: ID_Hito | C1: Resumen
A2: 2026-02 | B2: M1 | C2: Avance: levantamiento de flujos de proceso enviados por el Ministerio, borrador SRS del Módulo 1 de Seguimiento e integración inicial de Historias de Usuario en el Mockup Dashboard. Pendiente: definición de nuevas tablas relacionales y desarrollo de pantallas operativas. Arquitectura: auditoría del código heredado y levantamiento del diccionario de datos inicial.
A3: 2026-02 | B3: M2 | C3: Avance: redacción de historia de usuario inicial para unificación multicanal de reportes y valoración de riesgo por el Agente Integral. Pendiente: mapeo completo del instrumento Kobo/155 y construcción del motor de reglas.
A4: 2026-02 | B4: H06 | C4: Avance: auditoría técnica del código fuente heredado, diccionario de datos, atributos de tablas, guía de instalación local y diagnóstico de mejoras urgentes de seguridad. Riesgo: alta deuda técnica y acoplamiento en el sistema heredado.
A5: 2026-02 | B5: H07 | C5: Avance: entrega y validación de hojas de vida del equipo, diseño del Gantt y herramienta de control de horas conectada al Dashboard; 191 horas ejecutadas en Bolsa 1 (100% del mes).
A6: 2026-03 | B6: M1 | C6: Avance: levantamiento de requerimientos funcionales y 79 horas de redacción de Historias de Usuario de Seguimiento ancladas a Figma; simulación funcional v4.1 con formulario Kobo y revisión del código actual del módulo. Pendiente: construcción de pantallas Vue y endpoints en Go.
A7: 2026-03 | B7: M2 | C7: Avance: mapeo completo de las preguntas del instrumento actual (Kobo/155) hacia el diccionario de datos (DICCIONARIO_GAD) y definición de reglas de valoración de riesgo Extremo/Alto vs. Moderado/Bajo. Pendiente: implementación del motor DAG en base de datos.
A8: 2026-03 | B8: H06 | C8: Avance: diseño formal de la arquitectura EAV-DAG, propuesta de saneamiento de deuda técnica, revisión de backups y puesta en marcha de la capa DAO y modelos en Go. Decisión: adopción del modelo EAV-DAG sobre tabla pivote para soportar formularios dinámicos sin alterar el esquema relacional.
A9: 2026-03 | B9: H07 | C9: Avance: entrega del Plan de Trabajo v1.0, cronograma Gantt con KPIs por obligación y actas de mesas técnicas de marzo; 785 horas acumuladas a marzo (14,5 % del contrato).
A10: 2026-04 | B10: M1 | C10: Avance: construcción full-stack (Go/GORM + Vue 3) de Detalle del Caso, Detalle de Seguimiento, Mis Seguimientos del Día, Timeline, Reasignaciones y Reporte Unificado Excel (V1+V2); levantamiento y mockups del módulo de Barreras aprobados. Pendiente: pruebas integrales en el servidor oficial del Ministerio.
A11: 2026-04 | B11: M2 | C11: Avance: construcción del motor DAG que procesa el árbol de decisiones del tamizaje y visualización del nivel de riesgo en el detalle del caso. Pendiente: integración con los nuevos formularios dinámicos de seguimiento.
A12: 2026-04 | B12: APP | C12: Avance: 38 horas ejecutadas en Bolsa 2; levantamiento de requerimientos y flujos de navegación con el equipo ASP, diseño de interfaz en Figma y definición de integración con el Core SALVIA. Pendiente: compilación y firma de la primera versión para Google Play Store.
... A34: 2026-08 | B34: H10 | C34: Avance: 15 videos de uso de SALVIA Web (Seguimiento, Barreras y Notificaciones), el Mapa de navegación de SALVIA y el consolidado de historias de usuario, compartidos con la entidad en el cobro de agosto.

Sheet Tareas
A1: Task ID | B1: Nombre_tarea | C1: Item_EDT | D1: Observacion
A2: T-101 | B2: Documentación y Metodología (SALVIA Web) | C2: 4.1.1
A3: T-102 | B3: Documentación y Metodología (App MASP) | C3: 4.2.8
A4: T-103 | B4: Historias de Usuario Actuales | C4: 4.1.2
A5: T-104 | B5: Arquitectura Actual | C5: 4.1.3
A6: T-201 | B6: Presentación, Aprobación y Uso de Mockup Kreivo-Salvia | C6: 2.1.1
A7: T-202 | B7: Firma de Acta de Alcance y SLA | C7: 2.1.2
A8: T-203 | B8: Módulo Web ASP: Variables de Riesgo | C8: 2.1.3
A9: T-204 | B9: App MASP: Diseño de interfaz segura | C9: 2.2.1
A10: T-205 | B10: App MASP: Alertas y Push Notifications | C10: 2.2.2
A11: T-206 | B11: App MASP: Integración con Core SALVIA | C11: 2.2.3
A12: T-207 | B12: Gantt Plan de trabajo Kreivo-Salvia | C12: 2.1.4
A13: T-301 | B13: Diseño y Lógica: Landing Page, Login y Captcha | C13: 3.1.1
... A20: T-403 | B20: Diagramas - Figma y Diccionario de datos | C20: 4.2.3
A21: T-404 | B21: Diagramas - Figma y Diccionario de datos (Bolsa 2) | C21: 4.3.1 | D21: En TimeLogs se usó sobre todo para coordinación de sprints (Bolsa 2)
A22: T-405 | B22: Actas de mesas técnicas | C22: 4.2.4
A23: T-406 | B23: Historias de Usuario - Anclado a Figma | C23: 4.2.5
A24: T-407 | B24: Kobo a Zenkit | C24: 4.2.6
A25: T-408 | B25: Integración Data SOG hacia EAV-DAG | C25: 4.2.7
A26: T-501 | B26: Sprint 1: Setup Entornos, BD y Seguridad | C26: 5.1.1
A27: T-502 | B27: Sprint 2: Módulos de Registro y Motor de Tamizaje | C27: 5.1.2
A28: T-503 | B28: Sprint 3: Dashboard de Trazabilidad y Alertas | C28: 5.1.3
A29: T-504 | B29: Sprint 4: Desarrollo App MASP | C29: 5.2.1
A30: T-505 | B30: Sprint 5: Integración SIVIGE (Interoperabilidad) | C30: 5.1.4 | D30: En TimeLogs incluye backend de Rutas y reasignación masiva, no SIVIGE
A31: T-506 | B31: Ejecución de Pruebas Unitarias y de Carga (sprint) | C31: 5.2.2
A32: T-601 | B32: BI: Diseño de Dashboards y ETL | C32: 6.1.1
A33: T-602 | B33: Adopción: Manuales y Capacitación | C33: 6.1.2
A34: T-603 | B34: Despliegue: Migración a Producción (App) | C34: 6.2.1
A35: T-604 | B35: Soporte: Activación Mesa de Ayuda | C35: 6.2.2
A36: T-605 | B36: Ejecución de Pruebas Unitarias y de Carga (App) | C36: 6.2.3 | D36: En TimeLogs se usó para construir Atención Psicosocial, Rutas y Reportar Aquí (Bolsa 2), no para pruebas de la app
A37: T-606 | B37: Setup Entornos, BD Postgres y Seguridad | C37: 6.1.3
A38: T-607 | B38: Setup Entornos y Seguridad API (App MASP) | C38: 6.2.4
A39: T-608 | B39: Módulos Recepción y Motor de Tamizaje (Web) | C39: 6.1.4
A40: T-609 | B40: Módulo de Seguimiento y Tableros BI / ETL | C40: 6.1.5
A41: T-610 | B41: Desarrollo Interfaz y Lógica App Móvil MASP | C41: 6.2.5 | D41: En TimeLogs incluye mockups de Rutas y modales de Psicosocial
A42: T-702 | B42: Ajustes Post-UAT y Estabilización | C42: 7.2.1
A43: T-703 | B43: Transferencia de Conocimiento y Capacitación | C43: 7.1.2
A44: T-705 | B44: Paso a Producción Oficial SALVIA | C44: 7.1.3
A45: T-707 | B45: QA Unitarias, Carga y Vulnerabilidad (SALVIA Web) | C45: 7.1.5
A46: T-708 | B46: QA Unitarias, Estrés y Vulnerabilidad (App MASP) | C46: 7.2.3
A47: T-709 | B47: Pruebas de Aceptación de Usuario UAT (SALVIA Web) | C47: 7.1.6
A48: T-710 | B48: Pruebas de Aceptación de Usuario UAT (App MASP) | C48: 7.2.4
A49: T-801 | B49: Migración y Recibo en Producción (SALVIA) | C49: 8.1.1
A50: T-802 | B50: Despliegue de APIs a producción (MASP) | C50: 8.2.1
A51: T-901 | B51: Validación final de migración y recibo | C51: 9.1.1
A52: T-1201 | B52: Comités Técnicos, Gestión de Riesgos y Reportes (Bolsa 1) | C52: 13.1.1
A53: T-1202 | B53: Comités Técnicos, Gestión de Riesgos y Reportes (Bolsa 2) | C53: 13.2.1
A54: J-4.5.1 | B54: Historias de usuario de Medidas de Emergencia (Jira, octubre) | C54: 4.5.1 | D54: Agregada para las horas de octubre de la hoja Horas_Jira
A55: J-4.5.2 | B55: Mockups de Medidas de Emergencia (Jira, octubre) | C55: 4.5.2 | D55: Agregada para las horas de octubre de la hoja Horas_Jira
A56: J-6.1.8 | B56: Nuevo formulario de Reporte y Registro (Jira, octubre) | C56: 6.1.8 | D56: Agregada para las horas de octubre de la hoja Horas_Jira
A57: J-6.1.9 | B57: Medidas de Emergencia: pantallas y flujo (Jira, octubre) | C57: 6.1.9 | D57: Agregada para las horas de octubre de la hoja Horas_Jira
A58: J-6.1.11 | B58: Atención Psicosocial (Jira, octubre) | C58: 6.1.11 | D58: Agregada para las horas de octubre de la hoja Horas_Jira
A59: J-6.1.12 | B59: Rutas y gestión institucional (Jira, octubre) | C59: 6.1.12 | D59: Agregada para las horas de octubre de la hoja Horas_Jira

Sheet Horas_Jira
A1: Date | B1: Month | C1: Task ID | D1: BOLSA | E1: MODULO | F1: MODULO_SALVIA | G1: Work Description | H1: Hours | I1: Issue | J1: Desarrollador | K1: Sprint | L1: Grupo
A2: 46300 | B2: 10 | C2: J-6.1.11 | D2: Bolsa 1 | E2: Categoría 4: Ingeniería y Desarrollo Web - Macro-Módulo Central (Fase 2) | F2: 6. PSICOSOCIAL (contcto seguro) | G2: Inicio de atención inmediata duplica contactos | H2: 6 | I2: PSWYA-790 | J2: Juan Nicolas Ruiz | K2: Sprint 19 | L2: psico
A3: 46300 | B3: 10 | C3: T-707 | D3: Bolsa 1 | E3: Categoría 8: Aseguramiento de Calidad (QA) y Pruebas Técnicas | F3: 1. ARQUITECTURA | G3: QA de funcionalidades concretadas en sprint 18 | H3: 5 | I3: PSWYA-795 | J3: brayanmarbelo | K3: Sprint 19 | L3: qa
A4: 46300 | B4: 10 | C4: T-1201 | D4: Bolsa 1 | E4: Categoría 1: Gobernanza, Planificación Estratégica y Dirección del Proyecto | F4: 1. ARQUITECTURA | G4: Reunión 5 de octubre: avances de seguimiento | H4: 1 | I4: PSWYA-860 | J4: Andres Felipe Ascencio Medina | K4: Sprint 19 | L4: gestion
A5: 46300 | B5: 10 | C5: T-1201 | D5: Bolsa 1 | E5: Categoría 1: Gobernanza, Planificación Estratégica y Dirección del Proyecto | F5: 1. ARQUITECTURA | G5: Análisis y feedback del sprint del 5 de octubre | H5: 2 | I5: PSWYA-861 | J5: Andres Felipe Ascencio Medina | K5: Sprint 19 | L5: gestion
A6: 46301 | B6: 10 | C6: T-609 | D6: Bolsa 1 | E6: Categoría 4: Ingeniería y Desarrollo Web - Macro-Módulo Central (Fase 2) | F6: 2. SEGUIMIENTO | G6: Fechas inconsistentes entre pantallas del portal | H6: 8 | I6: PSWYA-780 | J6: Juan Nicolas Ruiz | K6: Sprint 19 | L6: seguimiento
A7: 46301 | B7: 10 | C7: T-609 | D7: Bolsa 1 | E7: Categoría 4: Ingeniería y Desarrollo Web - Macro-Módulo Central (Fase 2) | F7: 2. SEGUIMIENTO | G7: Mis Casos muestra casos de otros agentes | H7: 1 | I7: PSWYA-782 | J7: brayanmarbelo | K7: Sprint 19 | L7: seguimiento
A8: 46301 | B8: 10 | C8: J-6.1.12 | D8: Bolsa 1 | E8: Categoría 4: Ingeniería y Desarrollo Web - Macro-Módulo Central (Fase 2) | F8: 7. ACTIVACION RUTAS (protección urgente) | G8: Etiquetas DIVIPOLA incorrectas en Directorio de Entidades | H8: 2.5 | I8: PSWYA-783 | J8: Brandon Martin Naranjo Piraban | K8: Sprint 19 | L8: rutas
A9: 46301 | B9: 10 | C9: J-6.1.11 | D9: Bolsa 1 | E9: Categoría 4: Ingeniería y Desarrollo Web - Macro-Módulo Central (Fase 2) | F9: 6. PSICOSOCIAL (contcto seguro) | G9: Revisión exhaustiva de terminología en flujo psicosocial | H9: 5 | I9: PSWYA-784 | J9: Brandon Martin Naranjo Piraban | K9: Sprint 19 | L9: psico
A10: 46301 | B10: 10 | C10: J-6.1.11 | D10: Bolsa 1 | E10: Categoría 4: Ingeniería y Desarrollo Web - Macro-Módulo Central (Fase 2) | F10: 6. PSICOSOCIAL (contcto seguro) | G10: De inmediato no redirige al formulario de seguimiento | H10: 1 | I10: PSWYA-786 | J10: brayanmarbelo | K10: Sprint 19 | L10: psico
A11: 46301 | B11: 10 | C11: J-6.1.11 | D11: Bolsa 1 | E11: Categoría 4: Ingeniería y Desarrollo Web - Macro-Módulo Central (Fase 2) | F11: 6. PSICOSOCIAL (contcto seguro) | G11: Consentimiento informado con texto de pruebas | H11: 2 | I11: PSWYA-791 | J11: brayanmarbelo | K11: Sprint 19 | L11: psico
A12: 46301 | B12: 10 | C12: J-6.1.11 | D12: Bolsa 1 | E12: Categoría 4: Ingeniería y Desarrollo Web - Macro-Módulo Central (Fase 2) | F12: 6. PSICOSOCIAL (contcto seguro) | G12: Consentimiento de persona de apoyo obligatorio indebidamente | H12: 2 | I12: PSWYA-792 | J12: brayanmarbelo | K12: Sprint 19 | L12: psico
A13: 46301 | B13: 10 | C13: J-4.5.1 | D13: Bolsa 1 | E13: Categoría 3: Requerimientos, Diseño Funcional y Prototipado UX/UI | F13: 8. MEDIDAS DE EMERGENCIA | G13: Redactar historias de usuario de Medidas de Emergencia | H13: 3 | I13: PSWYA-796 | J13: brayanmarbelo | K13: Sprint 19 | L13: med_hu
... A86: 46309 | B86: 10 | C86: T-602 | D86: Bolsa 2 | E86: Categoría 10: Transferencia de Conocimiento, Soporte y Cierre Legal | F86: 1. ARQUITECTURA | G86: Transferencia de conocimiento: 9 manuales técnicos de SALVIA y Red de Acción SALVIA (30 pantallas, 74 capturas) | H86: 35 | I86: Informe INF-SGC-09 | J86: Andrés Posada | K86: Oct (1 al 23) | L86: gerencia

Sheet Plan_Cierre
A1: Linea | B1: Etapa | C1: Estado | D1: Responsable | E1: Semana_Inicio | F1: Semana_Fin | G1: Hitos | H1: Items_EDT
A2: Registro y Reporte | B2: Pruebas | C2: Ajustar Alerta Inminente en el mockup. Actualmente en ajustes del prototipo; pendiente revisión de pruebas antes del despliegue a todos en pruebas. | D2: Andrés Felipe Ascencio | E2: 1 | F2: 4 | G2: M2, M4, M5 | H2: 6.1.8
A3: Seguimiento y Detalle del Caso | B3: Desarrollo | C3: En revisión algunos hallazgos pendientes. Revisando en pruebas. Pendiente despliegue. | D3: Brayan Marbello | E3: 4 | F3: 6 | G3: M1 | H3: 6.1.5
A4: Notificaciones | B4: Desarrollo | C4: En revisión algunos hallazgos pendientes. Revisando en pruebas. Pendiente despliegue. | D4: Juan Nicolás Buitrago | E4: 2 | F4: 4 | G4: M1 | H4: 6.1.5
A5: Enlace territorial | B5: Pruebas | C5: En revisión funcionalidades. | D5: Juan Nicolás Buitrago | E5: 3 | F5: 7 | G5: M1 | H5: 6.1.12
A6: Entidad territorial | B6: Pruebas | C6: En revisión funcionalidades. Avance sustancial con Amazonía. Requiere revisar según avance de la 3.ª semana de octubre. | D6: Brandon Martín | E6: 2 | F6: 5 | G6: M1 | H6: 6.1.12
A7: Mecanismo Articulador | B7: Pruebas | C7: En revisión funcionalidades. | D7: Brayan Marbello | E7: 1 | F7: 3 | G7: M1 | H7: 6.1.12
A8: Equipo Psicosocial | B8: Desarrollo | C8: En revisión algunos hallazgos pendientes. Revisando en pruebas. Pendiente despliegue. | D8: Santiago Ramos | E8: 4 | F8: 7 | G8: M1 | H8: 6.1.11
A9: Medidas de Emergencia | B9: Pruebas | C9: En avance hacia prototipo. Pendiente retroalimentación con el Equipo Técnico-Administrativo. | D9: Santiago Ramos | E9: 1 | F9: 4 | G9: M3 | H9: 6.1.9, 6.1.10
A10: Hombres | B10: Pendiente por ideación | C10: Pendiente reunión para iniciar diseño en mesa de trabajo interna. Los equipos ya enviaron insumos iniciales. | D10: Andrés Posada | E10: 4 | F10: 5 | G10: M1 | H10: 4.2.2
A11: Estabilización | B11: Pendiente por ideación | C11: Pendiente reunión para iniciar diseño en mesa de trabajo interna. Los equipos ya enviaron insumos iniciales. | D11: Andrés Posada | E11: 5 | F11: 7 | G11: M3 | H11: 4.5.3
A12: Registro Familiares Feminicidio | B12: MockUp | C12: Actualmente está en mockup. Pendiente revisión y retroalimentación. | D12: Andrés Felipe Ascencio | E12: 2 | F12: 5 | G12: M3 | H12: 4.5.4
A13: Ajustes de discapacidad | B13: Pendiente por ideación | C13: Por definir ruta. | D13: Camilo Arias | E13: 3 | F13: 7 | G13: M4 | H13: 6.1.6

Sheet Tareas_Pendientes
A1: Responsable | B1: Tarea | C1: Linea | D1: Fuente | E1: Hito | F1: Semana_Inicio | G1: Semana_Fin | H1: Estado
A2: Brandon Martín | B2: Bloquear la creación de usuarios de entidad desde la pantalla de crear usuarios y dejarla solo en el Directorio de Entidades (al crear el usuario desde el admin la entidad no queda bien creada) | C2: Entidad territorial | D2: FigJam · Sprint 26 Oct | E2: M1 | F2: 2 | G2: 5 | H2: Pendiente
A3: Brandon Martín | B3: Hacer la versión definitiva de los formularios de Psicosocial | C3: Equipo Psicosocial | D3: FigJam · Sprint 26 Oct | E3: M1 | F3: 4 | G3: 7 | H3: Pendiente
A4: Juan Nicolás Buitrago | B4: Enviar el caso al mecanismo articulador elegido al guardar el formulario de decisiones del comité (alerta por barreras) | C4: Enlace territorial | D4: FigJam · Sprint 26 Oct | E4: M1 | F4: 3 | G4: 7 | H4: Pendiente
A5: Juan Nicolás Buitrago | B5: Guardar las recomendaciones al agente que el equipo técnico selecciona al gestionar una alerta por barreras; validar con SALVIA dónde deben quedar | C5: Enlace territorial | D5: FigJam · Sprint 26 Oct | E5: M1 | F5: 3 | G5: 7 | H5: Pendiente
A6: Juan Nicolás Buitrago | B6: Hacer las tareas del flujo de Medidas de Emergencia | C6: Medidas de Emergencia | D6: FigJam · Sprint 26 Oct | E6: M3 | F6: 1 | G6: 4 | H6: Pendiente
A7: Brayan Marbello | B7: Análisis del caso: habilitar desde esa sección la misma tarea de decisiones del equipo técnico (remitir a mesa técnica) | C7: Mecanismo Articulador | D7: FigJam · Sprint 26 Oct | E7: M1 | F7: 1 | G7: 3 | H7: Pendiente
A8: Brayan Marbello | B8: Validar que la entidad pueda responder las solicitudes en Mis acciones institucionales: lo registrado desde seguimiento debe verse en la entidad, crear la tarea de la solicitud y que al completarla se genere la acción institucional | C8: Entidad territorial | D8: FigJam · Sprint 26 Oct | E8: M1 | F8: 2 | G8: 5 | H8: Pendiente
A9: Brayan Marbello | B9: Hacer los manuales de usuario | C9: Documentación y capacitación | D9: FigJam · Sprint 26 Oct | E9: H10 | F9: 1 | G9: 8 | H9: Pendiente
A10: Brayan Marbello | B10: Priorizar con Laura los ajustes más importantes de Rutas, Psicosocial y Seguimiento | C10: Seguimiento y Detalle del Caso | D10: FigJam · Sprint 26 Oct | E10: H08 | F10: 4 | G10: 6 | H10: Pendiente
A11: Santiago Ramos | B11: Probar que el 3x3 de Psicosocial funciona y que se puede cerrar la remisión por falta de contacto; dejar un botón exclusivo para el intento de contacto | C11: Equipo Psicosocial | D11: FigJam · Sprint 26 Oct | E11: M1 | F11: 4 | G11: 7 | H11: Pendiente
A12: Santiago Ramos | B12: Hacer las tareas del flujo de Medidas de Emergencia | C12: Medidas de Emergencia | D12: FigJam · Sprint 26 Oct | E12: M3 | F12: 1 | G12: 4 | H12: Pendiente
A13: Santiago Ramos | B13: Flujo Medidas · Agente de seguimiento remite el caso | C13: Medidas de Emergencia | D13: FigJam · Terminar Medidas | E13: M3 | F13: 1 | G13: 4 | H13: Pendiente
... A36: Por asignar | B36: Hallazgo 115 (Alta) · Falta el checklist de acciones institucionales; aclarar si debe incluirse y su contenido | C36: Entidad territorial | D36: FigJam · Módulo Rutas (hallazgos SALVIA) | E36: M1 | F36: 2 | G36: 5 | H36: Abierto

Sheet Plan_Documentacion
A1: Orden | B1: Modulo | C1: Avance_referido | D1: Responsable | E1: Documento | F1: Semana_Inicio | G1: Semana_Fin | H1: Nota
A2: 1 | B2: Seguimiento | C2: 0.95 | D2: Brayan Marbello | E2: Documento de requerimientos funcionales y no funcionales | F2: 1 | G2: 3 | H2: Se documenta primero
A3: 1 | B3: Seguimiento | C3: 0.95 | D3: Brayan Marbello | E3: Documento de historias de usuario | F3: 1 | G3: 3 | H3: Se documenta primero
A4: 1 | B4: Seguimiento | C4: 0.95 | D4: Brayan Marbello | E4: Documento de casos de uso | F4: 1 | G4: 3 | H4: Se documenta primero
A5: 1 | B5: Seguimiento | C5: 0.95 | D5: Brayan Marbello | E5: Documento de diagramas de flujo de procesos | F5: 1 | G5: 3 | H5: Se documenta primero
A6: 1 | B6: Seguimiento | C6: 0.95 | D6: Brayan Marbello | E6: Manual técnico para el equipo de desarrollo | F6: 1 | G6: 3 | H6: Se documenta primero
A7: 1 | B7: Seguimiento | C7: 0.95 | D7: Brayan Marbello | E7: Plan de pruebas funcionales | F7: 1 | G7: 3 | H7: Se documenta primero
A8: 1 | B8: Seguimiento | C8: 0.95 | D8: Brayan Marbello | E8: Registro y seguimiento de errores y correcciones (bugs) | F8: 1 | G8: 3 | H8: Se documenta primero
A9: 1 | B9: Seguimiento | C9: 0.95 | D9: Brayan Marbello | E9: Documento de validación de criterios de aceptación | F9: 1 | G9: 3 | H9: Se documenta primero
A10: 1 | B10: Seguimiento | C10: 0.95 | D10: Brayan Marbello | E10: Registro de ajustes funcionales acordados y validados | F10: 1 | G10: 3 | H10: Se documenta primero
A11: 1 | B11: Seguimiento | C11: 0.95 | D11: Brayan Marbello | E11: Inventario de entregables realizados | F11: 1 | G11: 3 | H11: Se documenta primero
A12: 1 | B12: Seguimiento | C12: 0.95 | D12: Brayan Marbello | E12: Acta o registro de entrega de documentación técnica, manuales y actas generadas | F12: 1 | G12: 3 | H12: Se documenta primero
A13: 2 | B13: Reporte y Registro | C13: 0.8 | D13: Brayan Marbello | E13: Documento de requerimientos funcionales y no funcionales | F13: 5 | G13: 6 | H13: Se documenta cuando cierre su desarrollo (semana 4)
... A34: 3 | B34: Medidas de Emergencia | C34: 0.5 | D34: Brayan Marbello | E34: Acta o registro de entrega de documentación técnica, manuales y actas generadas | F34: 7 | G34: 8 | H34: Se documenta al final para darle tiempo al desarrollo

Sheet Semanas_Cierre
A1: Semana | B1: Etiqueta | C1: Inicio | D1: Fin | E1: Uso
A2: 1 | B2: 26 - 31 oct | C2: 46321 | D2: 46326 | E2: Desarrollo
A3: 2 | B3: 2 - 7 nov | C3: 46328 | D3: 46333 | E3: Desarrollo
A4: 3 | B4: 9 - 14 nov | C4: 46335 | D4: 46340 | E4: Desarrollo
A5: 4 | B5: 16 - 21 nov | C5: 46342 | D5: 46347 | E5: Desarrollo
A6: 5 | B6: 23 - 28 nov | C6: 46349 | D6: 46354 | E6: Desarrollo
A7: 6 | B7: 1 - 5 dic | C7: 46357 | D7: 46361 | E7: Desarrollo
A8: 7 | B8: 7 - 12 dic | C8: 46363 | D8: 46368 | E8: Desarrollo
A9: 8 | B9: 14 - 19 dic | C9: 46370 | D9: 46375 | E9: Capacitación y entrega
A10: 9 | B10: 21 - 31 dic | C10: 46377 | D10: 46387 | E10: Capacitación y entrega

Sheet Reglas_Hito
A1: Prioridad | B1: Campo | C1: Valor | D1: Hito | E1: Descripcion
A2: 10 | B2: Categoria | C2: 1 | D2: H07 | E2: Categoría 1: Gobernanza y dirección del proyecto
A3: 11 | B3: Categoria | C3: 2 | D3: H06 | E3: Categoría 2: Diagnóstico, arquitectura de datos y refactorización
A4: 12 | B4: Categoria | C4: 8 | D4: H08 | E4: Categoría 8: QA y pruebas técnicas
A5: 13 | B5: Categoria | C5: 9 | D5: H09 | E5: Categoría 9: Estabilización, migración y paso a producción
A6: 14 | B6: Categoria | C6: 10 | D6: H10 | E6: Categoría 10: Transferencia, soporte y cierre
A7: 20 | B7: Tarea | C7: T-104, T-401, T-407, T-408 | D7: H06 | E7: Tareas de arquitectura
A8: 21 | B8: Tarea | C8: T-1201, T-1202, T-207 | D8: H07 | E8: Tareas de gobernanza y Gantt
A9: 22 | B9: Tarea | C9: T-203 | D9: M5 | E9: Módulo web ASP
A10: 30 | B10: Palabra_clave | C10: OSIGHN|OSIGD|LGBT|identitario | D10: M4 | E10: Trabajo diferencial LGBTIQ+ dentro de otros módulos
A11: 31 | B11: Palabra_clave | C11: tamizaje | D11: M2 | E11: Tamizaje dentro de otros módulos
A12: 40 | B12: Modulo_SALVIA | C12: 2.3. | D12: M2 | E12: Tamizaje
A13: 41 | B13: Modulo_SALVIA | C13: 10. | D13: M4 | E13: LGBTIQ+
... A25: 61 | B25: Tarea | C25: T-302 | D25: M2 | E25: Árbol de decisión del tamizaje
A26: 99 | B26: Defecto | D26: M1 | E26: Resto: requerimientos, diseño y desarrollo del macro-módulo

Sheet Contrato
A1: Bolsa | B1: Horas
A2: Bolsa 1: SALVIA | B2: 3744
A3: Bolsa 2: MASP | B3: 1652

Sheet Avance_Mensual
A1: ID | B1: Actividad | C1: 2026-02 | D1: 2026-03 | E1: 2026-04 | F1: 2026-05 | G1: 2026-06 | H1: 2026-07 | I1: 2026-08 | J1: 2026-09 | K1: 2026-10 | L1: Criterio
A2: 1.1.1 | B2: Entrega de hojas de vida y soportes del equipo | C2: 1 | D2: 1 | E2: 1 | F2: 1 | G2: 1 | H2: 1 | I2: 1 | J2: 1 | K2: =Plan!E4 -> 1 | L2: Según evidencia documentada por mes
A3: 1.1.2 | B3: Reunion de inicio y presentacion del proyecto | C3: 1 | D3: 1 | E3: 1 | F3: 1 | G3: 1 | H3: 1 | I3: 1 | J3: 1 | K3: =Plan!E5 -> 1 | L3: Según evidencia documentada por mes
A4: 2.1.1 | B4: Presentacion, aprobacion y uso del Mockup Kreivo-SALVIA | C4: 0.2 | D4: 0.5 | E4: 0.6 | F4: 0.6 | G4: 0.85 | H4: 1 | I4: 1 | J4: 1 | K4: =Plan!E8 -> 1 | L4: Proporcional a las horas acumuladas de sus tareas
A5: 2.1.2 | B5: Firma de Acta de Alcance y SLA | C5: 0 | D5: 0 | E5: 0 | F5: 0.75 | G5: 0.75 | H5: 0.75 | I5: 0.75 | J5: 0.75 | K5: =Plan!E9 -> 0.9 | L5: Proporcional a las horas acumuladas de sus tareas
A6: 2.1.3 | B6: Levantamiento: Modulo Web ASP - Variables de Riesgo | C6: 0.2 | D6: 0.2 | E6: 0.2 | F6: 0.2 | G6: 0.35 | H6: 0.5 | I6: 0.5 | J6: 0.5 | K6: =Plan!E10 -> 0.5 | L6: Proporcional a las horas acumuladas de sus tareas
A7: 2.1.4 | B7: Gantt y plan de trabajo Kreivo-SALVIA | C7: 0.85 | D7: 0.9 | E7: 0.9 | F7: 0.9 | G7: 0.9 | H7: 0.9 | I7: 0.9 | J7: 0.9 | K7: =Plan!E11 -> 1 | L7: Proporcional a las horas acumuladas de sus tareas
A8: 2.2.1 | B8: App MASP: diseno de interfaz segura | C8: 0 | D8: 0 | E8: 0 | F8: 0 | G8: 0 | H8: 0 | I8: 0 | J8: 1 | K8: =Plan!E13 -> 1 | L8: Proporcional a las horas acumuladas de sus tareas
A9: 2.2.2 | B9: App MASP: diseno de alertas y Push Notifications | C9: 0 | D9: 0 | E9: 0 | F9: 0.25 | G9: 0.25 | H9: 0.25 | I9: 0.75 | J9: 0.75 | K9: =Plan!E14 -> 0.75 | L9: Según evidencia documentada por mes
A10: 2.2.3 | B10: App MASP: integracion con core SALVIA | C10: 0 | D10: 0 | E10: 0.25 | F10: 0.25 | G10: 0.25 | H10: 0.25 | I10: 0.25 | J10: 0.25 | K10: =Plan!E15 -> 0.25 | L10: Proporcional a las horas acumuladas de sus tareas
A11: 3.1.1 | B11: Diseno y logica: Landing Page, Login y Captcha | C11: 0 | D11: 0 | E11: 1 | F11: 1 | G11: 1 | H11: 1 | I11: 1 | J11: 1 | K11: =Plan!E18 -> 1 | L11: Proporcional a las horas acumuladas de sus tareas
A12: 3.1.2 | B12: Logica y arbol de decision: Modulo de Tamizaje (escala severidad) | C12: 0 | D12: 0 | E12: 0 | F12: 0.5 | G12: 0.5 | H12: 0.5 | I12: 0.5 | J12: 0.5 | K12: =Plan!E19 -> 0.65 | L12: Proporcional a las horas acumuladas de sus tareas
A13: 3.1.3 | B13: Refinamiento UX: Dashboard y trazabilidad de casos | C13: 0 | D13: 0 | E13: 0.65 | F13: 0.65 | G13: 0.85 | H13: 0.85 | I13: 0.85 | J13: 0.85 | K13: =Plan!E20 -> 0.9 | L13: Proporcional a las horas acumuladas de sus tareas
A14: 3.2.1 | B14: Diseno de flujos y UI: App Movil MASP | C14: 0 | D14: 0 | E14: 0.8 | F14: 0.8 | G14: 0.8 | H14: 0.95 | I14: 1 | J14: 1 | K14: =Plan!E22 -> 1 | L14: Proporcional a las horas acumuladas de sus tareas
A15: 3.2.2 | B15: Aprobacion de Arquitectura e Interoperabilidad | C15: 0 | D15: 0.5 | E15: 0.5 | F15: 0.5 | G15: 0.5 | H15: 0.5 | I15: 0.5 | J15: 0.5 | K15: =Plan!E23 -> 0.5 | L15: Según evidencia documentada por mes
A16: 4.1.1 | B16: Documentacion y metodologia SALVIA Web heredada | C16: 0.9 | D16: 1 | E16: 1 | F16: 1 | G16: 1 | H16: 1 | I16: 1 | J16: 1 | K16: =Plan!E26 -> 1 | L16: Proporcional a las horas acumuladas de sus tareas
A17: 4.1.2 | B17: Historias de Usuario actuales (sistema heredado) | C17: 0.05 | D17: 0.65 | E17: 1 | F17: 1 | G17: 1 | H17: 1 | I17: 1 | J17: 1 | K17: =Plan!E27 -> 1 | L17: Proporcional a las horas acumuladas de sus tareas
A18: 4.1.3 | B18: Arquitectura actual y diagnostico de deuda tecnica | C18: 0.2 | D18: 1 | E18: 1 | F18: 1 | G18: 1 | H18: 1 | I18: 1 | J18: 1 | K18: =Plan!E28 -> 1 | L18: Proporcional a las horas acumuladas de sus tareas
A19: 4.2.1 | B19: Arquitectura SOG hacia EAV-DAG | C19: 0 | D19: 1 | E19: 1 | F19: 1 | G19: 1 | H19: 1 | I19: 1 | J19: 1 | K19: =Plan!E30 -> 1 | L19: Proporcional a las horas acumuladas de sus tareas
A20: 4.2.2 | B20: Casos de uso e Historias de Usuario (interconectividad y flujo) | C20: 0 | D20: 0.15 | E20: 0.15 | F20: 0.15 | G20: 0.35 | H20: 0.35 | I20: 0.5 | J20: 0.75 | K20: =Plan!E31 -> 0.85 | L20: Proporcional a las horas acumuladas de sus tareas
A21: 4.2.3 | B21: Diagramas Figma y diccionario de datos (SALVIA Web) | C21: 0 | D21: 0 | E21: 0.45 | F21: 0.6 | G21: 0.75 | H21: 0.75 | I21: 0.75 | J21: 0.75 | K21: =Plan!E32 -> 0.75 | L21: Proporcional a las horas acumuladas de sus tareas
A22: 4.2.4 | B22: Actas de mesas tecnicas | C22: 0 | D22: 0.55 | E22: 0.6 | F22: 0.65 | G22: 0.65 | H22: 0.65 | I22: 0.65 | J22: 0.9 | K22: =Plan!E33 -> 0.9 | L22: Proporcional a las horas acumuladas de sus tareas
A23: 4.2.5 | B23: Historias de Usuario ancladas a Figma | C23: 0 | D23: 0.35 | E23: 0.35 | F23: 0.35 | G23: 0.55 | H23: 0.6 | I23: 0.6 | J23: 0.6 | K23: =Plan!E34 -> 0.6 | L23: Proporcional a las horas acumuladas de sus tareas
A24: 4.2.6 | B24: Migracion de Kobo a Zenkit (analisis solucion transitoria) | C24: 0 | D24: 1 | E24: 1 | F24: 1 | G24: 1 | H24: 1 | I24: 1 | J24: 1 | K24: =Plan!E35 -> 1 | L24: Proporcional a las horas acumuladas de sus tareas
A25: 4.2.7 | B25: Integracion data SOG hacia EAV-DAG | C25: 0 | D25: 0 | E25: 0.65 | F25: 0.65 | G25: 0.65 | H25: 0.65 | I25: 0.8 | J25: 0.8 | K25: =Plan!E36 -> 0.8 | L25: Proporcional a las horas acumuladas de sus tareas
A26: 4.2.8 | B26: Documentacion y metodologia App MASP | C26: 0 | D26: 0 | E26: 0 | F26: 0 | G26: 0 | H26: 0 | I26: 0.1 | J26: 0.5 | K26: =Plan!E37 -> 0.5 | L26: Proporcional a las horas acumuladas de sus tareas
A27: 4.3.1 | B27: Diagramas Figma y diccionario de datos (App MASP) | C27: 0 | D27: 0 | E27: 0 | F27: 0 | G27: 0 | H27: 0.55 | I27: 0.6 | J27: 0.6 | K27: =Plan!E39 -> 0.6 | L27: Proporcional a las horas acumuladas de sus tareas
A28: 4.4.1 | B28: Guion Funcional de Registro v3.0 y Formulario Kreivo v5.0 | C28: 0 | D28: 0 | E28: 0 | F28: 0 | G28: 0 | H28: 0 | I28: 0 | J28: 0.9 | K28: =Plan!E41 -> 1 | L28: Según evidencia documentada por mes
A29: 4.4.2 | B29: Mockup de Reporte y Registro y guia de 22 videos | C29: 0 | D29: 0 | E29: 0 | F29: 0 | G29: 0 | H29: 0 | I29: 0 | J29: 1 | K29: =Plan!E42 -> 1 | L29: Según evidencia documentada por mes
A30: 4.4.3 | B30: Identificacion de la victima: preguntas OSIGD para poblacion LGBTIQ+ | C30: 0 | D30: 0 | E30: 0 | F30: 0 | G30: 0 | H30: 0 | I30: 0 | J30: 0.75 | K30: =Plan!E43 -> 1 | L30: Según evidencia documentada por mes
A31: 4.4.4 | B31: Identificacion de la victima: actividades sexuales pagas (ASP) | C31: 0 | D31: 0 | E31: 0 | F31: 0 | G31: 0 | H31: 0 | I31: 0 | J31: 0.5 | K31: =Plan!E44 -> 1 | L31: Según evidencia documentada por mes
A32: 4.4.5 | B32: Tamizaje de riesgo en el registro: bifurcaciones, puntaje y alertas | C32: 0 | D32: 0 | E32: 0 | F32: 0 | G32: 0 | H32: 0 | I32: 0 | J32: 0.6 | K32: =Plan!E45 -> 0.9 | L32: Según evidencia documentada por mes
A33: 4.4.6 | B33: Gestion de reportes, recontacto 3x3 y envio del caso a Seguimiento | C33: 0 | D33: 0 | E33: 0 | F33: 0 | G33: 0 | H33: 0 | I33: 0 | J33: 0.9 | K33: =Plan!E46 -> 0.9 | L33: Según evidencia documentada por mes
A34: 4.4.7 | B34: Validacion con el Ministerio de los puntos abiertos del mockup | C34: 0 | D34: 0 | E34: 0 | F34: 0 | G34: 0 | H34: 0 | I34: 0 | J34: 0 | K34: =Plan!E47 -> 1 | L34: Sin horas; aparece solo en el corte actual
A35: 4.4.8 | B35: Historia de usuario del nuevo formulario de registro | C35: 0 | D35: 0 | E35: 0 | F35: 0 | G35: 0 | H35: 0 | I35: 0 | J35: 0.5 | K35: =Plan!E48 -> 0.7 | L35: Según evidencia documentada por mes
A36: 4.5.1 | B36: Historias de usuario de Medidas de Emergencia v1.0 (38 HU) | C36: 0 | D36: 0 | E36: 0 | F36: 0 | G36: 0 | H36: 0 | I36: 0 | J36: 0 | K36: =Plan!E50 -> 1 | L36: Sin horas; aparece solo en el corte actual
A37: 4.5.2 | B37: Mockups de Medidas de Emergencia y revision con el Ministerio | C37: 0 | D37: 0 | E37: 0 | F37: 0 | G37: 0 | H37: 0 | I37: 0 | J37: 0.75 | K37: =Plan!E51 -> 0.85 | L37: Según evidencia documentada por mes
A38: 4.5.3 | B38: Matriz de campos y logica para determinar las medidas | C38: 0 | D38: 0 | E38: 0 | F38: 0.1 | G38: 0.1 | H38: 0.1 | I38: 0.4 | J38: 0.4 | K38: =Plan!E52 -> 0.4 | L38: Según evidencia documentada por mes
A39: 4.5.4 | B39: Familiares y personas huerfanas dentro de Medidas (Ley 2530 de 2025) | C39: 0 | D39: 0 | E39: 0 | F39: 0 | G39: 0 | H39: 0 | I39: 0 | J39: 0.3 | K39: =Plan!E53 -> 0.4 | L39: Según evidencia documentada por mes
A40: 4.5.5 | B40: Criterios de aceptacion y estados aprobados por el Ministerio | C40: 0 | D40: 0 | E40: 0 | F40: 0 | G40: 0 | H40: 0 | I40: 0 | J40: 0 | K40: =Plan!E54 -> 0 | L40: Sin horas registradas
A41: 5.1.1 | B41: Sprint 1: Setup de entornos, BD y seguridad (autenticacion) | C41: 0 | D41: 0.1 | E41: 0.35 | F41: 1 | G41: 1 | H41: 1 | I41: 1 | J41: 1 | K41: =Plan!E57 -> 1 | L41: Proporcional a las horas acumuladas de sus tareas
A42: 5.1.2 | B42: Sprint 2: Modulos de registro y motor de tamizaje | C42: 0 | D42: 0 | E42: 0 | F42: 0.35 | G42: 0.5 | H42: 0.55 | I42: 0.6 | J42: 0.6 | K42: =Plan!E58 -> 0.7 | L42: Proporcional a las horas acumuladas de sus tareas
A43: 5.1.3 | B43: Sprint 3: Dashboard de trazabilidad y alertas | C43: 0 | D43: 0 | E43: 0 | F43: 0.45 | G43: 0.7 | H43: 0.7 | I43: 0.7 | J43: 0.7 | K43: =Plan!E59 -> 0.75 | L43: Proporcional a las horas acumuladas de sus tareas
A44: 5.1.4 | B44: Sprint 5: Integracion SIVIGE (interoperabilidad) | C44: 0 | D44: 0 | E44: 0 | F44: 0 | G44: 0 | H44: 0 | I44: 0 | J44: 0 | K44: =Plan!E60 -> 0 | L44: Sin horas registradas
A45: 5.2.1 | B45: Sprint 4: Desarrollo App MASP (iOS / Android) | C45: 0 | D45: 0 | E45: 0 | F45: 0.3 | G45: 0.3 | H45: 0.3 | I45: 0.5 | J45: 0.6 | K45: =Plan!E62 -> 0.6 | L45: Según evidencia documentada por mes
A46: 5.2.2 | B46: Ejecucion de pruebas unitarias y de carga (sprint) | C46: 0 | D46: 0 | E46: 0 | F46: 0 | G46: 0 | H46: 0 | I46: 0 | J46: 0 | K46: =Plan!E63 -> 0 | L46: Sin horas registradas
A47: 6.1.1 | B47: BI: Diseno de Dashboards y ETL | C47: 0 | D47: 0 | E47: 0 | F47: 0 | G47: 0.5 | H47: 0.5 | I47: 0.5 | J47: 0.5 | K47: =Plan!E66 -> 0.5 | L47: Proporcional a las horas acumuladas de sus tareas
A48: 6.1.2 | B48: Adopcion: manuales y capacitacion (SALVIA Web) | C48: 0 | D48: 0 | E48: 0 | F48: 0 | G48: 0.1 | H48: 0.1 | I48: 0.3 | J48: 0.3 | K48: =Plan!E67 -> 0.65 | L48: Según evidencia documentada por mes: videos compartidos en agosto
A49: 6.1.3 | B49: Setup entornos, BD Postgres y seguridad (SALVIA) | C49: 0 | D49: 0 | E49: 0 | F49: 0.3 | G49: 0.75 | H49: 0.8 | I49: 0.9 | J49: 1 | K49: =Plan!E68 -> 1 | L49: Proporcional a las horas acumuladas de sus tareas
A50: 6.1.4 | B50: Modulo de recepcion y motor de tamizaje (web) | C50: 0 | D50: 0 | E50: 0 | F50: 0 | G50: 0.1 | H50: 0.5 | I50: 0.5 | J50: 0.5 | K50: =Plan!E69 -> 0.6 | L50: Proporcional a las horas acumuladas de sus tareas
A51: 6.1.5 | B51: Modulo de seguimiento y tableros BI/ETL (web) | C51: 0 | D51: 0 | E51: 0 | F51: 0.15 | G51: 0.45 | H51: 0.45 | I51: 0.9 | J51: 0.9 | K51: =Plan!E70 -> 0.9 | L51: Proporcional a las horas acumuladas de sus tareas
A52: 6.1.6 | B52: Modulo LGBTIQ+ (construccion y variables diferenciales) | C52: 0 | D52: 0 | E52: 0 | F52: 0 | G52: 0.1 | H52: 0.1 | I52: 0.1 | J52: 0.25 | K52: =Plan!E71 -> 0.25 | L52: Según evidencia documentada por mes
A53: 6.1.7 | B53: Modulo ASP Web - caracterizacion y analisis de riesgo | C53: 0 | D53: 0 | E53: 0 | F53: 0 | G53: 0 | H53: 0 | I53: 0 | J53: 0 | K53: =Plan!E72 -> 0 | L53: Sin horas registradas
A54: 6.1.8 | B54: Nuevo formulario de Reporte y Registro (construccion) | C54: 0 | D54: 0 | E54: 0 | F54: 0 | G54: 0 | H54: 0 | I54: 0 | J54: 0.25 | K54: =Plan!E73 -> 0.75 | L54: Según evidencia documentada por mes
A55: 6.1.9 | B55: Modulo Medidas de Emergencia: pantallas y flujo | C55: 0 | D55: 0 | E55: 0 | F55: 0 | G55: 0 | H55: 0 | I55: 0 | J55: 0 | K55: =Plan!E74 -> 0.15 | L55: Sin horas registradas
A56: 6.1.10 | B56: Medidas de Emergencia: logica de medidas, entrega y seguimiento | C56: 0 | D56: 0 | E56: 0 | F56: 0 | G56: 0 | H56: 0 | I56: 0 | J56: 0 | K56: =Plan!E75 -> 0 | L56: Sin horas registradas
A57: 6.1.11 | B57: Atencion Psicosocial: construccion y estabilizacion | C57: 0 | D57: 0 | E57: 0 | F57: 0 | G57: 0.1 | H57: 0.45 | I57: 0.6 | J57: 0.75 | K57: =Plan!E76 -> 0.9 | L57: Según evidencia documentada por mes
A58: 6.1.12 | B58: Rutas y gestion institucional: portal de entidades, mecanismos y directorio | C58: 0 | D58: 0 | E58: 0 | F58: 0 | G58: 0 | H58: 0.2 | I58: 0.4 | J58: 0.55 | K58: =Plan!E77 -> 0.8 | L58: Según evidencia documentada por mes
A59: 6.2.1 | B59: Despliegue: migracion a produccion (App) | C59: 0 | D59: 0 | E59: 0 | F59: 0.4 | G59: 0.4 | H59: 0.4 | I59: 0.4 | J59: 0.6 | K59: =Plan!E79 -> 0.6 | L59: Proporcional a las horas acumuladas de sus tareas
A60: 6.2.2 | B60: Soporte: activacion de mesa de ayuda | C60: 0 | D60: 0 | E60: 0 | F60: 0 | G60: 0 | H60: 0 | I60: 0 | J60: 0 | K60: =Plan!E80 -> 0 | L60: Sin horas registradas
A61: 6.2.3 | B61: Ejecucion de pruebas unitarias y de carga (App) | C61: 0 | D61: 0 | E61: 0 | F61: 0 | G61: 0 | H61: 0 | I61: 0 | J61: 0 | K61: =Plan!E81 -> 0 | L61: Sin horas registradas
A62: 6.2.4 | B62: Setup de entornos y seguridad API (App MASP) | C62: 0 | D62: 0 | E62: 0 | F62: 0 | G62: 0 | H62: 0 | I62: 0.1 | J62: 0.9 | K62: =Plan!E82 -> 0.9 | L62: Proporcional a las horas acumuladas de sus tareas
A63: 6.2.5 | B63: Desarrollo de interfaz y logica de App Movil MASP | C63: 0 | D63: 0 | E63: 0 | F63: 0 | G63: 0 | H63: 0.2 | I63: 0.6 | J63: 0.6 | K63: =Plan!E83 -> 0.6 | L63: Proporcional a las horas acumuladas de sus tareas
A64: 6.2.6 | B64: Desarrollo backend - Boton de Panico Linea 155 | C64: 0 | D64: 0 | E64: 0 | F64: 0 | G64: 0 | H64: 0 | I64: 0.5 | J64: 0.5 | K64: =Plan!E84 -> 0.5 | L64: Según evidencia documentada por mes
A65: 6.2.7 | B65: Integracion App - Boton de Panico Linea 155 | C65: 0 | D65: 0 | E65: 0 | F65: 0 | G65: 0 | H65: 0 | I65: 0.25 | J65: 0.25 | K65: =Plan!E85 -> 0.25 | L65: Según evidencia documentada por mes
A66: 7.1.1 | B66: Pruebas de Aceptacion de Usuario (UAT) con el Ministerio | C66: 0 | D66: 0 | E66: 0 | F66: 0 | G66: 0.2 | H66: 0.2 | I66: 0.2 | J66: 0.3 | K66: =Plan!E88 -> 0.45 | L66: Según evidencia documentada por mes
A67: 7.1.2 | B67: Transferencia de conocimiento y capacitacion inicial | C67: 0 | D67: 0 | E67: 0 | F67: 0 | G67: 0.2 | H67: 0.25 | I67: 0.4 | J67: 0.4 | K67: =Plan!E89 -> 0.65 | L67: Según evidencia documentada por mes: videos compartidos en agosto
A68: 7.1.3 | B68: Paso a produccion oficial SALVIA | C68: 0 | D68: 0 | E68: 0 | F68: 0 | G68: 0.3 | H68: 0.65 | I68: 0.65 | J68: 0.65 | K68: =Plan!E90 -> 0.65 | L68: Proporcional a las horas acumuladas de sus tareas
A69: 7.1.4 | B69: API de sincronizacion SIVIGE (Minsalud) | C69: 0 | D69: 0 | E69: 0 | F69: 0 | G69: 0 | H69: 0 | I69: 0 | J69: 0 | K69: =Plan!E91 -> 0 | L69: Sin horas registradas
A70: 7.1.5 | B70: QA unitarias, carga y vulnerabilidad (SALVIA Web) | C70: 0 | D70: 0 | E70: 0 | F70: 0 | G70: 0.1 | H70: 0.1 | I70: 0.3 | J70: 0.3 | K70: =Plan!E92 -> 0.35 | L70: Proporcional a las horas acumuladas de sus tareas
A71: 7.1.6 | B71: Pruebas de Aceptacion de Usuario UAT (SALVIA Web) | C71: 0 | D71: 0 | E71: 0 | F71: 0 | G71: 0.4 | H71: 0.4 | I71: 0.45 | J71: 0.45 | K71: =Plan!E93 -> 0.45 | L71: Proporcional a las horas acumuladas de sus tareas
A72: 7.1.7 | B72: Pruebas y aceptacion de Medidas de Emergencia | C72: 0 | D72: 0 | E72: 0 | F72: 0 | G72: 0 | H72: 0 | I72: 0 | J72: 0 | K72: =Plan!E94 -> 0 | L72: Sin horas registradas
A73: 7.2.1 | B73: Ajustes Post-UAT y estabilizacion | C73: 0 | D73: 0 | E73: 0 | F73: 0 | G73: 0.15 | H73: 0.6 | I73: 0.6 | J73: 0.6 | K73: =Plan!E96 -> 0.6 | L73: Proporcional a las horas acumuladas de sus tareas
A74: 7.2.2 | B74: Publicacion App MASP en stores | C74: 0 | D74: 0 | E74: 0 | F74: 0.5 | G74: 0.5 | H74: 0.5 | I74: 0.5 | J74: 0.5 | K74: =Plan!E97 -> 0.5 | L74: Según evidencia documentada por mes
A75: 7.2.3 | B75: QA unitarias, estres y vulnerabilidad (App MASP) | C75: 0 | D75: 0 | E75: 0 | F75: 0 | G75: 0 | H75: 0 | I75: 0 | J75: 0 | K75: =Plan!E98 -> 0 | L75: Sin horas registradas
A76: 7.2.4 | B76: Pruebas de Aceptacion de Usuario UAT (App MASP) | C76: 0 | D76: 0 | E76: 0 | F76: 0 | G76: 0 | H76: 0 | I76: 0 | J76: 0 | K76: =Plan!E99 -> 0 | L76: Sin horas registradas
A77: 8.1.1 | B77: Migracion RedHat y recibo en produccion (SALVIA) | C77: 0 | D77: 0 | E77: 0 | F77: 0 | G77: 0 | H77: 0 | I77: 0 | J77: 0 | K77: =Plan!E102 -> 0 | L77: Sin horas registradas
A78: 8.1.2 | B78: Manuales y capacitaciones a funcionarios (SALVIA) | C78: 0 | D78: 0 | E78: 0 | F78: 0 | G78: 0 | H78: 0 | I78: 0.3 | J78: 0.3 | K78: =Plan!E103 -> 0.6 | L78: Según evidencia documentada por mes: videos compartidos en agosto
A79: 8.1.3 | B79: Registro ante la DNDA (propiedad intelectual web) | C79: 0 | D79: 0 | E79: 0 | F79: 0 | G79: 0 | H79: 0 | I79: 0 | J79: 0 | K79: =Plan!E104 -> 0 | L79: Sin horas registradas
A80: 8.2.1 | B80: Despliegue de APIs a produccion (MASP) | C80: 0 | D80: 0 | E80: 0 | F80: 0 | G80: 0 | H80: 0 | I80: 0 | J80: 0.5 | K80: =Plan!E106 -> 0.5 | L80: Proporcional a las horas acumuladas de sus tareas
A81: 8.2.2 | B81: Manuales y videos de uso App (MASP) | C81: 0 | D81: 0 | E81: 0 | F81: 0 | G81: 0 | H81: 0 | I81: 0 | J81: 0 | K81: =Plan!E107 -> 0.2 | L81: Sin horas registradas
A82: 8.2.3 | B82: Publicacion oficial en Play Store / App Store | C82: 0 | D82: 0 | E82: 0 | F82: 0.5 | G82: 0.5 | H82: 0.5 | I82: 0.5 | J82: 0.5 | K82: =Plan!E108 -> 0.5 | L82: Según evidencia documentada por mes
A83: 9.1.1 | B83: Validacion final de migracion RedHat y recibo (SALVIA) | C83: 0 | D83: 0 | E83: 0 | F83: 0 | G83: 0 | H83: 0 | I83: 0 | J83: 0 | K83: =Plan!E111 -> 0 | L83: Sin horas registradas
A84: 9.1.2 | B84: Validacion final de manuales y capacitaciones (SALVIA) | C84: 0 | D84: 0 | E84: 0 | F84: 0 | G84: 0 | H84: 0 | I84: 0 | J84: 0 | K84: =Plan!E112 -> 0.2 | L84: Sin horas registradas
A85: 9.1.3 | B85: Validacion final del registro ante DNDA | C85: 0 | D85: 0 | E85: 0 | F85: 0 | G85: 0 | H85: 0 | I85: 0 | J85: 0 | K85: =Plan!E113 -> 0 | L85: Sin horas registradas
A86: 9.2.1 | B86: Validacion final de despliegue de APIs (MASP) | C86: 0 | D86: 0 | E86: 0 | F86: 0 | G86: 0 | H86: 0 | I86: 0 | J86: 0 | K86: =Plan!E115 -> 0 | L86: Sin horas registradas
A87: 9.2.2 | B87: Validacion final de manuales y videos de uso App | C87: 0 | D87: 0 | E87: 0 | F87: 0 | G87: 0 | H87: 0 | I87: 0 | J87: 0 | K87: =Plan!E116 -> 0 | L87: Sin horas registradas
A88: 9.2.3 | B88: Validacion final de publicacion en tiendas | C88: 0 | D88: 0 | E88: 0 | F88: 0 | G88: 0 | H88: 0 | I88: 0 | J88: 0 | K88: =Plan!E117 -> 0 | L88: Sin horas registradas
A89: 10.1.1 | B89: Preparacion de documentacion tecnica para DNDA (Web) | C89: 0 | D89: 0 | E89: 0 | F89: 0 | G89: 0 | H89: 0 | I89: 0 | J89: 0 | K89: =Plan!E120 -> 0 | L89: Sin horas registradas
A90: 10.1.2 | B90: Radicacion y seguimiento DNDA (Web) | C90: 0 | D90: 0 | E90: 0 | F90: 0 | G90: 0 | H90: 0 | I90: 0 | J90: 0 | K90: =Plan!E121 -> 0 | L90: Sin horas registradas
A91: 10.2.1 | B91: Preparacion de documentacion tecnica para DNDA (App) | C91: 0 | D91: 0 | E91: 0 | F91: 0 | G91: 0 | H91: 0 | I91: 0 | J91: 0 | K91: =Plan!E123 -> 0 | L91: Sin horas registradas
A92: 10.2.2 | B92: Radicacion y seguimiento DNDA (App) | C92: 0 | D92: 0 | E92: 0 | F92: 0 | G92: 0 | H92: 0 | I92: 0 | J92: 0 | K92: =Plan!E124 -> 0 | L92: Sin horas registradas
A93: 11.1.1 | B93: Compra y configuracion de cuenta Play Store | C93: 0 | D93: 0 | E93: 0 | F93: 0.5 | G93: 0.5 | H93: 0.5 | I93: 0.5 | J93: 0.5 | K93: =Plan!E127 -> 0.5 | L93: Según evidencia documentada por mes
A94: 11.1.2 | B94: Compra y configuracion de cuenta App Store | C94: 0 | D94: 0 | E94: 0 | F94: 0 | G94: 0 | H94: 0 | I94: 0 | J94: 0 | K94: =Plan!E128 -> 0 | L94: Sin horas registradas
A95: 11.2.1 | B95: Publicacion oficial en Play Store | C95: 0 | D95: 0 | E95: 0 | F95: 0.5 | G95: 0.5 | H95: 0.5 | I95: 0.5 | J95: 0.75 | K95: =Plan!E130 -> 0.75 | L95: Según evidencia documentada por mes
A96: 11.2.2 | B96: Publicacion oficial en App Store | C96: 0 | D96: 0 | E96: 0 | F96: 0 | G96: 0 | H96: 0 | I96: 0 | J96: 0 | K96: =Plan!E131 -> 0 | L96: Sin horas registradas
A97: 12.1.1 | B97: Plan de capacitacion SALVIA Web | C97: 0 | D97: 0 | E97: 0 | F97: 0 | G97: 0.25 | H97: 0.25 | I97: 0.25 | J97: 0.25 | K97: =Plan!E134 -> 0.5 | L97: Según evidencia documentada por mes
A98: 12.1.2 | B98: Capacitaciones masivas a Linea 155 y gestoras | C98: 0 | D98: 0 | E98: 0 | F98: 0 | G98: 0 | H98: 0 | I98: 0 | J98: 0 | K98: =Plan!E135 -> 0.25 | L98: Sin horas registradas
A99: 12.1.3 | B99: Encuestas de adopcion y apropiacion (Web) | C99: 0 | D99: 0 | E99: 0 | F99: 0 | G99: 0 | H99: 0 | I99: 0 | J99: 0 | K99: =Plan!E136 -> 0 | L99: Sin horas registradas
A100: 12.2.1 | B100: Plan de capacitacion App MASP | C100: 0 | D100: 0 | E100: 0 | F100: 0 | G100: 0 | H100: 0 | I100: 0 | J100: 0 | K100: =Plan!E138 -> 0 | L100: Sin horas registradas
...

Sheet Despliegue_13oct
A1: N.º | B1: Sección | C1: Cambio listo para main | D1: Ítem EDT | E1: Hito | F1: Bitácora (1-oct) | G1: Matriz SALVIA (8-oct) | H1: Lectura
A2: 1 | B2: Detalle de Caso — Derivaciones | C2: Nueva sección donde el Equipo Técnico puede dejar comentarios de análisis del caso, visibles en el historial. | D2: 6.1.12 | E2: M1 | F2: RUT-13 | H2: Corrige un hallazgo registrado; pendiente de despliegue y validación
A3: 2 | B3: Detalle de Caso — Derivaciones | C3: Nuevo modal para que el Equipo Técnico remita un caso directamente a otros equipos (medidas de emergencia, psicosocial, atención a hombres, estabilización económica), sin pasar por el formulario de seguimiento. | D3: 6.1.12 | E3: M1 | H3: Mejora o funcionalidad nueva lista para despliegue
A4: 3 | B4: Detalle de Caso — Derivaciones | C4: El supervisor ahora también puede remitir un caso a psicosocial desde Derivaciones (antes solo podía hacerlo el Equipo Técnico). | D4: 6.1.11 | E4: M1 | H4: Mejora o funcionalidad nueva lista para despliegue
A5: 4 | B5: Detalle de Caso — Derivaciones | C5: Nueva tabla “Profesionales de atención” que muestra a todas las personas que han intervenido en el caso. | D5: 3.1.3 | E5: M1 | F5: SEG-34, SEG-36 | G5: Seguimiento #29 | H5: Corrige un hallazgo registrado; pendiente de despliegue y validación
A6: 5 | B6: Detalle de Caso — Derivaciones | C6: Se quitó de esa tabla la columna “Notas”, por ser poco legible; el detalle de cada actividad sigue disponible en la pestaña Timeline. | D6: 3.1.3 | E6: M1 | G6: Seguimiento #41 | H6: Corrige un hallazgo registrado; pendiente de despliegue y validación
A7: 6 | B7: Detalle de Caso — Derivaciones | C7: La sección de comentarios del Equipo Técnico se amplió para incluir también el análisis y las decisiones tomadas en la mesa técnica, bajo el nuevo nombre “Análisis del caso”. | D7: 6.1.12 | E7: M1 | F7: RUT-13 | H7: Corrige un hallazgo registrado; pendiente de despliegue y validación
A8: 7 | B8: Detalle de Caso — Seguimientos | C8: Los hechos reportados ahora se muestran ordenados cronológicamente por fecha del suceso. | D8: 6.1.5 | E8: M1 | F8: SEG-20 | G8: Seguimiento #30 | H8: Corrige un hallazgo registrado; pendiente de despliegue y validación
A9: 8 | B9: Detalle de Caso — Seguimientos | C9: Un seguimiento pendiente cuya fecha ya pasó se marca automáticamente como “Vencido” y deja de contarse en la numeración de seguimientos. | D9: 6.1.5 | E9: M1 | F9: SEG-32 | G9: Seguimiento #31 | H9: Corrige un hallazgo registrado; pendiente de despliegue y validación
A10: 9 | B10: Detalle de Caso — Seguimientos | C10: Nuevo aviso que explica por qué un seguimiento no se puede editar (caso cerrado, formulario migrado, etc.). | D10: 6.1.5 | E10: M1 | H10: Mejora o funcionalidad nueva lista para despliegue
A11: 10 | B11: Detalle de Caso — Seguimientos | C11: Se corrigió que Ciudad y Municipio no cargaban al ver el detalle de un seguimiento. | D11: 6.1.5 | E11: M1 | F11: SEG-31 | G11: Seguimiento #33 | H11: Corrige un hallazgo registrado; pendiente de despliegue y validación
A12: 11 | B12: Detalle de Caso — Seguimientos | C12: Se corrigió un error de zona horaria que podía rechazar una reprogramación válida cerca de las 10 p.m. | D12: 6.1.5 | E12: M1 | F12: SEG-26 | H12: Corrige un hallazgo registrado; pendiente de despliegue y validación
A13: 12 | B13: Detalle de Caso — Seguimientos | C13: Se corrigió un error que impedía abrir el formulario de seguimiento desde su propio detalle. | D13: 6.1.5 | E13: M1 | H13: Mejora o funcionalidad nueva lista para despliegue
A14: 13 | B14: Detalle de Caso — Tareas | C14: La pestaña Tareas ahora filtra para que el usuario de una entidad solo vea las tareas asignadas a él. | D14: 6.1.12 | E14: M1 | H14: Mejora o funcionalidad nueva lista para despliegue
A15: 14 | B15: Detalle de Caso — Tareas | C15: Se amplió el límite de caracteres permitido en los campos del formulario de tareas. | D15: 6.1.5 | E15: M1 | F15: SEG-11 | G15: Seguimiento #9 | H15: Corrige un hallazgo registrado; pendiente de despliegue y validación
A16: 15 | B16: Detalle de Caso — Mecanismos Articuladores | C16: Nueva tarjeta de Mecanismos en la gestión institucional del caso, para escalarlo a un mecanismo articulador (municipal, departamental o nacional). | D16: 6.1.12 | E16: M1 | H16: Mejora o funcionalidad nueva lista para despliegue
A17: 16 | B17: Detalle de Caso — Mecanismos Articuladores | C17: El bloque de Mecanismos ahora aparece después de Barreras, siguiendo primero la barrera identificada y luego el mecanismo con el que se gestiona. | D17: 6.1.12 | E17: M1 | H17: Mejora o funcionalidad nueva lista para despliegue
A18: 17 | B18: Detalle de Caso — Mecanismos Articuladores | C18: Ajustes al formulario según el alcance del mecanismo (municipal, departamental o nacional). | D18: 6.1.12 | E18: M1 | H18: Mejora o funcionalidad nueva lista para despliegue
A19: 18 | B19: Detalle de Caso — General | C19: Solo el rol supervisor puede reabrir un caso. | D19: 6.1.5 | E19: M1 | F19: SEG-29 | G19: Seguimiento #34 | H19: Corrige un hallazgo registrado; pendiente de despliegue y validación
A20: 19 | B20: Detalle de Barrera | C20: Nueva pestaña “Oficios” que muestra los oficios asociados a esa barrera específica. | D20: 6.1.12 | E20: M1 | H20: Mejora o funcionalidad nueva lista para despliegue
A21: 20 | B21: Comité Técnico (Decisiones) | C21: Nueva opción “Activar Enlace Territorial” en las decisiones del comité: permite elegir el enlace destino y crea automáticamente su tarea de articulación. | D21: 6.1.12 | E21: M1 | H21: Mejora o funcionalidad nueva lista para despliegue
A22: 21 | B22: Comité Técnico (Decisiones) | C22: Al asociar una entidad a un caso, ahora se puede marcar un checklist de tareas u obligaciones que esa entidad debe gestionar. | D22: 6.1.12 | E22: M1 | F22: RUT-03 | G22: Rutas #8 | H22: Atiende un hallazgo que la matriz aún marca abierto; pendiente de despliegue y validación
A23: 22 | B23: Comité Técnico (Decisiones) | C23: La tarea “Decisiones del Comité” ahora es una bolsa de trabajo abierta a todo el Equipo Técnico (antes se asignaba a una sola persona). | D23: 6.1.12 | E23: M1 | F23: RUT-14 | H23: Corrige un hallazgo registrado; pendiente de despliegue y validación
A24: 23 | B24: Comité Técnico (Decisiones) | C24: Nuevo paso de “Gestión del oficio” en la decisión del comité, indicando quién lo gestiona. | D24: 6.1.12 | E24: M1 | F24: RUT-13 | H24: Corrige un hallazgo registrado; pendiente de despliegue y validación
A25: 24 | B25: Comité Técnico (Decisiones) | C25: Se muestra la entidad y la solicitud relacionada en las tarjetas de tareas de enlace territorial. | D25: 6.1.12 | E25: M1 | F25: RUT-10 | G25: Rutas #5 | H25: Atiende un hallazgo que la matriz aún marca abierto; pendiente de despliegue y validación
A26: 25 | B26: Gestión Institucional (Entidades vinculadas al caso) | C26: Nuevo checklist de obligaciones pendientes por entidad, visible al vincular una entidad al caso. | D26: 6.1.12 | E26: M1 | F26: RUT-03 | G26: Rutas #8 | H26: Atiende un hallazgo que la matriz aún marca abierto; pendiente de despliegue y validación
A27: 26 | B27: Gestión Institucional (Entidades vinculadas al caso) | C27: Nuevo modal de “Respuesta institucional” para que la entidad registre el estado de su gestión (radicado, ampliación, estado). | D27: 6.1.12 | E27: M1 | H27: Mejora o funcionalidad nueva lista para despliegue
A28: 27 | B28: Gestión Institucional (Entidades vinculadas al caso) | C28: Se crea automáticamente una tarea para la entidad cuando el agente procesa una solicitud institucional. | D28: 6.1.12 | E28: M1 | H28: Mejora o funcionalidad nueva lista para despliegue
A29: 28 | B29: Gestión Institucional (Entidades vinculadas al caso) | C29: Se agregó el campo “N.º de radicado/NUNC/MP” al registrar que la víctima ya acudió a una entidad. | D29: 6.1.12 | E29: M1 | H29: Mejora o funcionalidad nueva lista para despliegue
A30: 29 | B30: Gestión Institucional (Entidades vinculadas al caso) | C30: Se corrigió que el panel de Gestión Institucional se rompía por completo si fallaba una sola de sus fuentes de datos. | D30: 6.1.12 | E30: M1 | H30: Mejora o funcionalidad nueva lista para despliegue
A31: 30 | B31: Casos Entidad y Casos Mecanismo (roles externos) | C31: Nueva pantalla de detalle del caso para el usuario de una entidad (antes el botón “Ver detalle” solo mostraba un aviso de “pendiente”). | D31: 6.1.12 | E31: M1 | G31: Rutas #11 | H31: Atiende un hallazgo que la matriz aún marca abierto; pendiente de despliegue y validación
A32: 31 | B32: Casos Entidad y Casos Mecanismo (roles externos) | C32: Nueva pantalla “Casos Mecanismo” donde el usuario mecanismo ve sus casos activos asignados, con el historial de sus gestiones. | D32: 6.1.12 | E32: M1 | H32: Mejora o funcionalidad nueva lista para despliegue
A33: 32 | B33: Casos Entidad y Casos Mecanismo (roles externos) | C33: Estos roles (Entidad, Mecanismo) ya no ven el menú de Reportes ni la lista general de casos; cada uno navega directo a su propia pantalla al iniciar sesión. | D33: 6.1.12 | E33: M1 | H33: Mejora o funcionalidad nueva lista para despliegue
A34: 33 | B34: Identificación de Entidades (formularios) | C34: La sección para registrar entidades a las que la víctima ya acudió ahora también está disponible en Primera Atención, Atención Psicosocial, Cierre y en el Registro de Caso (antes faltaba en esas pantallas). | D34: 6.1.12 | E34: M1 | H34: Mejora o funcionalidad nueva lista para despliegue
A35: 34 | B35: Mis Acciones Institucionales (rol Entidad) | C35: Nueva pantalla para que la entidad vea y complete sus acciones institucionales pendientes, con pestañas de Pendientes y Completadas. | D35: 6.1.12 | E35: M1 | F35: RUT-16, RUT-17 | H35: Corrige un hallazgo registrado; pendiente de despliegue y validación
A36: 35 | B36: Mis Acciones Institucionales (rol Entidad) | C36: Rediseño de la pantalla con tarjetas en rejilla, checklist colapsable y barra de progreso por caso. | D36: 6.1.12 | E36: M1 | H36: Mejora o funcionalidad nueva lista para despliegue
A37: 36 | B37: Mis Acciones Institucionales (rol Entidad) | C37: Se corrigió un error que impedía cargar la pantalla cuando la ciudad del filtro no era válida. | D37: 6.1.12 | E37: M1 | H37: Mejora o funcionalidad nueva lista para despliegue
A38: 37 | B38: Directorio de Entidades | C38: Nuevo catálogo de competencias por entidad, para sugerir opciones en los formularios de seguimiento. | D38: 6.1.12 | E38: M1 | G38: Rutas #7 | H38: Atiende un hallazgo que la matriz aún marca abierto; pendiente de despliegue y validación
A39: 38 | B39: Directorio de Entidades | C39: Nueva carga masiva del Directorio desde un archivo. | D39: 6.1.12 | E39: M1 | F39: RUT-02 | G39: Rutas #1-3 | H39: Atiende un hallazgo que la matriz aún marca abierto; pendiente de despliegue y validación
A40: 39 | B40: Directorio de Entidades | C40: Se corrigió el filtro por departamento, que no encontraba entidades antiguas (incluida Bogotá). | D40: 6.1.12 | E40: M1 | F40: PSI-15 | G40: Psicosocial #13 | H40: Corrige un hallazgo registrado; pendiente de despliegue y validación
A41: 40 | B41: Directorio de Entidades | C41: Se corrigieron las etiquetas de ubicación para que coincidan con la jerarquía oficial (Municipio / Centro poblado). | D41: 6.1.12 | E41: M1 | F41: SEG-16 | G41: Seguimiento #36 | H41: Corrige un hallazgo registrado; pendiente de despliegue y validación
A42: 41 | B42: Remisión Psicosocial | C42: El cierre y la validación de una remisión ya no fallan por datos faltantes. | D42: 6.1.11 | E42: M1 | F42: PSI-03 | G42: Psicosocial #31, #93 | H42: Corrige un hallazgo registrado; pendiente de despliegue y validación
A43: 42 | B43: Remisión Psicosocial | C43: Se corrigió el botón de contacto inmediato, que ahora abre el formulario de atención en vez de un aviso de “pendiente”. | D43: 6.1.11 | E43: M1 | F43: PSI-14 | G43: Psicosocial #102 | H43: Corrige un hallazgo registrado; pendiente de despliegue y validación
A44: 43 | B44: Remisión Psicosocial | C44: El buscador de “profesional asignada” ahora solo sugiere profesionales realmente asignados a una remisión. | D44: 6.1.11 | E44: M1 | F44: PSI-23 | G44: Psicosocial #101 | H44: Corrige un hallazgo registrado; pendiente de despliegue y validación
A45: 44 | B45: Remisión Psicosocial | C45: Se unificó la terminología en toda la interfaz (“Profesional en Psicología” / “Profesional en Trabajo Social” / “Profesional psicosocial” según el contexto). | D45: 6.1.11 | E45: M1 | F45: PSI-09, PSI-19 | G45: Psicosocial #6, #7 | H45: Corrige un hallazgo registrado; pendiente de despliegue y validación
A46: 45 | B46: Remisión Psicosocial | C46: El detalle de la remisión ahora permite filtrar y ordenar los contactos, y oculta el botón de registrar contacto al supervisor. | D46: 6.1.11 | E46: M1 | H46: Mejora o funcionalidad nueva lista para despliegue
A47: 46 | B47: Remisión Psicosocial | C47: Se exige registrar los criterios y la evidencia de la remisión en todas las formas de crearla, no solo desde el formulario. | D47: 6.1.11 | E47: M1 | H47: Mejora o funcionalidad nueva lista para despliegue
A48: 47 | B48: Remisión Psicosocial | C48: Si en el Primer Contacto la persona no desea continuar, el contacto queda registrado pero la remisión sigue abierta para un nuevo intento, en vez de cerrarse por error. También se corrigió que una sesión podía quedar marcada como “realizada” antes de completarse, duplicando el conteo. | D48: 6.1.11 | E48: M1 | F48: PSI-21, PSI-01 | G48: Psicosocial #74, #43, #66 | H48: Corrige un hallazgo registrado; pendiente de despliegue y validación
A49: 48 | B49: Calendario Psicosocial | C49: El supervisor ahora puede filtrar el calendario por dupla de profesionales (psicólogo y trabajador social). | D49: 6.1.11 | E49: M1 | F49: PSI-04 | G49: Psicosocial #70 | H49: Corrige un hallazgo registrado; pendiente de despliegue y validación
A50: 49 | B50: Calendario Psicosocial | C50: El calendario ahora también muestra los seguimientos psicosociales programados automáticamente. | D50: 6.1.11 | E50: M1 | F50: PSI-12 | G50: Psicosocial #16 | H50: Corrige un hallazgo registrado; pendiente de despliegue y validación
A51: 50 | B51: Formularios Psicosociales (Primer Contacto, Atención, Cierre) | C51: Nueva sección de “Derivación a equipos SALVIA” al final de cada formulario psicosocial, para remitir el caso a otros equipos. | D51: 6.1.11 | E51: M1 | H51: Mejora o funcionalidad nueva lista para despliegue
A52: 51 | B52: Formularios Psicosociales (Primer Contacto, Atención, Cierre) | C52: Se retiraron las preguntas de tipo y número de documento de una sección que ya no las requiere. | D52: 6.1.11 | E52: M1 | H52: Mejora o funcionalidad nueva lista para despliegue
A53: 52 | B53: Reporte Ciudadano (formulario público) | C53: Nueva versión del formulario público de reporte ciudadano, con más pasos y más tipos de reportante disponibles. | D53: 6.1.8 | E53: M2 | F53: MOC-01 | H53: Corrige un hallazgo registrado; pendiente de despliegue y validación
A54: 53 | B54: Reporte Excel Consolidado | C54: Se agregaron cerca de 30 campos adicionales al reporte consolidado. | D54: 6.1.1 | E54: M1 | F54: SEG-10 | G54: Seguimiento #1 | H54: Corrige un hallazgo registrado; pendiente de despliegue y validación
A55: 54 | B55: Reporte Excel Consolidado | C55: Se corrigió un error que mezclaba el tipo y el subtipo de violencia en el reporte. | D55: 6.1.1 | E55: M1 | F55: SEG-08 | H55: Corrige un hallazgo registrado; pendiente de despliegue y validación
A56: 55 | B56: Lista de Casos | C56: Nueva columna que muestra el avance de los intentos de contacto del seguimiento activo de cada caso. | D56: 5.1.3 | E56: M1 | F56: SEG-42 | H56: Corrige un hallazgo registrado; pendiente de despliegue y validación
A57: 56 | B57: Roles y Permisos | C57: El Equipo Técnico ahora tiene acceso a “Mis Tareas” y “Lista Casos”. | D57: 6.1.12 | E57: M1 | H57: Mejora o funcionalidad nueva lista para despliegue
A58: 57 | B58: Roles y Permisos | C58: Se restringió la pantalla de crear caso solo a los roles de agente correspondientes. | D58: 5.1.1 | E58: M1 | F58: SEG-50 | G58: Rutas #10 | H58: Atiende un hallazgo que la matriz aún marca abierto; pendiente de despliegue y validación
A59: 58 | B59: Roles y Permisos | C59: El rol Operador Territorial Nacional ahora también puede acceder a “Mis Barreras”. | D59: 6.1.12 | E59: M1 | H59: Mejora o funcionalidad nueva lista para despliegue
A60: 59 | B60: Roles y Permisos | C60: El rol Mecanismo ya no ve la gestión interna del caso (Derivaciones, Seguimientos, Timeline). | D60: 6.1.12 | E60: M1 | H60: Mejora o funcionalidad nueva lista para despliegue
A61: 60 | B61: Administración de Usuarios | C61: Se agregó el campo “Equipo” (seguimiento general o de riesgo) al crear o editar un usuario con rol Operador de Seguimiento. | D61: 5.1.1 | E61: M1 | F61: SEG-23 | H61: Corrige un hallazgo registrado; pendiente de despliegue y validación
A62: 61 | B62: Ajustes técnicos internos (sin cambios visibles para el usuario) | C62: Correcciones técnicas tras realizar la fusión de código. | D62: 7.1.3 | E62: H09 | H62: Mejora o funcionalidad nueva lista para despliegue
A63: 62 | B63: Ajustes técnicos internos (sin cambios visibles para el usuario) | C63: Nuevo registro de auditoría sobre qué agente queda asignado a cada caso y por qué. | D63: 5.1.3 | E63: M1 | F63: SEG-03 | H63: Corrige un hallazgo registrado; pendiente de despliegue y validación
A64: 63 | B64: Ajustes técnicos internos (sin cambios visibles para el usuario) | C64: Se corrigió que el ambiente de pruebas redirigía por error a la página pública de producción. | D64: 7.1.3 | E64: H09 | H64: Mejora o funcionalidad nueva lista para despliegue
A65: 64 | B65: Ajustes técnicos internos (sin cambios visibles para el usuario) | C65: Se unificó la zona horaria del sistema a hora Colombia en los procesos internos. | D65: 6.1.5 | E65: M1 | F65: SEG-07 | G65: Seguimiento #7 | H65: Corrige un hallazgo registrado; pendiente de despliegue y validación
A67: Fuente: SALVIA_Proximo_Despliegue_a_Main (corte 13-oct-2026) y Matriz_hallazgos_Salvia (revisión Kreivo 8-oct-2026). Los cambios de Enlace Territorial se validan aparte y no están en esta lista. La asociación con bitácora y matriz es por contenido.

Sheet Commits_23oct
A1: N.º | B1: Fecha | C1: Autor | D1: Commit | E1: Sección | F1: Cambio en testing | G1: Ítem EDT | H1: Hito | I1: Lectura
A2: 1 | B2: 46308 | C2: Santiago Ramos | D2: 1dee9b9 | E2: Lista de casos | F2: Los casos registrados quedan con estado (antes podían quedar sin estado) | G2: 5.1.3 | H2: M1 | I2: Corrige hallazgo
A3: 2 | B3: 46309 | C3: Andrés Felipe Ascencio | D3: 1a08a2c | E3: Reporte y Registro | F3: Listado y Mis Reportes con modal de gestión (cierre, esquema 3x3, reasignación) y Registro V3 completo: Habeas Data, cabezote, 7 módulos, tamizaje, Gestión Salvia y cierre | G3: 6.1.8 | H3: M2 | I3: Funcionalidad nueva
A4: 3 | B4: 46310 | C4: Andrés Felipe Ascencio | D4: 2c78f3b | E4: Reporte y Registro | F4: QA de Registro V3 con Playwright de punta a punta; 8 bugs corregidos y plan de pruebas con 25 casos | G4: 6.1.8, 7.1.5 | H4: M2, H08 | I4: QA
A5: 4 | B5: 46310 | C5: Santiago Ramos | D5: 54d6294 | E5: Formulario de seguimiento V4 | F5: Prototipo del formulario de seguimiento V4 (integrando Salvia Dignidad) a partir del Excel del 14-oct | G5: 4.2.2 | H5: M1 | I5: Prototipo
A6: 5 | B6: 46311 | C6: Santiago Ramos | D6: ac99cb5 | E6: Formulario de seguimiento V4 | F6: Ajustes del prototipo | G6: 4.2.2 | H6: M1 | I6: Prototipo
A7: 6 | B7: 46311 | C7: Santiago Ramos | D7: 9fb40c8 | E7: Formulario de seguimiento V4 | F7: Salto entre secciones del prototipo | G7: 4.2.2 | H7: M1 | I7: Prototipo
A8: 7 | B8: 46314 | C8: Santiago Ramos | D8: 4f9b633 | E8: Lista de casos | F8: Muestra y filtra los estados de caso que la lista dejaba como Desconocido | G8: 3.1.3, 5.1.3 | H8: M1 | I8: Corrige hallazgo
A9: 8 | B9: 46314 | C9: Juan Nicolás Buitrago | D9: e09fb2f | E9: Atención Psicosocial | F9: Indicador de atenciones realizadas y agendadas en detalle y remisiones, filtro por estado y nuevo seguimiento con autoasignación para rol an | G9: 6.1.11 | H9: M1 | I9: Mejora
A10: 9 | B10: 46315 | C10: Brandon Martín | D10: b207846 | E10: Atención Psicosocial | F10: Abrir el seguimiento desde la cita y mostrar siempre el filtro por dupla | G10: 6.1.11 | H10: M1 | I10: Mejora
A11: 10 | B11: 46315 | C11: Brandon Martín | D11: 2b8e270 | E11: Atención Psicosocial | F11: Prueba del calendario actualizada tras los seguimientos v2 | G11: 6.1.11, 7.1.5 | H11: M1 | I11: QA
A12: 11 | B12: 46315 | C12: Santiago Ramos | D12: c139c9d | E12: Formulario de seguimiento V4 | F12: Ajustes del prototipo | G12: 4.2.2 | H12: M1 | I12: Prototipo
A13: 12 | B13: 46315 | C13: Santiago Ramos | D13: 664e08c | E13: Formulario de seguimiento V4 | F13: Ajustes del prototipo v4 | G13: 4.2.2 | H13: M1 | I13: Prototipo
... A28: 27 | B28: 46318 | C28: Santiago Ramos | D28: b6756a1 | E28: Formulario de seguimiento V4 | F28: Ajuste de pregunta condicional del prototipo | G28: 4.2.2 | H28: M1 | I28: Prototipo
A30: Fuente: commits sin merges de las ramas develop y testing del repositorio SOG_SALVIA entre el 13 y el 23-oct-2026 (testing en PR #132). Ninguno está en main, que sigue sin cambios desde el 10-sep.

Sheet Trabajo_sin_horas
A1: Fecha | B1: Entregable | C1: Tipo | D1: Hitos | E1: Items_EDT | F1: Estado | G1: Descripcion
A2: 46318 | B2: 29 commits en testing del 13 al 23-oct (hoja Commits_23oct) | C2: Desarrollo | D2: M1, M2, M4, M5, H08 | E2: 6.1.8, 6.1.11, 6.1.12, 6.1.5, 4.2.2, 3.1.3, 5.1.3, 7.1.5 | F2: En testing (QA); pendientes de paso a main y validación por SALVIA | G2: Registro V3 completo con QA en Playwright; migración de Alcaldías y 38 entidades con acciones institucionales; correcciones del rol entidad pedidas por la supervisión (sede, cerrar sesión, Mis Tareas, estilos, sucursal); prototipo del formulario de seguimiento V4; mejoras de Psicosocial y Seguimiento. Sus horas entran por la hoja Horas_Jira (Sprints 19 a 21).
A3: 46308 | B3: Mockup de Reportes, Registro y Alerta Inminente | C3: Mockup | D3: M2, M4, M5, M1 | E3: 4.4.1, 4.4.2, 4.4.3, 4.4.4, 4.4.5, 4.4.7 | F3: Aprobado por Gestión del Conocimiento (según el equipo) | G3: Integra el Guion Funcional de Registro v3.0 y el Formulario v5.0: reporte ciudadano, gestión de reportes con recontacto 3x3, registro de la víctima con preguntas OSIGD y ASP, tamizaje de feminicidio con bifurcaciones y puntaje, alerta inminente y envío del caso a Seguimiento. Archivo: Mockup_Reportes_Registro_Alerta.html.
A4: 46308 | B4: Formulario de alerta inminente (dentro del mockup de Reportes y Registro) | C4: Mockup | D4: M3, M1 | E4: 4.5.2 | F4: Aprobado con el mockup (según el equipo) | G4: Activación y reactivación de la alerta inminente desde el caso; conecta con el riesgo inminente de las historias de Medidas de Emergencia (HUE-002 y HUE-004). Relacionado con MOC-06 de la bitácora.
A5: 46301 | B5: Historias de usuario de Medidas de Emergencia v1.0 | C5: Historias de usuario | D5: M3 | E5: 4.5.1 | F5: Entregado; base para el mockup de Medidas | G5: 38 historias en 12 grupos: remisión, riesgo inminente, revisión del Equipo Técnico, bandeja y asignación, consentimiento y caracterización, aprobación, Cruz Roja, seguimiento, matriz de medidas, novedades, conclusión y trazabilidad. No cubren familiares ni personas huérfanas.
A6: 46292 | B6: Guía y guion de grabación de los 22 videos del mockup de Reporte y Registro | C6: Documentación | D6: M2, M4, M5, M1 | E6: 4.4.2 | F6: Entregados; los videos no se grabaron | G6: Guía funcional de las 22 partes y guion de grabación clip a clip. Los videos no se grabaron porque el HTML y sus componentes se entregaron directamente al equipo de desarrollo.
A7: 46308 | B7: Entrega del HTML del mockup de Reporte y Registro al equipo de desarrollo | C7: Desarrollo | D7: M2, M4, M5, M1 | E7: 6.1.8 | F7: En construcción; paso al servidor de pruebas prevista para finales de la semana del 13-oct o, a más tardar, a mediados de la semana del 20-oct | G7: El equipo de desarrollo toma el HTML y sus componentes para construir el nuevo Reporte y Registro (formularios de tamizaje, LGBTIQ+ y ASP) en el servidor de pruebas.
A8: 46308 | B8: 64 cambios listos para el próximo despliegue a main | C8: Desarrollo y despliegue | D8: M1, H09 | E8: 6.1.5, 6.1.11, 6.1.12 y otros (hoja Despliegue_13oct) | F8: Listos en la rama; pendientes de despliegue y validación | G8: Parte del desarrollo de septiembre sí está en TimeLogs; las horas de octubre aún no están registradas. Se menciona para que el avance no dependa solo del registro de horas.
A9: 46265 | B9: Videos de uso de SALVIA Web (15), Mapa de navegación e historias de usuario consolidadas | C9: Videos y documentación | D9: H10, M1 | E9: 6.1.2, 7.1.2, 8.1.2 | F9: Compartidos con la entidad en el cobro de agosto (carpeta 08_2026_Kreivo_Cobro). Según el equipo (28-oct), la entidad los usa en capacitaciones masivas a satisfacción y parte fueron aceptados para producción | G9: Videos: consulta y gestión de caso, detalle y timeline del caso, iniciar y detallar seguimiento, esquema 3x3, plan automático de contactos, reasignación por supervisor, gestión de tareas, reporte de casos, barreras, notificaciones, ciclo del oficio y rol agente de notificaciones. Fecha: cierre del periodo de cobro de agosto.
A10: 46310 | B10: Manuales técnicos de SALVIA (9, en PDF) | C10: Documentación | D10: H10 | E10: 6.1.2, 8.1.2, 8.2.2 | F10: Entregados en la carpeta de Drive del proyecto; pendiente validación por SALVIA. Horas incluidas en octubre dentro de las de Andrés Posada (hoja Horas_Jira) | G10: Seguimiento; Barreras, notificaciones y oficios; Psicosocial; Reporte, Registro y Alerta inminente; Medidas de Emergencia y Estabilización; Rutas y gestión institucional; Usuarios, roles y permisos; Arquitectura e infraestructura; App MASP. Cada manual marca lo implementado, lo pendiente de main y lo por validar.
A11: 46314 | B11: Red de acción SALVIA (mapa interactivo) | C11: Material de capacitación | D11: H10 | E11: 7.1.2, 12.1.1 | F11: Publicada en el tablero de hitos (pipeline.html). Horas incluidas en octubre dentro de las de Andrés Posada (hoja Horas_Jira) | G11: 30 pantallas en cinco familias de roles, traspasos en serie y en paralelo, alerta inminente transversal y 74 capturas de los mockups. Base para capacitar por rol.
A12: Trabajo realizado que no está registrado, o no completo, en TimeLogs. Se muestra en el tablero como evidencia; no suma ni modifica las horas reportadas.

Sheet Riesgos_QA
A1: ID | B1: Fuente | C1: Modulo | D1: Hito | E1: Severidad | F1: Fecha_deteccion | G1: Estado | H1: Fecha_cierre | I1: Critico | J1: Descripcion
A2: SEG-1 | B2: Matriz de hallazgos (cliente) | C2: Seguimiento | D2: M1 | E2: Alta | F2: 46234 | G2: En Proceso | I2: Sí | J2: Sin trazabilidad de asignaciones automáticas - Descarga reporte consolidado: en las pestañas de seguimientos y casos no aparece la columna de que agente tiene el caso actualmente.
A3: SEG-2 | B3: Matriz de hallazgos (cliente) | C3: Seguimiento | D3: M1 | E3: Alta | F3: 46234 | G3: Cerrado | H3: 46294 | I3: Sí | J3: Botón de "guardar borrador" se desplegó sin avisar a Laura ni a los agentes — en los despliegues siempre avisarle a lau que funcionalidades nuevas se están subiendo
A4: SEG-3 | B4: Matriz de hallazgos (cliente) | C4: Seguimiento | D4: M1 | E4: Media | F4: 46234 | G4: Cerrado | H4: 46294 | I4: No | J4: Orden de seguimientos desordenado: Cuando se atiende un caso del cual se hizo las migraciones los seguimientos están quedando supremamente desordenados ej: caso 1122268334 producci
A5: SEG-4 | B5: Matriz de hallazgos (cliente) | C5: Seguimiento | D5: M1 | E5: Sin severidad | G5: Sin estado | I5: No | J5: - Migración
A6: SEG-5 | B6: Matriz de hallazgos (cliente) | C6: Seguimiento | D6: M1 | E6: Sin severidad | G6: Sin estado | I6: No | J6: - Reasignación de 3x3 - pasa al sigueitne seguimiento
A7: SEG-6 | B7: Matriz de hallazgos (cliente) | C7: Seguimiento | D7: M1 | E7: Sin severidad | G7: Sin estado | I7: No | J7: - + Nuevo seguimiento - agrega uno al final de la cola
A8: SEG-4-b | B8: Matriz de hallazgos (cliente) | C8: Seguimiento | D8: M1 | E8: Baja | F8: 46234 | G8: Cerrado | H8: 46294 | I8: No | J8: Pregúntas del formulario de seguimietno no se arrastran al resumen: hay preguntas del formulario de seguimiento que deben estar en el resumen del seguimiento, esto lo indico lau ha
A9: SEG-5-b | B9: Matriz de hallazgos (cliente) | C9: Seguimiento | D9: M1 | E9: Baja | F9: 46234 | G9: Cerrado | H9: 46294 | I9: No | J9: Botón "atrás" funciona mal: al salir del caso y dar "atrás", en vez de volver a la lista de casos manda al reporte; y desde seguimientos manda a información general en vez de un pa
A10: SEG-6-b | B10: Matriz de hallazgos (cliente) | C10: Seguimiento | D10: M1 | E10: Baja | F10: 46234 | G10: Cerrado | H10: 46294 | I10: No | J10: Etiquetas de equipo incorrectas: los equipos aparecen como "riesgo bajo" / "riesgo alto" en la pantalla de lista de casos, pero deberían llamarse "equipo de seguimiento general" (B
A11: SEG-7 | B11: Matriz de hallazgos (cliente) | C11: Seguimiento | D11: M1 | E11: Media | F11: 46234 | G11: En Proceso | I11: No | J11: Al realizar la descarga del consolidado de seguimiento se registra un desfase horario respecto a la hora en que efectivamente se realiza el registro de la acción. La plataforma tie
A12: SEG-8 | B12: Matriz de hallazgos (cliente) | C12: Seguimiento | D12: M1 | E12: Alta | F12: 46234 | G12: Cerrado | H12: 46294 | I12: Sí | J12: Lista de tareas de les agentes. No les aparece a los agentes de seguimiento (estaba oculta)
A13: SEG-9 | B13: Matriz de hallazgos (cliente) | C13: Seguimiento | D13: M1 | E13: Media | F13: 46234 | G13: Cerrado | H13: 46303 | I13: No | J13: Existe un limite de caracteres para los formularios de tareas, esto debe ampliarse
A14: SEG-10 | B14: Matriz de hallazgos (cliente) | C14: Seguimiento | D14: M1 | E14: Alta | F14: 46244 | G14: En Proceso | I14: Sí | J14: Antes de junio no deja descargar datos. Pendiente revisión de las variables por parte de Gestión del Conocimiento. El miércoles se envió correo.
A15: SEG-11 | B15: Matriz de hallazgos (cliente) | C15: Seguimiento | D15: M1 | E15: Media | F15: 46234 | G15: Cerrado | H15: 46294 | I15: No | J15: Limite de seguimientos
A16: SEG-12 | B16: Matriz de hallazgos (cliente) | C16: Seguimiento | D16: M1 | E16: Media | F16: 46244 | G16: Cerrado | H16: 46294 | I16: No | J16: LLave de busqueda de nombre
A17: SEG-13 | B17: Matriz de hallazgos (cliente) | C17: Seguimiento | D17: M1 | E17: Media | F17: 46244 | G17: Cerrado | H17: 46294 | I17: No | J17: Video enviado el 10-08 a las 7pm. No dejo registrar el + Nuevo por fecha
A18: SEG-14 | B18: Matriz de hallazgos (cliente) | C18: Seguimiento | D18: M1 | E18: Media | F18: 46248 | G18: En Proceso | I18: No | J18: El formulario no contiene información de los Excel y no se encuentra migrado un registro en Kobo que si se ubico. 1000118689
A19: SEG-15 | B19: Matriz de hallazgos (cliente) | C19: Seguimiento | D19: M1 | E19: Media | F19: 46248 | G19: Cerrado | H19: 46303 | I19: No | J19: Casos asignados a una agente no le permite regsitrar sus seguimientos. Esto se solucionó inicialmente con el "+ Nuevo Seguimiento". Ejemplo. Sara 1036644826 (sin seg) y 1075303225
A20: SEG-16 | B20: Matriz de hallazgos (cliente) | C20: Seguimiento | D20: M1 | E20: Alta | F20: 46248 | G20: Cerrado | H20: 46294 | I20: Sí | J20: Logro registrar caso sin registrar el seguimiento a barreras y tenia una barrera registrada previamente. Ver el seguimiento 2. 1030529554
A21: SEG-17 | B21: Matriz de hallazgos (cliente) | C21: Seguimiento | D21: M1 | E21: Alta | F21: 46248 | G21: En Proceso | I21: Sí | J21: No despliega Municipio ni departamento para registrar barrera. Lo reporto Andres Barboza. Adicionalmente, cuando uno va a consultar no permite ver esta información.
A22: SEG-21 | B22: Matriz de hallazgos (cliente) | C22: Seguimiento | D22: M1 | E22: Sin severidad | G22: Sin estado | I22: No | J22: Tampoco se visualiza el seguimiento a la barrera y parece que si se registro
A23: SEG-18 | B23: Matriz de hallazgos (cliente) | C23: Seguimiento | D23: M1 | E23: Media | F23: 46248 | G23: Cerrado | H23: 46294 | I23: No | J23: * En pruebas vi el formulario de registro de entidad y nos hace falta la pregunta u opción de que si la persona refiere que no desea activación aún asi en algunas ocasiones va a re
A24: SEG-19 | B24: Matriz de hallazgos (cliente) | C24: Seguimiento | D24: M1 | E24: Media | F24: 46248 | G24: En Proceso | I24: No | J24: Formulario de seguimiento - actualizarlo con el fin de cambiar algunas terminologias, incluir Salvia dignidad y la gestión del caso sin barreras.
A25: SEG-20 | B25: Matriz de hallazgos (cliente) | C25: Seguimiento | D25: M1 | E25: Media | F25: 46248 | G25: Cerrado | H25: 46294 | I25: No | J25: Cuenta con 7 intentos efectivos de contacto el mismo dia (09/06/2026), y no cuenta con ningun formulario de seguimientos registrado. CC 1070627387.
A26: SEG-21-b | B26: Matriz de hallazgos (cliente) | C26: Seguimiento | D26: M1 | E26: Media | F26: 46248 | G26: Cerrado | H26: 46294 | I26: No | J26: Funcionalidad de reapertura del caso.
A27: SEG-22 | B27: Matriz de hallazgos (cliente) | C27: Seguimiento | D27: M1 | E27: Media | F27: 46252 | G27: En Proceso | I27: No | J27: Los tiempos de seguimiento como recordatorio mas que como regla, me debe permitir registrar seguimientos en cualquier momento por la dinámica de los casos.
A28: SEG-23 | B28: Matriz de hallazgos (cliente) | C28: Seguimiento | D28: M1 | E28: Media | F28: 46259 | G28: Cerrado | H28: 46303 | I28: No | J28: Rol de Equipo técnico permite agendar tarea al de seguimiento y queda la trazabilidad de la gestión de esta.
A29: SEG-24 | B29: Matriz de hallazgos (cliente) | C29: Seguimiento | D29: M1 | E29: Media | F29: 46265 | G29: Cerrado | H29: 46303 | I29: No | J29: 1097990913 Ciudadana Liliana Gutierres, caso en el que se registran barreras pero no quedan tareas
A30: SEG-25 | B30: Matriz de hallazgos (cliente) | C30: Seguimiento | D30: M1 | E30: Media | F30: 46266 | G30: Abierto | I30: No | J30: Eliminar condicional de oficio de cierre. Cuando se realiza una conclusión del caso se generaba una tarea de oficio de cierre a todos los casos. Esta decisión es discrecional. No e
A31: SEG-26 | B31: Matriz de hallazgos (cliente) | C31: Seguimiento | D31: M1 | E31: Media | F31: 46267 | G31: Cerrado | H31: 46294 | I31: No | J31: En el nuevo boton de crear seguimiento, util, peroo.. envia de inmediato como si hubiera sido efectivo, es decir, se salta el 3x3
A32: SEG-27 | B32: Matriz de hallazgos (cliente) | C32: Seguimiento | D32: M1 | E32: Alta | F32: 46268 | G32: Cerrado | H32: 46303 | I32: Sí | J32: Agente Alcira entra a Mis Casos, y dentro de sus casos hay algunos que corresponden a otros agentes
A33: SEG-28 | B33: Matriz de hallazgos (cliente) | C33: Seguimiento | D33: M1 | E33: Baja | G33: Cerrado | H33: 46294 | I33: No | J33: Cambio de derivaciones por atención SALVIA y colocar intervenientes
A34: SEG-29 | B34: Matriz de hallazgos (cliente) | C34: Seguimiento | D34: M1 | E34: Media | G34: Cerrado | H34: 46294 | I34: No | J34: Cada proceso debe ir al detalle de gestion de cada profesional
A35: SEG-30 | B35: Matriz de hallazgos (cliente) | C35: Seguimiento | D35: M1 | E35: Media | F35: 46283 | G35: Cerrado | H35: 46294 | I35: No | J35: Orden con las fechas de seguimiento (en el orden en el que se realizan la acción).
A36: SEG-31 | B36: Matriz de hallazgos (cliente) | C36: Seguimiento | D36: M1 | E36: Media | F36: 46283 | G36: Cerrado | H36: 46294 | I36: No | J36: Los seguimientos que no se realicen a tiempo, deben marcarse como "No realizo - vencido". Suprimir el número, el número debe corresponder a los efectivos
A37: SEG-32 | B37: Matriz de hallazgos (cliente) | C37: Seguimiento | D37: M1 | E37: Media | F37: 46283 | G37: En Proceso | I37: No | J37: Agregar botón (lista desplegable) en el módulo de barreras (sección identificación de barreras). Y de aquí en adelante, en todas las secciones que tengan más de tres opciones de r
A38: SEG-33 | B38: Matriz de hallazgos (cliente) | C38: Seguimiento | D38: M1 | E38: Media | F38: 46283 | G38: Cerrado | H38: 46294 | I38: No | J38: En la sección "identificación de barreras" ciudad, municipio y entidades no sale lo que se guarda en el formulario. No arrastra la info
A39: SEG-34 | B39: Matriz de hallazgos (cliente) | C39: Seguimiento | D39: M1 | E39: Media | F39: 46283 | G39: Cerrado | H39: 46294 | I39: No | J39: El botón "reabrir" casos debe ser asociado a los roles de supervisión. Debe incluirse un cajón para explicar la razón de reapertura.
A40: SEG-35 | B40: Matriz de hallazgos (cliente) | C40: Seguimiento | D40: M1 | E40: Media | F40: 46283 | G40: Cerrado | H40: 46303 | I40: No | J40: Si se intenta alguna acción con un caso cerrado, se debe generar una alerta de la imposibilidad de hacerlo por su estado "cerrado", por ejemplo, entrar al formulario de seguimiento
A41: SEG-36 | B41: Matriz de hallazgos (cliente) | C41: Seguimiento | D41: M1 | E41: Media | F41: 46283 | G41: En Proceso | I41: No | J41: Revisar DIVIPOLA para municipio y centro poblado. Donde dice Ciudad, debe decir municipio y donde dice municipio, son centros poblados. Están bien los desplegables, corregir los tí
A42: SEG-37 | B42: Matriz de hallazgos (cliente) | C42: Seguimiento | D42: M1 | E42: Media | F42: 46283 | G42: En Proceso | I42: No | J42: Asociar la entidad al DIVIPOLA
A43: SEG-38 | B43: Matriz de hallazgos (cliente) | C43: Seguimiento | D43: M1 | E43: Media | F43: 46283 | G43: En Proceso | I43: No | J43: Registrar la barrera al mismo tiempo que se registra la entidad.
A44: SEG-39 | B44: Matriz de hallazgos (cliente) | C44: Seguimiento | D44: M1 | E44: Media | F44: 46283 | G44: Cerrado | H44: 46303 | I44: No | J44: En la sección "Conclusión del ciclo de atención" eliminar "indique las gestiones institucionales ..."
A45: SEG-40 | B45: Matriz de hallazgos (cliente) | C45: Seguimiento | D45: M1 | E45: Media | F45: 46283 | G45: Cerrado | H45: 46303 | I45: No | J45: Orden de seguimiento:
A46: SEG-45 | B46: Matriz de hallazgos (cliente) | C46: Seguimiento | D46: M1 | E46: Sin severidad | G46: Sin estado | I46: No | J46: Valoración del riesgo
A47: SEG-46 | B47: Matriz de hallazgos (cliente) | C47: Seguimiento | D47: M1 | E47: Sin severidad | G47: Sin estado | I47: No | J47: Identificación de entidades
A48: SEG-47 | B48: Matriz de hallazgos (cliente) | C48: Seguimiento | D48: M1 | E48: Sin severidad | G48: Sin estado | I48: No | J48: Seguimiento a entidades
A49: SEG-48 | B49: Matriz de hallazgos (cliente) | C49: Seguimiento | D49: M1 | E49: Sin severidad | G49: Sin estado | I49: No | J49: Identificación de barreras
A50: SEG-49 | B50: Matriz de hallazgos (cliente) | C50: Seguimiento | D50: M1 | E50: Sin severidad | G50: Sin estado | I50: No | J50: Seguimiento a barreras
A51: SEG-50 | B51: Matriz de hallazgos (cliente) | C51: Seguimiento | D51: M1 | E51: Sin severidad | G51: Sin estado | I51: No | J51: Seguimiento de caso
A52: SEG-51 | B52: Matriz de hallazgos (cliente) | C52: Seguimiento | D52: M1 | E52: Sin severidad | G52: Sin estado | I52: No | J52: Conclusión del ciclo de atención
A53: SEG-41 | B53: Matriz de hallazgos (cliente) | C53: Seguimiento | D53: M1 | E53: Media | F53: 46283 | G53: Cerrado | H53: 46303 | I53: No | J53: En la pestaña "Derivaciones", del apartado "profesionales de atención" no es necesario ver "Notas".
A54: SEG-42 | B54: Matriz de hallazgos (cliente) | C54: Seguimiento | D54: M1 | E54: Crítica | F54: 46290 | G54: Abierto | I54: Sí | J54: Se realiza el diligenciamiento de un formulario de seguimiento de los siguientes casos con el fin de probar Notificaciones, para esto se realizó el registro y ademas se seleccionar
A55: SEG-43 | B55: Matriz de hallazgos (cliente) | C55: Seguimiento | D55: M1 | E55: Crítica | F55: 46291 | G55: Abierto | I55: Sí | J55: Contrario al anterior, Brayan, con usuaio de agente integral, registro un seguimiento de este caso 1095942131, al registrarlo selecciono que realizó orientación, sin embargo, el si
A56: PSI-1 | B56: Matriz de hallazgos (cliente) | C56: Psicosocial | D56: M1 | E56: Media | F56: 46258 | G56: Cerrado | H56: 46303 | I56: No | J56: No aparece la opción "Psicosocial" en filtro "por equipos"
A57: PSI-2 | B57: Matriz de hallazgos (cliente) | C57: Psicosocial | D57: M1 | E57: Media | F57: 46258 | G57: Cerrado | H57: 46295 | I57: No | J57: Agregar opcion "administrar profesionales" para usuario de coordinación
A58: PSI-3 | B58: Matriz de hallazgos (cliente) | C58: Psicosocial | D58: M1 | E58: Media | F58: 46258 | G58: Cerrado | H58: 46295 | I58: No | J58: No aparecen las duplas para la asignación de casos de acuerdo a las profesionales en dupla diponibles
A59: PSI-4 | B59: Matriz de hallazgos (cliente) | C59: Psicosocial | D59: M1 | E59: Baja | F59: 46989 | G59: Cerrado | H59: 46303 | I59: No | J59: cambiar en creación de Duplas "Psicologa" por "profesionale en Psicología" y "Trabajadora social" por "profesional en Trabajo Social"
A60: PSI-5 | B60: Matriz de hallazgos (cliente) | C60: Psicosocial | D60: M1 | E60: Baja | F60: 46258 | G60: Cerrado | H60: 46295 | I60: No | J60: Aparece el término "paciente" y no cuidadana.
A61: PSI-6 | B61: Matriz de hallazgos (cliente) | C61: Psicosocial | D61: M1 | E61: Baja | F61: 46258 | G61: Cerrado | H61: 46303 | I61: No | J61: Aparece el término "psicóloga" y no profesional psicosocial.
A62: PSI-5-b | B62: Matriz de hallazgos (cliente) | C62: Psicosocial | D62: M1 | E62: Media | F62: 46258 | G62: Cerrado | H62: 46303 | I62: No | J62: Se registra de manera erronea la profesión de las Trabajadoras Sociales, aparece "psicóloga".
A63: PSI-8 | B63: Matriz de hallazgos (cliente) | C63: Psicosocial | D63: M1 | E63: Baja | F63: 46258 | G63: Cerrado | H63: 46295 | I63: No | J63: Aparece el término "sesión" y no atención.
A64: PSI-9 | B64: Matriz de hallazgos (cliente) | C64: Psicosocial | D64: M1 | E64: Alta | F64: 46258 | G64: Cerrado | H64: 46303 | I64: Sí | J64: Consentimiento informado está incompleto.
A65: PSI-10 | B65: Matriz de hallazgos (cliente) | C65: Psicosocial | D65: M1 | E65: Alta | F65: 46258 | G65: Cerrado | H65: 46303 | I65: Sí | J65: Consentimiento de la persona de apoyo aparece como obligatorio, éste no debe ser un item obligatorio. ya que no se realiza en todos los casos.
A66: PSI-11 | B66: Matriz de hallazgos (cliente) | C66: Psicosocial | D66: M1 | E66: Alta | F66: 46989 | G66: Cerrado | H66: 46303 | I66: Sí | J66: EL consentimiento informado debe aparecer solo en la primera atención.
A67: PSI-12 | B67: Matriz de hallazgos (cliente) | C67: Psicosocial | D67: M1 | E67: Alta | F67: 46258 | G67: Abierto | I67: Sí | J67: El caso asignado para Jose Felipe Calixto identificado con C.C1014223917 se triplica en la base de remisiones.
A68: PSI-13 | B68: Matriz de hallazgos (cliente) | C68: Psicosocial | D68: M1 | E68: Alta | F68: 46258 | G68: En Proceso | I68: Sí | J68: En la pestaña de Directorio de entidades no filtra las instituciones que uno busca por departamento - ciudad (EJ: se buscó comisarias de Bogotá sin resultado alguno)
A69: PSI-14 | B69: Matriz de hallazgos (cliente) | C69: Psicosocial | D69: M1 | E69: Alta | F69: 46258 | G69: En Proceso | I69: Sí | J69: En la plataforma de remisión de casos, pestaña "Registrar Intentos": si la persona contesta y valida el consentimiento informado, seleccionar "De inmediato" en la pregunta ¿Cuándo
A70: PSI-15 | B70: Matriz de hallazgos (cliente) | C70: Psicosocial | D70: M1 | E70: Media | F70: 46258 | G70: Abierto | I70: No | J70: En primera atención al continuar solicita información de barreras y anteriormente se habia marcado que NO.
A71: PSI-16 | B71: Matriz de hallazgos (cliente) | C71: Psicosocial | D71: M1 | E71: Media | F71: 46258 | G71: Abierto | I71: No | J71: El seguimiento que aparece en el calendario no deriva directo al seguimiento.
A72: PSI-17 | B72: Matriz de hallazgos (cliente) | C72: Psicosocial | D72: M1 | E72: Media | F72: 46258 | G72: En Proceso | I72: No | J72: Cuando se elige "proxima atención" y se despliega el calendario, al seleccionar el calendario aparece que no hay disponibilidad. Que hay algo agendado.
A73: PSI-18 | B73: Matriz de hallazgos (cliente) | C73: Psicosocial | D73: M1 | E73: Media | F73: 46258 | G73: En Proceso | I73: No | J73: 53074151 - No permite visualizar el formulario de atenciones impares
A74: PSI-19 | B74: Matriz de hallazgos (cliente) | C74: Psicosocial | D74: M1 | E74: Media | F74: 46258 | G74: Cerrado | H74: 46295 | I74: No | J74: No permite avanzar del formulario de registrar barreras al de Primera atención - 3134914154
A75: PSI-20 | B75: Matriz de hallazgos (cliente) | C75: Psicosocial | D75: M1 | E75: Media | F75: 46258 | G75: Cerrado | H75: 46295 | I75: No | J75: En Derivaciones registrar el campo de Observaciones del fomrulario para que sea visible al analisis del caso.
A76: PSI-21 | B76: Matriz de hallazgos (cliente) | C76: Psicosocial | D76: M1 | E76: Media | F76: 46273 | G76: Cerrado | H76: 46295 | I76: No | J76: no permite crear profesionales ni duplas para la atención (en rol coordinación), por tanto no permite la asignación de casos, agregar botón administrar profesionales
A77: PSI-22 | B77: Matriz de hallazgos (cliente) | C77: Psicosocial | D77: M1 | E77: Alta | F77: 46273 | G77: Cerrado | H77: 46295 | I77: Sí | J77: Corregir en "administrar duplas": Cada profesional en Psicología puede pertenecer a una sola dupla; cada profesional en Trabajo Social puede puede pertenecer a una sola dupla. Dad
A78: PSI-23 | B78: Matriz de hallazgos (cliente) | C78: Psicosocial | D78: M1 | E78: Baja | F78: 46273 | G78: Cerrado | H78: 46295 | I78: No | J78: en agenda el dia viernes aparece como "rivalizar"
A79: PSI-24 | B79: Matriz de hallazgos (cliente) | C79: Psicosocial | D79: M1 | E79: Media | F79: 47004 | G79: Cerrado | H79: 46303 | I79: No | J79: no permite en rol de coordinación ver las agendas de las profesionales psicosociales
A80: PSI-25 | B80: Matriz de hallazgos (cliente) | C80: Psicosocial | D80: M1 | E80: Media | F80: 47369 | G80: Cerrado | H80: 46303 | I80: No | J80: no permite en rol de coordinación filtrar por número de documento
A81: PSI-26 | B81: Matriz de hallazgos (cliente) | C81: Psicosocial | D81: M1 | E81: Alta | F81: 47734 | G81: Cerrado | H81: 46303 | I81: Sí | J81: en el rol de psicosocial no esta la opción lista de casos, por lo que no permite la consulta de casos previamente asignados al despliegue
A82: PSI-27 | B82: Matriz de hallazgos (cliente) | C82: Psicosocial | D82: M1 | E82: Media | F82: 46274 | G82: Cerrado | H82: 46295 | I82: No | J82: Solo en algunos casos sale la información de cúal equipo y profesional esta remitiendo.
A83: PSI-28 | B83: Matriz de hallazgos (cliente) | C83: Psicosocial | D83: M1 | E83: Baja | F83: 46274 | G83: Cerrado | H83: 46295 | I83: No | J83: En el apartado de la información de la remisión, aparece "🔒 Preferencia de horario de la cuidadora (solo equipo psicosocial)" Cambiar la palabra cuidadora, por "ciudadana"
A84: PSI-29 | B84: Matriz de hallazgos (cliente) | C84: Psicosocial | D84: M1 | E84: Alta | F84: 46276 | G84: Cerrado | H84: 46295 | I84: Sí | J84: No permite realizar devolución de los casos asignados.
A85: PSI-30 | B85: Matriz de hallazgos (cliente) | C85: Psicosocial | D85: M1 | E85: Media | F85: 46276 | G85: En Proceso | I85: No | J85: Al consultar posteriormente la información del caso, se evidencia que el sistema Salvia no refleja de manera adecuada la información registrada durante los intentos de contacto, es
A86: PSI-31 | B86: Matriz de hallazgos (cliente) | C86: Psicosocial | D86: M1 | E86: Alta | F86: 46276 | G86: En Proceso | I86: Sí | J86: Al finalizar el registro de los intentos de contacto, el sistema Salvia no habilita la opción para realizar el cierre del caso, aun cuando ya se cuenta con la información necesaria
A87: PSI-32 | B87: Matriz de hallazgos (cliente) | C87: Psicosocial | D87: M1 | E87: Alta | F87: 46280 | G87: Cerrado | H87: 46303 | I87: Sí | J87: No aparece la opción de validar para recepcionar el caso con C.C. 1002595679
A88: PSI-33 | B88: Matriz de hallazgos (cliente) | C88: Psicosocial | D88: M1 | E88: Alta | F88: 46280 | G88: Cerrado | H88: 46303 | I88: Sí | J88: No aparece la opción de validar para recepcionar / devolver el caso con C.C. 1080292921
A89: PSI-34 | B89: Matriz de hallazgos (cliente) | C89: Psicosocial | D89: M1 | E89: Alta | F89: 46280 | G89: Cerrado | H89: 46303 | I89: Sí | J89: No aparece la opción de validar para recepcionar / devolver el caso con C.C. 52281134
A90: PSI-35 | B90: Matriz de hallazgos (cliente) | C90: Psicosocial | D90: M1 | E90: Alta | F90: 46280 | G90: Cerrado | H90: 46303 | I90: Sí | J90: No aparece la opción de validar para recepcionar / devolver el caso con CC: 1067596642
A91: PSI-36 | B91: Matriz de hallazgos (cliente) | C91: Psicosocial | D91: M1 | E91: Alta | F91: 46280 | G91: Cerrado | H91: 46303 | I91: Sí | J91: No aparece la opción de validar para recepcionar / devolver el caso con CC: 1144136810
A92: PSI-37 | B92: Matriz de hallazgos (cliente) | C92: Psicosocial | D92: M1 | E92: Alta | F92: 46280 | G92: Cerrado | H92: 46303 | I92: Sí | J92: No aparece la opción de validar para recepcionar / devolver el caso con CC: 1006596731
A93: PSI-38 | B93: Matriz de hallazgos (cliente) | C93: Psicosocial | D93: M1 | E93: Alta | F93: 46280 | G93: Cerrado | H93: 46303 | I93: Sí | J93: No aparece la opción de validar para recepcionar / devolver el caso con CC: 1093795028
A94: PSI-39 | B94: Matriz de hallazgos (cliente) | C94: Psicosocial | D94: M1 | E94: Alta | F94: 46280 | G94: Cerrado | H94: 46303 | I94: Sí | J94: No aparece la opción de validar para recepcionar / devolver el caso con cc: 1022944966
A95: PSI-40 | B95: Matriz de hallazgos (cliente) | C95: Psicosocial | D95: M1 | E95: Alta | F95: 46281 | G95: Cerrado | H95: 46303 | I95: Sí | J95: No aparece la opción de validar para recepcionar / devolver el caso con cc: 1035433565
A96: PSI-41 | B96: Matriz de hallazgos (cliente) | C96: Psicosocial | D96: M1 | E96: Alta | F96: 46281 | G96: Cerrado | H96: 46303 | I96: Sí | J96: No aparece la opción de validar para recepcionar el caso con cc: 29360591
A97: PSI-42 | B97: Matriz de hallazgos (cliente) | C97: Psicosocial | D97: M1 | E97: Alta | F97: 46281 | G97: Cerrado | H97: 46303 | I97: Sí | J97: No aparece el consentimiento informado, aparece "texto de prueba"
A98: PSI-43 | B98: Matriz de hallazgos (cliente) | C98: Psicosocial | D98: M1 | E98: Alta | F98: 46281 | G98: Abierto | I98: Sí | J98: Se llena el contenido de la primera ateción a la ciudadana CC: 42143519. Sin embargo en SALVIA aparecen 2 registros, además cuenta 4 atenciones de 6 (pero la ciudadana solo lleva u
A99: PSI-44 | B99: Matriz de hallazgos (cliente) | C99: Psicosocial | D99: M1 | E99: Baja | F99: 46281 | G99: Cerrado | H99: 46303 | I99: No | J99: El apellido de la profesional identificada con cédula 1000832586 es Quimbay, no Kimbay.
A100: PSI-45 | B100: Matriz de hallazgos (cliente) | C100: Psicosocial | D100: M1 | E100: Alta | F100: 46281 | G100: Cerrado | H100: 46303 | I100: Sí | J100: No aparece la opción de validar para recepcionar el caso con cc: 1053803128
...
